Workbook

Sheet Mom's Portfolio
A1: Phantom wallet 5 (starting with $9000)
A2: USDC vault
A3: Jito/SOL
A4: SOL vault
A6: All of them on Kamino for now.

Sheet Baskets
A1: Drone Basket
A2: Company | B2: Price | C2: Number of shares | D2: Value | E2: Employees | F2: MarketCap | G2: P/E | H2: Beta | I2: Marketcap per employee | J2: Share of portfolio
A3: #VALUE! | B3: {=_FV(A3,"Price")} -> 16.05 | C3: 88.731145 | D3: =IFERROR(Table1[[#This Row],[Price]]*Table1[[#This Row],[Number of shares]],0) -> 1424.1349 | E3: {=_FV(Table1[[#This Row],[Company]],"Employees")} -> 115 | F3: {=_FV(Table1[[#This Row],[Company]],"Market cap",TRUE)} -> 1944277740 | G3: {=_FV(Table1[[#This Row],[Company]],"P/E",TRUE)} -> 0 | H3: {=_FV(Table1[[#This Row],[Company]],"Beta")} -> 1.2419 | I3: =Table1[[#This Row],[MarketCap]]/Table1[[#This Row],[Employees]] -> 16906763 | J3: =Table1[[#This Row],[Value]] / SUM(Table1[Value]) -> 0.091773127
A4: #VALUE! | B4: {=_FV(A4,"Price")} -> 71.38 | C4: 24.931439 | D4: =IFERROR(Table1[[#This Row],[Price]]*Table1[[#This Row],[Number of shares]],0) -> 1779.6061 | E4: {=_FV(Table1[[#This Row],[Company]],"Employees")} -> 226 | F4: {=_FV(Table1[[#This Row],[Company]],"Market cap",TRUE)} -> 250688701 | G4: {=_FV(Table1[[#This Row],[Company]],"P/E",TRUE)} -> 29.8025 | H4: {=_FV(Table1[[#This Row],[Company]],"Beta")} -> 0.6598 | I4: =Table1[[#This Row],[MarketCap]]/Table1[[#This Row],[Employees]] -> 1109242 | J4: =Table1[[#This Row],[Value]] / SUM(Table1[Value]) -> 0.11468016
A5: #VALUE! | B5: {=_FV(A5,"Price")} -> 14.73 | C5: 91.99632 | D5: =IFERROR(Table1[[#This Row],[Price]]*Table1[[#This Row],[Number of shares]],0) -> 1355.1058 | E5: {=_FV(Table1[[#This Row],[Company]],"Employees")} -> 141 | F5: {=_FV(Table1[[#This Row],[Company]],"Market cap",TRUE)} -> 703866421 | G5: {=_FV(Table1[[#This Row],[Company]],"P/E",TRUE)} -> #VALUE! | H5: {=_FV(Table1[[#This Row],[Company]],"Beta")} -> 3.338 | I5: =Table1[[#This Row],[MarketCap]]/Table1[[#This Row],[Employees]] -> 4991960.4 | J5: =Table1[[#This Row],[Value]] / SUM(Table1[Value]) -> 0.087324802
A6: #VALUE! | B6: {=_FV(A6,"Price")} -> 201.62 | C6: 3.6492355 | D6: =IFERROR(Table1[[#This Row],[Price]]*Table1[[#This Row],[Number of shares]],0) -> 735.75886 | E6: {=_FV(Table1[[#This Row],[Company]],"Employees")} -> 1456 | F6: {=_FV(Table1[[#This Row],[Company]],"Market cap",TRUE)} -> 10202994213 | G6: {=_FV(Table1[[#This Row],[Company]],"P/E",TRUE)} -> 0 | H6: {=_FV(Table1[[#This Row],[Company]],"Beta")} -> 1.3456 | I6: =Table1[[#This Row],[MarketCap]]/Table1[[#This Row],[Employees]] -> 7007551 | J6: =Table1[[#This Row],[Value]] / SUM(Table1[Value]) -> 0.04741327
A7: #VALUE! | B7: {=_FV(A7,"Price")} -> 78.195 | C7: 16.91475 | D7: =IFERROR(Table1[[#This Row],[Price]]*Table1[[#This Row],[Number of shares]],0) -> 1322.6488 | E7: {=_FV(Table1[[#This Row],[Company]],"Employees")} -> 4300 | F7: {=_FV(Table1[[#This Row],[Company]],"Market cap",TRUE)} -> 14603518351 | G7: {=_FV(Table1[[#This Row],[Company]],"P/E",TRUE)} -> 594.6388 | H7: {=_FV(Table1[[#This Row],[Company]],"Beta")} -> 1.1771 | I7: =Table1[[#This Row],[MarketCap]]/Table1[[#This Row],[Employees]] -> 3396167.1 | J7: =Table1[[#This Row],[Value]] / SUM(Table1[Value]) -> 0.085233234
A8: #VALUE! | B8: {=_FV(A8,"Price")} -> 10.6 | C8: 448.43049 | D8: =IFERROR(Table1[[#This Row],[Price]]*Table1[[#This Row],[Number of shares]],0) -> 4753.3632 | E8: {=_FV(Table1[[#This Row],[Company]],"Employees")} -> 113 | F8: {=_FV(Table1[[#This Row],[Company]],"Market cap",TRUE)} -> 4943604680 | G8: {=_FV(Table1[[#This Row],[Company]],"P/E",TRUE)} -> 0 | H8: {=_FV(Table1[[#This Row],[Company]],"Beta")} -> 2.5151 | I8: =Table1[[#This Row],[MarketCap]]/Table1[[#This Row],[Employees]] -> 43748714 | J8: =Table1[[#This Row],[Value]] / SUM(Table1[Value]) -> 0.30631299
A9: #VALUE! | B9: {=_FV(A9,"Price")} -> 45.11 | C9: 20.777062 | D9: =IFERROR(Table1[[#This Row],[Price]]*Table1[[#This Row],[Number of shares]],0) -> 937.25327 | E9: {=_FV(Table1[[#This Row],[Company]],"Employees")} -> 7300 | F9: {=_FV(Table1[[#This Row],[Company]],"Market cap",TRUE)} -> 11991248464 | G9: {=_FV(Table1[[#This Row],[Company]],"P/E",TRUE)} -> 43.5845 | H9: {=_FV(Table1[[#This Row],[Company]],"Beta")} -> 0.4389 | I9: =Table1[[#This Row],[MarketCap]]/Table1[[#This Row],[Employees]] -> 1642636.8 | J9: =Table1[[#This Row],[Value]] / SUM(Table1[Value]) -> 0.060397835
A10: #VALUE! | B10: {=_FV(A10,"Price")} -> 628.345 | C10: 1.7741191 | D10: =IFERROR(Table1[[#This Row],[Price]]*Table1[[#This Row],[Number of shares]],0) -> 1114.7589 | E10: {=_FV(Table1[[#This Row],[Company]],"Employees")} -> 15800 | F10: {=_FV(Table1[[#This Row],[Company]],"Market cap",TRUE)} -> 29103231301 | G10: {=_FV(Table1[[#This Row],[Company]],"P/E",TRUE)} -> 33.2852 | H10: {=_FV(Table1[[#This Row],[Company]],"Beta")} -> 0.9929 | I10: =Table1[[#This Row],[MarketCap]]/Table1[[#This Row],[Employees]] -> 1841976.7 | J10: =Table1[[#This Row],[Value]] / SUM(Table1[Value]) -> 0.071836532
A11: #VALUE! | B11: {=_FV(A11,"Price")} -> 907.23 | C11: 2.3096288 | D11: =IFERROR(Table1[[#This Row],[Price]]*Table1[[#This Row],[Number of shares]],0) -> 2095.3646 | E11: {=_FV(Table1[[#This Row],[Company]],"Employees")} -> 19712 | F11: {=_FV(Table1[[#This Row],[Company]],"Market cap",TRUE)} -> 102027000000 | G11: {=_FV(Table1[[#This Row],[Company]],"P/E",TRUE)} -> 90.4374 | H11: {=_FV(Table1[[#This Row],[Company]],"Beta")} -> 0.4644 | I11: =Table1[[#This Row],[MarketCap]]/Table1[[#This Row],[Employees]] -> 5175882.7 | J11: =Table1[[#This Row],[Value]] / SUM(Table1[Value]) -> 0.13502805
A13: (BATS:RCAT*88+BATS:MPTI*25+BATS:UMAC*92+BATS:AVAV*3.64+BATS:KTOS*17+BATS:ONDS*448+BATS:DRS*20.77+BATS:TDY*1.77+BATS:ESLT*2.3)/BATS:SPY
A15: Robotics Basket
A16: Company | B16: Price | C16: Number of shares | D16: Value | E16: Employees | F16: MarketCap | G16: P/E | H16: Beta | I16: Marketcap per employee | J16: Share of Portfolio
A17: #VALUE! | B17: {=_FV(A17,"Price")} -> 212.15 | C17: 5 | D17: =IFERROR(Table13[[#This Row],[Price]]*Table13[[#This Row],[Number of shares]],0) -> 1060.75 | E17: {=_FV(Table13[[#This Row],[Company]],"Employees")} -> 1576000 | F17: {=_FV(Table13[[#This Row],[Company]],"Market cap",TRUE)} -> 2277413278000 | G17: {=_FV(Table13[[#This Row],[Company]],"P/E",TRUE)} -> 29.5795 | H17: {=_FV(Table13[[#This Row],[Company]],"Beta")} -> 1.3909 | I17: =Table13[[#This Row],[MarketCap]]/Table13[[#This Row],[Employees]] -> 1445059.2 | J17: =Table13[[#This Row],[Value]] / SUM(Table13[Value]) -> 0.079259581
A18: #VALUE! | B18: {=_FV(A18,"Price")} -> 323.46 | C18: 11 | D18: =IFERROR(Table13[[#This Row],[Price]]*Table13[[#This Row],[Number of shares]],0) -> 3558.06 | E18: {=_FV(Table13[[#This Row],[Company]],"Employees")} -> 6600 | F18: {=_FV(Table13[[#This Row],[Company]],"Market cap",TRUE)} -> 50639603760 | G18: {=_FV(Table13[[#This Row],[Company]],"P/E",TRUE)} -> 92.8682 | H18: {=_FV(Table13[[#This Row],[Company]],"Beta")} -> 1.7619 | I18: =Table13[[#This Row],[MarketCap]]/Table13[[#This Row],[Employees]] -> 7672667.2 | J18: =Table13[[#This Row],[Value]] / SUM(Table13[Value]) -> 0.26585939
A19: #VALUE! | B19: {=_FV(A19,"Price")} -> 63.68 | C19: 17 | D19: =IFERROR(Table13[[#This Row],[Price]]*Table13[[#This Row],[Number of shares]],0) -> 1082.56 | E19: {=_FV(Table13[[#This Row],[Company]],"Employees")} -> 22600 | F19: {=_FV(Table13[[#This Row],[Company]],"Market cap",TRUE)} -> 25091225440 | G19: {=_FV(Table13[[#This Row],[Company]],"P/E",TRUE)} -> 192.2125 | H19: {=_FV(Table13[[#This Row],[Company]],"Beta")} -> 1.5247 | I19: =Table13[[#This Row],[MarketCap]]/Table13[[#This Row],[Employees]] -> 1110231.2 | J19: =Table13[[#This Row],[Value]] / SUM(Table13[Value]) -> 0.080889232
A20: #VALUE! | B20: {=_FV(A20,"Price")} -> 9.77 | C20: 149 | D20: =IFERROR(Table13[[#This Row],[Price]]*Table13[[#This Row],[Number of shares]],0) -> 1455.73 | E20: {=_FV(Table13[[#This Row],[Company]],"Employees")} -> 190 | F20: {=_FV(Table13[[#This Row],[Company]],"Market cap",TRUE)} -> 2254845656 | G20: {=_FV(Table13[[#This Row],[Company]],"P/E",TRUE)} -> 0 | H20: {=_FV(Table13[[#This Row],[Company]],"Beta")} -> 3.1239 | I20: =Table13[[#This Row],[MarketCap]]/Table13[[#This Row],[Employees]] -> 11867609 | J20: =Table13[[#This Row],[Value]] / SUM(Table13[Value]) -> 0.10877261
A21: #VALUE! | B21: {=_FV(A21,"Price")} -> 3.2 | C21: 220 | D21: =IFERROR(Table13[[#This Row],[Price]]*Table13[[#This Row],[Number of shares]],0) -> 704 | E21: {=_FV(Table13[[#This Row],[Company]],"Employees")} -> 800 | F21: {=_FV(Table13[[#This Row],[Company]],"Market cap",TRUE)} -> 715714240 | G21: {=_FV(Table13[[#This Row],[Company]],"P/E",TRUE)} -> 0 | H21: {=_FV(Table13[[#This Row],[Company]],"Beta")} -> 2.6059 | I21: =Table13[[#This Row],[MarketCap]]/Table13[[#This Row],[Employees]] -> 894642.8 | J21: =Table13[[#This Row],[Value]] / SUM(Table13[Value]) -> 0.052603107
A22: #VALUE! | B22: {=_FV(A22,"Price")} -> 290.39 | C22: 6 | D22: =IFERROR(Table13[[#This Row],[Price]]*Table13[[#This Row],[Number of shares]],0) -> 1742.34 | E22: {=_FV(Table13[[#This Row],[Company]],"Employees")} -> 190820 | F22: {=_FV(Table13[[#This Row],[Company]],"Market cap",TRUE)} -> 3512847830000 | G22: {=_FV(Table13[[#This Row],[Company]],"P/E",TRUE)} -> 26.9032 | H22: {=_FV(Table13[[#This Row],[Company]],"Beta")} -> 1.1251 | I22: =Table13[[#This Row],[MarketCap]]/Table13[[#This Row],[Employees]] -> 18409222 | J22: =Table13[[#This Row],[Value]] / SUM(Table13[Value]) -> 0.13018821
A23: #VALUE! | B23: {=_FV(A23,"Price")} -> 44.77 | C23: 40 | D23: =IFERROR(Table13[[#This Row],[Price]]*Table13[[#This Row],[Number of shares]],0) -> 1790.8 | E23: {=_FV(Table13[[#This Row],[Company]],"Employees")} -> 2100 | F23: {=_FV(Table13[[#This Row],[Company]],"Market cap",TRUE)} -> 595325045 | G23: {=_FV(Table13[[#This Row],[Company]],"P/E",TRUE)} -> 112.8845 | H23: {=_FV(Table13[[#This Row],[Company]],"Beta")} -> 0.9019 | I23: =Table13[[#This Row],[MarketCap]]/Table13[[#This Row],[Employees]] -> 283488.12 | J23: =Table13[[#This Row],[Value]] / SUM(Table13[Value]) -> 0.13380915
A24: #VALUE! | B24: {=_FV(A24,"Price")} -> 36.84 | C24: 35 | D24: =IFERROR(Table13[[#This Row],[Price]]*Table13[[#This Row],[Number of shares]],0) -> 1289.4 | E24: {=_FV(Table13[[#This Row],[Company]],"Employees")} -> 16700 | F24: {=_FV(Table13[[#This Row],[Company]],"Market cap",TRUE)} -> 5371253580 | G24: {=_FV(Table13[[#This Row],[Company]],"P/E",TRUE)} -> 184.847 | H24: {=_FV(Table13[[#This Row],[Company]],"Beta")} -> 1.1191 | I24: =Table13[[#This Row],[MarketCap]]/Table13[[#This Row],[Employees]] -> 321631.95 | J24: =Table13[[#This Row],[Value]] / SUM(Table13[Value]) -> 0.096344383
A25: #VALUE! | B25: {=_FV(A25,"Price")} -> 21.2 | C25: 33 | D25: =IFERROR(Table13[[#This Row],[Price]]*Table13[[#This Row],[Number of shares]],0) -> 699.6 | E25: {=_FV(Table13[[#This Row],[Company]],"Employees")} -> 320 | F25: {=_FV(Table13[[#This Row],[Company]],"Market cap",TRUE)} -> 1331444588 | G25: {=_FV(Table13[[#This Row],[Company]],"P/E",TRUE)} -> 0 | H25: {=_FV(Table13[[#This Row],[Company]],"Beta")} -> 2.934 | I25: =Table13[[#This Row],[MarketCap]]/Table13[[#This Row],[Employees]] -> 4160764.3 | J25: =Table13[[#This Row],[Value]] / SUM(Table13[Value]) -> 0.052274337
A27: (NASDAQ:AMZN*5+NASDAQ:TER*11+NASDAQ:ON*17+NASDAQ:NVTS*149+NASDAQ:INDI*220+NASDAQ:GOOG*6+NYSE:VPG*40+NYSE:ST*35+NASDAQ:OUST*33)/AMEX:SPY
A29: SemiConductors
A30: Company | B30: Price | C30: Number of shares | D30: Value | E30: Employees | F30: MarketCap | G30: P/E | H30: Beta | I30: Marketcap per employee | J30: Share of Portfolio
A31: #VALUE! | B31: {=_FV(A31,"Price")} -> 100.285 | C31: 5 | D31: =IFERROR(Table134[[#This Row],[Price]]*Table134[[#This Row],[Number of shares]],0) -> 501.425 | E31: {=_FV(Table134[[#This Row],[Company]],"Employees")} -> 1174 | F31: {=_FV(Table134[[#This Row],[Company]],"Market cap",TRUE)} -> 13725947779 | G31: {=_FV(Table134[[#This Row],[Company]],"P/E",TRUE)} -> 4497.0852 | H31: {=_FV(Table134[[#This Row],[Company]],"Beta")} -> 1.629 | I31: =Table134[[#This Row],[MarketCap]]/Table134[[#This Row],[Employees]] -> 11691608 | J31: =Table134[[#This Row],[Value]] / SUM(Table134[Value]) -> 0.0055398515
A32: #VALUE! | B32: {=_FV(A32,"Price")} -> 47.2901 | C32: 11 | D32: =IFERROR(Table134[[#This Row],[Price]]*Table134[[#This Row],[Number of shares]],0) -> 520.1911 | E32: {=_FV(Table134[[#This Row],[Company]],"Employees")} -> 85100 | F32: {=_FV(Table134[[#This Row],[Company]],"Market cap",TRUE)} -> 237444065001 | G32: {=_FV(Table134[[#This Row],[Company]],"P/E",TRUE)} -> 0 | H32: {=_FV(Table134[[#This Row],[Company]],"Beta")} -> 1.3543 | I32: =Table134[[#This Row],[MarketCap]]/Table134[[#This Row],[Employees]] -> 2790177 | J32: =Table134[[#This Row],[Value]] / SUM(Table134[Value]) -> 0.0057471834
A33: #VALUE! | B33: {=_FV(A33,"Price")} -> 93.075 | C33: 17 | D33: =IFERROR(Table134[[#This Row],[Price]]*Table134[[#This Row],[Number of shares]],0) -> 1582.275 | E33: {=_FV(Table134[[#This Row],[Company]],"Employees")} -> 791 | F33: {=_FV(Table134[[#This Row],[Company]],"Market cap",TRUE)} -> 10066936155 | G33: {=_FV(Table134[[#This Row],[Company]],"P/E",TRUE)} -> 44.0759 | H33: {=_FV(Table134[[#This Row],[Company]],"Beta")} -> 1.5964 | I33: =Table134[[#This Row],[MarketCap]]/Table134[[#This Row],[Employees]] -> 12726847 | J33: =Table134[[#This Row],[Value]] / SUM(Table134[Value]) -> 0.017481315
A34: #VALUE! | B34: {=_FV(A34,"Price")} -> 33.05 | C34: 149 | D34: =IFERROR(Table134[[#This Row],[Price]]*Table134[[#This Row],[Number of shares]],0) -> 4924.45 | E34: {=_FV(Table134[[#This Row],[Company]],"Employees")} -> 4060 | F34: {=_FV(Table134[[#This Row],[Company]],"Market cap",TRUE)} -> 6123864244 | G34: {=_FV(Table134[[#This Row],[Company]],"P/E",TRUE)} -> 0 | H34: {=_FV(Table134[[#This Row],[Company]],"Beta")} -> 1.6829 | I34: =Table134[[#This Row],[MarketCap]]/Table134[[#This Row],[Employees]] -> 1508340.9 | J34: =Table134[[#This Row],[Value]] / SUM(Table134[Value]) -> 0.054406385
A35: #VALUE! | B35: {=_FV(A35,"Price")} -> 131.635 | C35: 220 | D35: =IFERROR(Table134[[#This Row],[Price]]*Table134[[#This Row],[Number of shares]],0) -> 28959.7 | E35: {=_FV(Table134[[#This Row],[Company]],"Employees")} -> 52000 | F35: {=_FV(Table134[[#This Row],[Company]],"Market cap",TRUE)} -> 140454545000 | G35: {=_FV(Table134[[#This Row],[Company]],"P/E",TRUE)} -> 27.1951 | H35: {=_FV(Table134[[#This Row],[Company]],"Beta")} -> 1.2816 | I35: =Table134[[#This Row],[MarketCap]]/Table134[[#This Row],[Employees]] -> 2701048.9 | J35: =Table134[[#This Row],[Value]] / SUM(Table134[Value]) -> 0.31995301
A36: #VALUE! | B36: {=_FV(A36,"Price")} -> 374.08 | C36: 6 | D36: =IFERROR(Table134[[#This Row],[Price]]*Table134[[#This Row],[Number of shares]],0) -> 2244.48 | E36: {=_FV(Table134[[#This Row],[Company]],"Employees")} -> 35500 | F36: {=_FV(Table134[[#This Row],[Company]],"Market cap",TRUE)} -> 296873591392 | G36: {=_FV(Table134[[#This Row],[Company]],"P/E",TRUE)} -> 38.3283 | H36: {=_FV(Table134[[#This Row],[Company]],"Beta")} -> 1.5969 | I36: =Table134[[#This Row],[MarketCap]]/Table134[[#This Row],[Employees]] -> 8362636.4 | J36: =Table134[[#This Row],[Value]] / SUM(Table134[Value]) -> 0.024797499
A37: #VALUE! | B37: {=_FV(A37,"Price")} -> 40.73 | C37: 40 | D37: =IFERROR(Table134[[#This Row],[Price]]*Table134[[#This Row],[Number of shares]],0) -> 1629.2 | E37: {=_FV(Table134[[#This Row],[Company]],"Employees")} -> 136 | F37: {=_FV(Table134[[#This Row],[Company]],"Market cap",TRUE)} -> 1247451558 | G37: {=_FV(Table134[[#This Row],[Company]],"P/E",TRUE)} -> 0 | H37: {=_FV(Table134[[#This Row],[Company]],"Beta")} -> 2.2671 | I37: =Table134[[#This Row],[MarketCap]]/Table134[[#This Row],[Employees]] -> 9172437.9 | J37: =Table134[[#This Row],[Value]] / SUM(Table134[Value]) -> 0.017999753
A38: #VALUE! | B38: {=_FV(A38,"Price")} -> 1398.7901 | C38: 35 | D38: =IFERROR(Table134[[#This Row],[Price]]*Table134[[#This Row],[Number of shares]],0) -> 48957.654 | E38: {=_FV(Table134[[#This Row],[Company]],"Employees")} -> 43520 | F38: {=_FV(Table134[[#This Row],[Company]],"Market cap",TRUE)} -> 542937160097 | G38: {=_FV(Table134[[#This Row],[Company]],"P/E",TRUE)} -> 48.1909 | H38: {=_FV(Table134[[#This Row],[Company]],"Beta")} -> 1.8562 | I38: =Table134[[#This Row],[MarketCap]]/Table134[[#This Row],[Employees]] -> 12475578 | J38: =Table134[[#This Row],[Value]] / SUM(Table134[Value]) -> 0.54089471
A39: #VALUE! | B39: {=_FV(A39,"Price")} -> 198.83 | C39: 6 | D39: =IFERROR(Table134[[#This Row],[Price]]*Table134[[#This Row],[Number of shares]],0) -> 1192.98 | E39: {=_FV(Table134[[#This Row],[Company]],"Employees")} -> 32169 | F39: {=_FV(Table134[[#This Row],[Company]],"Market cap",TRUE)} -> 50242929307 | G39: {=_FV(Table134[[#This Row],[Company]],"P/E",TRUE)} -> 25.022 | H39: {=_FV(Table134[[#This Row],[Company]],"Beta")} -> 1.469 | I39: =Table134[[#This Row],[MarketCap]]/Table134[[#This Row],[Employees]] -> 1561843.1 | J39: =Table134[[#This Row],[Value]] / SUM(Table134[Value]) -> 0.0131803
A43: AI
A44: Company | B44: Price | C44: Number of shares | D44: Value | E44: Employees | F44: MarketCap | G44: P/E | H44: Beta | I44: Marketcap per employee | J44: Share of Portfolio
A45: #VALUE! | B45: {=_FV(A45,"Price")} -> 180.405 | C45: 5 | D45: =IFERROR(Table1345[[#This Row],[Price]]*Table1345[[#This Row],[Number of shares]],0) -> 902.025 | E45: {=_FV(Table1345[[#This Row],[Company]],"Employees")} -> 42000 | F45: {=_FV(Table1345[[#This Row],[Company]],"Market cap",TRUE)} -> 4383841500000 | G45: {=_FV(Table1345[[#This Row],[Company]],"P/E",TRUE)} -> 36.8038 | H45: {=_FV(Table1345[[#This Row],[Company]],"Beta")} -> 2.3397 | I45: =Table1345[[#This Row],[MarketCap]]/Table1345[[#This Row],[Employees]] -> 1.0437718e+08 | J45: =Table1345[[#This Row],[Value]] / SUM(Table1345[Value]) -> 0.0083909148
A46: #VALUE! | B46: {=_FV(A46,"Price")} -> 116.395 | C46: 11 | D46: =IFERROR(Table1345[[#This Row],[Price]]*Table1345[[#This Row],[Number of shares]],0) -> 1280.345 | E46: {=_FV(Table1345[[#This Row],[Company]],"Employees")} -> 1371 | F46: {=_FV(Table1345[[#This Row],[Company]],"Market cap",TRUE)} -> 29449913715 | G46: {=_FV(Table1345[[#This Row],[Company]],"P/E",TRUE)} -> 698.6495 | H46: {=_FV(Table1345[[#This Row],[Company]],"Beta")} -> -13.254 | I46: =Table1345[[#This Row],[MarketCap]]/Table1345[[#This Row],[Employees]] -> 21480608 | J46: =Table1345[[#This Row],[Value]] / SUM(Table1345[Value]) -> 0.011910164
A47: #VALUE! | B47: {=_FV(A47,"Price")} -> 23.8699 | C47: 17 | D47: =IFERROR(Table1345[[#This Row],[Price]]*Table1345[[#This Row],[Number of shares]],0) -> 405.7883 | E47: {=_FV(Table1345[[#This Row],[Company]],"Employees")} -> 6238 | F47: {=_FV(Table1345[[#This Row],[Company]],"Market cap",TRUE)} -> 14333442904 | G47: {=_FV(Table1345[[#This Row],[Company]],"P/E",TRUE)} -> 18.1963 | H47: {=_FV(Table1345[[#This Row],[Company]],"Beta")} -> 1.6309 | I47: =Table1345[[#This Row],[MarketCap]]/Table1345[[#This Row],[Employees]] -> 2297762.6 | J47: =Table1345[[#This Row],[Value]] / SUM(Table1345[Value]) -> 0.0037747679
A48: #VALUE! | B48: {=_FV(A48,"Price")} -> 381.57 | C48: 149 | D48: =IFERROR(Table1345[[#This Row],[Price]]*Table1345[[#This Row],[Number of shares]],0) -> 56853.93 | E48: {=_FV(Table1345[[#This Row],[Company]],"Employees")} -> 53000 | F48: {=_FV(Table1345[[#This Row],[Company]],"Market cap",TRUE)} -> 430309462380 | G48: {=_FV(Table1345[[#This Row],[Company]],"P/E",TRUE)} -> 36.2709 | H48: {=_FV(Table1345[[#This Row],[Company]],"Beta")} -> 1.5364 | I48: =Table1345[[#This Row],[MarketCap]]/Table1345[[#This Row],[Employees]] -> 8119046.5 | J48: =Table1345[[#This Row],[Value]] / SUM(Table1345[Value]) -> 0.52887279
A49: #VALUE! | B49: {=_FV(A49,"Price")} -> 103.09 | C49: 220 | D49: =IFERROR(Table1345[[#This Row],[Price]]*Table1345[[#This Row],[Number of shares]],0) -> 22679.8 | E49: {=_FV(Table1345[[#This Row],[Company]],"Employees")} -> 622 | F49: {=_FV(Table1345[[#This Row],[Company]],"Market cap",TRUE)} -> 19014940191 | G49: {=_FV(Table1345[[#This Row],[Company]],"P/E",TRUE)} -> 90.0743 | H49: {=_FV(Table1345[[#This Row],[Company]],"Beta")} -> 2.6899 | I49: =Table1345[[#This Row],[MarketCap]]/Table1345[[#This Row],[Employees]] -> 30570643 | J49: =Table1345[[#This Row],[Value]] / SUM(Table1345[Value]) -> 0.21097449
A50: #VALUE! | B50: {=_FV(A50,"Price")} -> 348.525 | C50: 6 | D50: =IFERROR(Table1345[[#This Row],[Price]]*Table1345[[#This Row],[Number of shares]],0) -> 2091.15 | E50: {=_FV(Table1345[[#This Row],[Company]],"Employees")} -> 52045 | F50: {=_FV(Table1345[[#This Row],[Company]],"Market cap",TRUE)} -> 1807626655125 | G50: {=_FV(Table1345[[#This Row],[Company]],"P/E",TRUE)} -> 32.9671 | H50: {=_FV(Table1345[[#This Row],[Company]],"Beta")} -> 1.3467 | I50: =Table1345[[#This Row],[MarketCap]]/Table1345[[#This Row],[Employees]] -> 34731995 | J50: =Table1345[[#This Row],[Value]] / SUM(Table1345[Value]) -> 0.019452522
A51: #VALUE! | B51: {=_FV(A51,"Price")} -> 280.42 | C51: 40 | D51: =IFERROR(Table1345[[#This Row],[Price]]*Table1345[[#This Row],[Number of shares]],0) -> 11216.8 | E51: {=_FV(Table1345[[#This Row],[Company]],"Employees")} -> 34000 | F51: {=_FV(Table1345[[#This Row],[Company]],"Market cap",TRUE)} -> 107288243328 | G51: {=_FV(Table1345[[#This Row],[Company]],"P/E",TRUE)} -> 82.237 | H51: {=_FV(Table1345[[#This Row],[Company]],"Beta")} -> 2.0152 | I51: =Table1345[[#This Row],[MarketCap]]/Table1345[[#This Row],[Employees]] -> 3155536.6 | J51: =Table1345[[#This Row],[Value]] / SUM(Table1345[Value]) -> 0.10434213
A52: #VALUE! | B52: {=_FV(A52,"Price")} -> 307.34 | C52: 35 | D52: =IFERROR(Table1345[[#This Row],[Price]]*Table1345[[#This Row],[Number of shares]],0) -> 10756.9 | E52: {=_FV(Table1345[[#This Row],[Company]],"Employees")} -> 29591 | F52: {=_FV(Table1345[[#This Row],[Company]],"Market cap",TRUE)} -> 52395670000 | G52: {=_FV(Table1345[[#This Row],[Company]],"P/E",TRUE)} -> 42.8982 | H52: {=_FV(Table1345[[#This Row],[Company]],"Beta")} -> 1.2471 | I52: =Table1345[[#This Row],[MarketCap]]/Table1345[[#This Row],[Employees]] -> 1770662.4 | J52: =Table1345[[#This Row],[Value]] / SUM(Table1345[Value]) -> 0.100064
A53: #VALUE! | B53: {=_FV(A53,"Price")} -> 218.91 | C53: 6 | D53: =IFERROR(Table1345[[#This Row],[Price]]*Table1345[[#This Row],[Number of shares]],0) -> 1313.46 | E53: {=_FV(Table1345[[#This Row],[Company]],"Employees")} -> 31000 | F53: {=_FV(Table1345[[#This Row],[Company]],"Market cap",TRUE)} -> 356913272010 | G53: {=_FV(Table1345[[#This Row],[Company]],"P/E",TRUE)} -> 84.0539 | H53: {=_FV(Table1345[[#This Row],[Company]],"Beta")} -> 1.9662 | I53: =Table1345[[#This Row],[MarketCap]]/Table1345[[#This Row],[Employees]] -> 11513331 | J53: =Table1345[[#This Row],[Value]] / SUM(Table1345[Value]) -> 0.01221821
A57: Industrials
A58: Company | B58: Price | C58: Number of shares | D58: Value | E58: Employees | F58: MarketCap | G58: P/E | H58: Beta | I58: Marketcap per employee | J58: Share of Portfolio
A59: #VALUE! | B59: {=_FV(A59,"Price")} -> 195.775 | C59: 5 | D59: =IFERROR(Table13456[[#This Row],[Price]]*Table13456[[#This Row],[Number of shares]],0) -> 978.875 | E59: {=_FV(Table13456[[#This Row],[Company]],"Employees")} -> 7900 | F59: {=_FV(Table13456[[#This Row],[Company]],"Market cap",TRUE)} -> 21008811025 | G59: {=_FV(Table13456[[#This Row],[Company]],"P/E",TRUE)} -> 13.7793 | H59: {=_FV(Table13456[[#This Row],[Company]],"Beta")} -> 1.6244 | I59: =Table13456[[#This Row],[MarketCap]]/Table13456[[#This Row],[Employees]] -> 2659343.2 | J59: =Table13456[[#This Row],[Value]] / SUM(Table13456[Value]) -> 0.0077692919
A60: #VALUE! | B60: {=_FV(A60,"Price")} -> 280.42 | C60: 11 | D60: =IFERROR(Table13456[[#This Row],[Price]]*Table13456[[#This Row],[Number of shares]],0) -> 3084.62 | E60: {=_FV(Table13456[[#This Row],[Company]],"Employees")} -> 34000 | F60: {=_FV(Table13456[[#This Row],[Company]],"Market cap",TRUE)} -> 107288243328 | G60: {=_FV(Table13456[[#This Row],[Company]],"P/E",TRUE)} -> 82.237 | H60: {=_FV(Table13456[[#This Row],[Company]],"Beta")} -> 2.0152 | I60: =Table13456[[#This Row],[MarketCap]]/Table13456[[#This Row],[Employees]] -> 3155536.6 | J60: =Table13456[[#This Row],[Value]] / SUM(Table13456[Value]) -> 0.024482506
A61: #VALUE! | B61: {=_FV(A61,"Price")} -> 34.39 | C61: 17 | D61: =IFERROR(Table13456[[#This Row],[Price]]*Table13456[[#This Row],[Number of shares]],0) -> 584.63 | E61: {=_FV(Table13456[[#This Row],[Company]],"Employees")} -> 569 | F61: {=_FV(Table13456[[#This Row],[Company]],"Market cap",TRUE)} -> 1637386653 | G61: {=_FV(Table13456[[#This Row],[Company]],"P/E",TRUE)} -> 11.7396 | H61: {=_FV(Table13456[[#This Row],[Company]],"Beta")} -> 3.0122 | I61: =Table13456[[#This Row],[MarketCap]]/Table13456[[#This Row],[Employees]] -> 2877656.7 | J61: =Table13456[[#This Row],[Value]] / SUM(Table13456[Value]) -> 0.0046401851
A62: #VALUE! | B62: {=_FV(A62,"Price")} -> 123.445 | C62: 149 | D62: =IFERROR(Table13456[[#This Row],[Price]]*Table13456[[#This Row],[Number of shares]],0) -> 18393.305 | E62: {=_FV(Table13456[[#This Row],[Company]],"Employees")} -> 9400 | F62: {=_FV(Table13456[[#This Row],[Company]],"Market cap",TRUE)} -> 6296524550 | G62: {=_FV(Table13456[[#This Row],[Company]],"P/E",TRUE)} -> 31.2796 | H62: {=_FV(Table13456[[#This Row],[Company]],"Beta")} -> 1.819 | I62: =Table13456[[#This Row],[MarketCap]]/Table13456[[#This Row],[Employees]] -> 669843.04 | J62: =Table13456[[#This Row],[Value]] / SUM(Table13456[Value]) -> 0.14598693
A63: #VALUE! | B63: {=_FV(A63,"Price")} -> 440.17 | C63: 220 | D63: =IFERROR(Table13456[[#This Row],[Price]]*Table13456[[#This Row],[Number of shares]],0) -> 96837.4 | E63: {=_FV(Table13456[[#This Row],[Company]],"Employees")} -> 1595 | F63: {=_FV(Table13456[[#This Row],[Company]],"Market cap",TRUE)} -> 6106658879 | G63: {=_FV(Table13456[[#This Row],[Company]],"P/E",TRUE)} -> 51.8775 | H63: {=_FV(Table13456[[#This Row],[Company]],"Beta")} -> 0.5761 | I63: =Table13456[[#This Row],[MarketCap]]/Table13456[[#This Row],[Employees]] -> 3828626.3 | J63: =Table13456[[#This Row],[Value]] / SUM(Table13456[Value]) -> 0.76859459
A64: #VALUE! | B64: {=_FV(A64,"Price")} -> 48.72 | C64: 6 | D64: =IFERROR(Table13456[[#This Row],[Price]]*Table13456[[#This Row],[Number of shares]],0) -> 292.32 | E64: {=_FV(Table13456[[#This Row],[Company]],"Employees")} -> 22995 | F64: {=_FV(Table13456[[#This Row],[Company]],"Market cap",TRUE)} -> 6972138936 | G64: {=_FV(Table13456[[#This Row],[Company]],"P/E",TRUE)} -> 0 | H64: {=_FV(Table13456[[#This Row],[Company]],"Beta")} -> 1.2973 | I64: =Table13456[[#This Row],[MarketCap]]/Table13456[[#This Row],[Employees]] -> 303202.39 | J64: =Table13456[[#This Row],[Value]] / SUM(Table13456[Value]) -> 0.0023201322
A65: #VALUE! | B65: {=_FV(A65,"Price")} -> 129.5 | C65: 40 | D65: =IFERROR(Table13456[[#This Row],[Price]]*Table13456[[#This Row],[Number of shares]],0) -> 5180 | E65: {=_FV(Table13456[[#This Row],[Company]],"Employees")} -> 43000 | F65: {=_FV(Table13456[[#This Row],[Company]],"Market cap",TRUE)} -> 15209347650 | G65: {=_FV(Table13456[[#This Row],[Company]],"P/E",TRUE)} -> 33.8182 | H65: {=_FV(Table13456[[#This Row],[Company]],"Beta")} -> 0.7685 | I65: =Table13456[[#This Row],[MarketCap]]/Table13456[[#This Row],[Employees]] -> 353705.76 | J65: =Table13456[[#This Row],[Value]] / SUM(Table13456[Value]) -> 0.041113454
A66: #VALUE! | B66: {=_FV(A66,"Price")} -> 3.15 | C66: 35 | D66: =IFERROR(Table13456[[#This Row],[Price]]*Table13456[[#This Row],[Number of shares]],0) -> 110.25 | E66: {=_FV(Table13456[[#This Row],[Company]],"Employees")} -> 16 | F66: {=_FV(Table13456[[#This Row],[Company]],"Market cap",TRUE)} -> 38081578 | G66: {=_FV(Table13456[[#This Row],[Company]],"P/E",TRUE)} -> 0 | H66: {=_FV(Table13456[[#This Row],[Company]],"Beta")} -> 1.1262 | I66: =Table13456[[#This Row],[MarketCap]]/Table13456[[#This Row],[Employees]] -> 2380098.6 | J66: =Table13456[[#This Row],[Value]] / SUM(Table13456[Value]) -> 0.00087504986
A67: #VALUE! | B67: {=_FV(A67,"Price")} -> 88.57 | C67: 6 | D67: =IFERROR(Table13456[[#This Row],[Price]]*Table13456[[#This Row],[Number of shares]],0) -> 531.42 | E67: {=_FV(Table13456[[#This Row],[Company]],"Employees")} -> 51000 | F67: {=_FV(Table13456[[#This Row],[Company]],"Market cap",TRUE)} -> 11451091302 | G67: {=_FV(Table13456[[#This Row],[Company]],"P/E",TRUE)} -> 19.5756 | H67: {=_FV(Table13456[[#This Row],[Company]],"Beta")} -> 1.0647 | I67: =Table13456[[#This Row],[MarketCap]]/Table13456[[#This Row],[Employees]] -> 224531.2 | J67: =Table13456[[#This Row],[Value]] / SUM(Table13456[Value]) -> 0.0042178594
A71: Nuclear
A72: Company | B72: Price | C72: Number of shares | D72: Value | E72: Employees | F72: MarketCap | G72: P/E | H72: Beta | I72: Marketcap per employee | J72: Share of Portfolio
A73: #VALUE! | B73: {=_FV(A73,"Price")} -> 5.15 | C73: 5 | D73: =IFERROR(Table134567[[#This Row],[Price]]*Table134567[[#This Row],[Number of shares]],0) -> 25.75 | E73: {=_FV(Table134567[[#This Row],[Company]],"Employees")} -> 136 | F73: {=_FV(Table134567[[#This Row],[Company]],"Market cap",TRUE)} -> 644317015 | G73: {=_FV(Table134567[[#This Row],[Company]],"P/E",TRUE)} -> 0 | H73: {=_FV(Table134567[[#This Row],[Company]],"Beta")} -> 3.5039 | I73: =Table134567[[#This Row],[MarketCap]]/Table134567[[#This Row],[Employees]] -> 4737625.1 | J73: =Table134567[[#This Row],[Value]] / SUM(Table134567[Value]) -> 0.00037903777
A74: #VALUE! | B74: {=_FV(A74,"Price")} -> 110.85 | C74: 11 | D74: =IFERROR(Table134567[[#This Row],[Price]]*Table134567[[#This Row],[Number of shares]],0) -> 1219.35 | E74: {=_FV(Table134567[[#This Row],[Company]],"Employees")} -> 2424 | F74: {=_FV(Table134567[[#This Row],[Company]],"Market cap",TRUE)} -> 48278833050 | G74: {=_FV(Table134567[[#This Row],[Company]],"P/E",TRUE)} -> 112.3897 | H74: {=_FV(Table134567[[#This Row],[Company]],"Beta")} -> 1.0182 | I74: =Table134567[[#This Row],[MarketCap]]/Table134567[[#This Row],[Employees]] -> 19917010 | J74: =Table134567[[#This Row],[Value]] / SUM(Table134567[Value]) -> 0.017948727
A75: #VALUE! | B75: {=_FV(A75,"Price")} -> 215.84 | C75: 17 | D75: =IFERROR(Table134567[[#This Row],[Price]]*Table134567[[#This Row],[Number of shares]],0) -> 3669.28 | E75: {=_FV(Table134567[[#This Row],[Company]],"Employees")} -> 10400 | F75: {=_FV(Table134567[[#This Row],[Company]],"Market cap",TRUE)} -> 19773516812 | G75: {=_FV(Table134567[[#This Row],[Company]],"P/E",TRUE)} -> 60.277 | H75: {=_FV(Table134567[[#This Row],[Company]],"Beta")} -> 0.796 | I75: =Table134567[[#This Row],[MarketCap]]/Table134567[[#This Row],[Employees]] -> 1901299.7 | J75: =Table134567[[#This Row],[Value]] / SUM(Table134567[Value]) -> 0.054011484
A76: #VALUE! | B76: {=_FV(A76,"Price")} -> 196.565 | C76: 149 | D76: =IFERROR(Table134567[[#This Row],[Price]]*Table134567[[#This Row],[Number of shares]],0) -> 29288.185 | E76: {=_FV(Table134567[[#This Row],[Company]],"Employees")} -> 300 | F76: {=_FV(Table134567[[#This Row],[Company]],"Market cap",TRUE)} -> 3865364236 | G76: {=_FV(Table134567[[#This Row],[Company]],"P/E",TRUE)} -> 47.2569 | H76: {=_FV(Table134567[[#This Row],[Company]],"Beta")} -> 1.3067 | I76: =Table134567[[#This Row],[MarketCap]]/Table134567[[#This Row],[Employees]] -> 12884547 | J76: =Table134567[[#This Row],[Value]] / SUM(Table134567[Value]) -> 0.43111955
A77: #VALUE! | B77: {=_FV(A77,"Price")} -> 94.3 | C77: 220 | D77: =IFERROR(Table134567[[#This Row],[Price]]*Table134567[[#This Row],[Number of shares]],0) -> 20746 | E77: {=_FV(Table134567[[#This Row],[Company]],"Employees")} -> 29800 | F77: {=_FV(Table134567[[#This Row],[Company]],"Market cap",TRUE)} -> 105558571300 | G77: {=_FV(Table134567[[#This Row],[Company]],"P/E",TRUE)} -> 24.0745 | H77: {=_FV(Table134567[[#This Row],[Company]],"Beta")} -> 0.4201 | I77: =Table134567[[#This Row],[MarketCap]]/Table134567[[#This Row],[Employees]] -> 3542233.9 | J77: =Table134567[[#This Row],[Value]] / SUM(Table134567[Value]) -> 0.30537933
A78: #VALUE! | B78: {=_FV(A78,"Price")} -> 48.72 | C78: 6 | D78: =IFERROR(Table134567[[#This Row],[Price]]*Table134567[[#This Row],[Number of shares]],0) -> 292.32 | E78: {=_FV(Table134567[[#This Row],[Company]],"Employees")} -> 22995 | F78: {=_FV(Table134567[[#This Row],[Company]],"Market cap",TRUE)} -> 6972138936 | G78: {=_FV(Table134567[[#This Row],[Company]],"P/E",TRUE)} -> 0 | H78: {=_FV(Table134567[[#This Row],[Company]],"Beta")} -> 1.2973 | I78: =Table134567[[#This Row],[MarketCap]]/Table134567[[#This Row],[Employees]] -> 303202.39 | J78: =Table134567[[#This Row],[Value]] / SUM(Table134567[Value]) -> 0.0043029251
A79: #VALUE! | B79: {=_FV(A79,"Price")} -> 305.33 | C79: 40 | D79: =IFERROR(Table134567[[#This Row],[Price]]*Table134567[[#This Row],[Number of shares]],0) -> 12213.2 | E79: {=_FV(Table134567[[#This Row],[Company]],"Employees")} -> 15291 | F79: {=_FV(Table134567[[#This Row],[Company]],"Market cap",TRUE)} -> 110619440751 | G79: {=_FV(Table134567[[#This Row],[Company]],"P/E",TRUE)} -> 41.2898 | H79: {=_FV(Table134567[[#This Row],[Company]],"Beta")} -> 1.1582 | I79: =Table134567[[#This Row],[MarketCap]]/Table134567[[#This Row],[Employees]] -> 7234284.3 | J79: =Table134567[[#This Row],[Value]] / SUM(Table134567[Value]) -> 0.17977725
A80: #VALUE! | B80: {=_FV(A80,"Price")} -> 11.8299 | C80: 35 | D80: =IFERROR(Table134567[[#This Row],[Price]]*Table134567[[#This Row],[Number of shares]],0) -> 414.0465 | E80: {=_FV(Table134567[[#This Row],[Company]],"Employees")} -> 428 | F80: {=_FV(Table134567[[#This Row],[Company]],"Market cap",TRUE)} -> 3998699027 | G80: {=_FV(Table134567[[#This Row],[Company]],"P/E",TRUE)} -> #VALUE! | H80: {=_FV(Table134567[[#This Row],[Company]],"Beta")} -> 2.2597 | I80: =Table134567[[#This Row],[MarketCap]]/Table134567[[#This Row],[Employees]] -> 9342754.7 | J80: =Table134567[[#This Row],[Value]] / SUM(Table134567[Value]) -> 0.0060947287
A81: #VALUE! | B81: {=_FV(A81,"Price")} -> 11.175 | C81: 6 | D81: =IFERROR(Table134567[[#This Row],[Price]]*Table134567[[#This Row],[Number of shares]],0) -> 67.05 | E81: {=_FV(Table134567[[#This Row],[Company]],"Employees")} -> 293 | F81: {=_FV(Table134567[[#This Row],[Company]],"Market cap",TRUE)} -> 206934850 | G81: {=_FV(Table134567[[#This Row],[Company]],"P/E",TRUE)} -> 0 | H81: {=_FV(Table134567[[#This Row],[Company]],"Beta")} -> 0.5038 | I81: =Table134567[[#This Row],[MarketCap]]/Table134567[[#This Row],[Employees]] -> 706262.29 | J81: =Table134567[[#This Row],[Value]] / SUM(Table134567[Value]) -> 0.0009869702
A85: Energy
A86: Company | B86: Price | C86: Number of shares | D86: Value | E86: Employees | F86: MarketCap | G86: P/E | H86: Beta | I86: Marketcap per employee | J86: Share of Portfolio
A87: #VALUE! | B87: {=_FV(A87,"Price")} -> 44.03 | C87: 5 | D87: =IFERROR(Table1345678[[#This Row],[Price]]*Table1345678[[#This Row],[Number of shares]],0) -> 220.15 | E87: {=_FV(Table1345678[[#This Row],[Company]],"Employees")} -> 632 | F87: {=_FV(Table1345678[[#This Row],[Company]],"Market cap",TRUE)} -> 13584355750 | G87: {=_FV(Table1345678[[#This Row],[Company]],"P/E",TRUE)} -> 21.7121 | H87: {=_FV(Table1345678[[#This Row],[Company]],"Beta")} -> 0.4142 | I87: =Table1345678[[#This Row],[MarketCap]]/Table1345678[[#This Row],[Employees]] -> 21494234 | J87: =Table1345678[[#This Row],[Value]] / SUM(Table1345678[Value]) -> 0.0024674135
A88: #VALUE! | B88: {=_FV(A88,"Price")} -> 46.12 | C88: 11 | D88: =IFERROR(Table1345678[[#This Row],[Price]]*Table1345678[[#This Row],[Number of shares]],0) -> 507.32 | E88: {=_FV(Table1345678[[#This Row],[Company]],"Employees")} -> 564 | F88: {=_FV(Table1345678[[#This Row],[Company]],"Market cap",TRUE)} -> 10855771720 | G88: {=_FV(Table1345678[[#This Row],[Company]],"P/E",TRUE)} -> 16.8395 | H88: {=_FV(Table1345678[[#This Row],[Company]],"Beta")} -> 0.5118 | I88: =Table1345678[[#This Row],[MarketCap]]/Table1345678[[#This Row],[Employees]] -> 19247822 | J88: =Table1345678[[#This Row],[Value]] / SUM(Table1345678[Value]) -> 0.0056859788
A89: #VALUE! | B89: {=_FV(A89,"Price")} -> 49.325 | C89: 17 | D89: =IFERROR(Table1345678[[#This Row],[Price]]*Table1345678[[#This Row],[Number of shares]],0) -> 838.525 | E89: {=_FV(Table1345678[[#This Row],[Company]],"Employees")} -> 3678 | F89: {=_FV(Table1345678[[#This Row],[Company]],"Market cap",TRUE)} -> 5793403752 | G89: {=_FV(Table1345678[[#This Row],[Company]],"P/E",TRUE)} -> 0 | H89: {=_FV(Table1345678[[#This Row],[Company]],"Beta")} -> 0.2113 | I89: =Table1345678[[#This Row],[MarketCap]]/Table1345678[[#This Row],[Employees]] -> 1575150.6 | J89: =Table1345678[[#This Row],[Value]] / SUM(Table1345678[Value]) -> 0.0093980828
A90: #VALUE! | B90: {=_FV(A90,"Price")} -> 112.5 | C90: 149 | D90: =IFERROR(Table1345678[[#This Row],[Price]]*Table1345678[[#This Row],[Number of shares]],0) -> 16762.5 | E90: {=_FV(Table1345678[[#This Row],[Company]],"Employees")} -> 1600 | F90: {=_FV(Table1345678[[#This Row],[Company]],"Market cap",TRUE)} -> 27044808750 | G90: {=_FV(Table1345678[[#This Row],[Company]],"P/E",TRUE)} -> 14.9151 | H90: {=_FV(Table1345678[[#This Row],[Company]],"Beta")} -> 0.4609 | I90: =Table1345678[[#This Row],[MarketCap]]/Table1345678[[#This Row],[Employees]] -> 16903005 | J90: =Table1345678[[#This Row],[Value]] / SUM(Table1345678[Value]) -> 0.18787199
A91: #VALUE! | B91: {=_FV(A91,"Price")} -> 284.95 | C91: 220 | D91: =IFERROR(Table1345678[[#This Row],[Price]]*Table1345678[[#This Row],[Number of shares]],0) -> 62689 | E91: {=_FV(Table1345678[[#This Row],[Company]],"Employees")} -> 1717 | F91: {=_FV(Table1345678[[#This Row],[Company]],"Market cap",TRUE)} -> 59897316355 | G91: {=_FV(Table1345678[[#This Row],[Company]],"P/E",TRUE)} -> 11.6917 | H91: {=_FV(Table1345678[[#This Row],[Company]],"Beta")} -> 0.1191 | I91: =Table1345678[[#This Row],[MarketCap]]/Table1345678[[#This Row],[Employees]] -> 34884867 | J91: =Table1345678[[#This Row],[Value]] / SUM(Table1345678[Value]) -> 0.70261043
A92: #VALUE! | B92: {=_FV(A92,"Price")} -> 141.64 | C92: 6 | D92: =IFERROR(Table1345678[[#This Row],[Price]]*Table1345678[[#This Row],[Number of shares]],0) -> 849.84 | E92: {=_FV(Table1345678[[#This Row],[Company]],"Employees")} -> 3400 | F92: {=_FV(Table1345678[[#This Row],[Company]],"Market cap",TRUE)} -> 75988656060 | G92: {=_FV(Table1345678[[#This Row],[Company]],"P/E",TRUE)} -> 15.5459 | H92: {=_FV(Table1345678[[#This Row],[Company]],"Beta")} -> 0.3383 | I92: =Table1345678[[#This Row],[MarketCap]]/Table1345678[[#This Row],[Employees]] -> 22349605 | J92: =Table1345678[[#This Row],[Value]] / SUM(Table1345678[Value]) -> 0.0095248999
A93: #VALUE! | B93: {=_FV(A93,"Price")} -> 163.71 | C93: 40 | D93: =IFERROR(Table1345678[[#This Row],[Price]]*Table1345678[[#This Row],[Number of shares]],0) -> 6548.4 | E93: {=_FV(Table1345678[[#This Row],[Company]],"Employees")} -> 58000 | F93: {=_FV(Table1345678[[#This Row],[Company]],"Market cap",TRUE)} -> 682140934440 | G93: {=_FV(Table1345678[[#This Row],[Company]],"P/E",TRUE)} -> 24.5057 | H93: {=_FV(Table1345678[[#This Row],[Company]],"Beta")} -> 0.3067 | I93: =Table1345678[[#This Row],[MarketCap]]/Table1345678[[#This Row],[Employees]] -> 11761051 | J93: =Table1345678[[#This Row],[Value]] / SUM(Table1345678[Value]) -> 0.073393644
A94: #VALUE! | B94: {=_FV(A94,"Price")} -> 11.63 | C94: 35 | D94: =IFERROR(Table1345678[[#This Row],[Price]]*Table1345678[[#This Row],[Number of shares]],0) -> 407.05 | E94: {=_FV(Table1345678[[#This Row],[Company]],"Employees")} -> 22311 | F94: {=_FV(Table1345678[[#This Row],[Company]],"Market cap",TRUE)} -> 40010851820 | G94: {=_FV(Table1345678[[#This Row],[Company]],"P/E",TRUE)} -> #VALUE! | H94: {=_FV(Table1345678[[#This Row],[Company]],"Beta")} -> 0.6288 | I94: =Table1345678[[#This Row],[MarketCap]]/Table1345678[[#This Row],[Employees]] -> 1793324 | J94: =Table1345678[[#This Row],[Value]] / SUM(Table1345678[Value]) -> 0.0045621652
A95: #VALUE! | B95: {=_FV(A95,"Price")} -> 66.7 | C95: 6 | D95: =IFERROR(Table1345678[[#This Row],[Price]]*Table1345678[[#This Row],[Number of shares]],0) -> 400.2 | E95: {=_FV(Table1345678[[#This Row],[Company]],"Employees")} -> 1523 | F95: {=_FV(Table1345678[[#This Row],[Company]],"Market cap",TRUE)} -> 41639075800 | G95: {=_FV(Table1345678[[#This Row],[Company]],"P/E",TRUE)} -> 20.1267 | H95: {=_FV(Table1345678[[#This Row],[Company]],"Beta")} -> 0.6833 | I95: =Table1345678[[#This Row],[MarketCap]]/Table1345678[[#This Row],[Employees]] -> 27340168 | J95: =Table1345678[[#This Row],[Value]] / SUM(Table1345678[Value]) -> 0.0044853913
A99: Consumer Discretionary
A100: Company | B100: Price | C100: Number of shares | D100: Value | E100: Employees | F100: MarketCap | G100: P/E | H100: Beta | I100: Marketcap per employee | J100: Share of Portfolio
A101: #VALUE! | B101: {=_FV(A101,"Price")} -> 394.5401 | C101: 5 | D101: =IFERROR(Table13456789[[#This Row],[Price]]*Table13456789[[#This Row],[Number of shares]],0) -> 1972.7005 | E101: {=_FV(Table13456789[[#This Row],[Company]],"Employees")} -> 134785 | F101: {=_FV(Table13456789[[#This Row],[Company]],"Market cap",TRUE)} -> 1480484896523 | G101: {=_FV(Table13456789[[#This Row],[Company]],"P/E",TRUE)} -> 366.8775 | H101: {=_FV(Table13456789[[#This Row],[Company]],"Beta")} -> 1.9062 | I101: =Table13456789[[#This Row],[MarketCap]]/Table13456789[[#This Row],[Employees]] -> 10984048 | J101: =Table13456789[[#This Row],[Value]] / SUM(Table13456789[Value]) -> 0.47459468
A102: #VALUE! | B102: {=_FV(A102,"Price")} -> 159.22 | C102: 11 | D102: =IFERROR(Table13456789[[#This Row],[Price]]*Table13456789[[#This Row],[Number of shares]],0) -> 1751.42 | E102: {=_FV(Table13456789[[#This Row],[Company]],"Employees")} -> 39000 | F102: {=_FV(Table13456789[[#This Row],[Company]],"Market cap",TRUE)} -> 18405609092 | G102: {=_FV(Table13456789[[#This Row],[Company]],"P/E",TRUE)} -> 11.0756 | H102: {=_FV(Table13456789[[#This Row],[Company]],"Beta")} -> 1.0481 | I102: =Table13456789[[#This Row],[MarketCap]]/Table13456789[[#This Row],[Employees]] -> 471938.69 | J102: =Table13456789[[#This Row],[Value]] / SUM(Table13456789[Value]) -> 0.42135875
A103: #VALUE! | B103: {=_FV(A103,"Price")} -> 25.44 | C103: 17 | D103: =IFERROR(Table13456789[[#This Row],[Price]]*Table13456789[[#This Row],[Number of shares]],0) -> 432.48 | E103: {=_FV(Table13456789[[#This Row],[Company]],"Employees")} -> 79000 | F103: {=_FV(Table13456789[[#This Row],[Company]],"Market cap",TRUE)} -> 9477990000 | G103: {=_FV(Table13456789[[#This Row],[Company]],"P/E",TRUE)} -> 11.4168 | H103: {=_FV(Table13456789[[#This Row],[Company]],"Beta")} -> 2.2266 | I103: =Table13456789[[#This Row],[MarketCap]]/Table13456789[[#This Row],[Employees]] -> 119974.56 | J103: =Table13456789[[#This Row],[Value]] / SUM(Table13456789[Value]) -> 0.10404656
B104: {=_FV(A104,"Price")} -> #VALUE! | C104: 149 | D104: =IFERROR(Table13456789[[#This Row],[Price]]*Table13456789[[#This Row],[Number of shares]],0) -> 0 | E104: {=_FV(Table13456789[[#This Row],[Company]],"Employees")} -> #VALUE! | F104: {=_FV(Table13456789[[#This Row],[Company]],"Market cap",TRUE)} -> #VALUE! | G104: {=_FV(Table13456789[[#This Row],[Company]],"P/E",TRUE)} -> #VALUE! | H104: {=_FV(Table13456789[[#This Row],[Company]],"Beta")} -> #VALUE! | I104: =Table13456789[[#This Row],[MarketCap]]/Table13456789[[#This Row],[Employees]] -> #VALUE! | J104: =Table13456789[[#This Row],[Value]] / SUM(Table13456789[Value]) -> 0
B105: {=_FV(A105,"Price")} -> #VALUE! | C105: 220 | D105: =IFERROR(Table13456789[[#This Row],[Price]]*Table13456789[[#This Row],[Number of shares]],0) -> 0 | E105: {=_FV(Table13456789[[#This Row],[Company]],"Employees")} -> #VALUE! | F105: {=_FV(Table13456789[[#This Row],[Company]],"Market cap",TRUE)} -> #VALUE! | G105: {=_FV(Table13456789[[#This Row],[Company]],"P/E",TRUE)} -> #VALUE! | H105: {=_FV(Table13456789[[#This Row],[Company]],"Beta")} -> #VALUE! | I105: =Table13456789[[#This Row],[MarketCap]]/Table13456789[[#This Row],[Employees]] -> #VALUE! | J105: =Table13456789[[#This Row],[Value]] / SUM(Table13456789[Value]) -> 0
B106: {=_FV(A106,"Price")} -> #VALUE! | C106: 6 | D106: =IFERROR(Table13456789[[#This Row],[Price]]*Table13456789[[#This Row],[Number of shares]],0) -> 0 | E106: {=_FV(Table13456789[[#This Row],[Company]],"Employees")} -> #VALUE! | F106: {=_FV(Table13456789[[#This Row],[Company]],"Market cap",TRUE)} -> #VALUE! | G106: {=_FV(Table13456789[[#This Row],[Company]],"P/E",TRUE)} -> #VALUE! | H106: {=_FV(Table13456789[[#This Row],[Company]],"Beta")} -> #VALUE! | I106: =Table13456789[[#This Row],[MarketCap]]/Table13456789[[#This Row],[Employees]] -> #VALUE! | J106: =Table13456789[[#This Row],[Value]] / SUM(Table13456789[Value]) -> 0
B107: {=_FV(A107,"Price")} -> #VALUE! | C107: 40 | D107: =IFERROR(Table13456789[[#This Row],[Price]]*Table13456789[[#This Row],[Number of shares]],0) -> 0 | E107: {=_FV(Table13456789[[#This Row],[Company]],"Employees")} -> #VALUE! | F107: {=_FV(Table13456789[[#This Row],[Company]],"Market cap",TRUE)} -> #VALUE! | G107: {=_FV(Table13456789[[#This Row],[Company]],"P/E",TRUE)} -> #VALUE! | H107: {=_FV(Table13456789[[#This Row],[Company]],"Beta")} -> #VALUE! | I107: =Table13456789[[#This Row],[MarketCap]]/Table13456789[[#This Row],[Employees]] -> #VALUE! | J107: =Table13456789[[#This Row],[Value]] / SUM(Table13456789[Value]) -> 0
B108: {=_FV(A108,"Price")} -> #VALUE! | C108: 35 | D108: =IFERROR(Table13456789[[#This Row],[Price]]*Table13456789[[#This Row],[Number of shares]],0) -> 0 | E108: {=_FV(Table13456789[[#This Row],[Company]],"Employees")} -> #VALUE! | F108: {=_FV(Table13456789[[#This Row],[Company]],"Market cap",TRUE)} -> #VALUE! | G108: {=_FV(Table13456789[[#This Row],[Company]],"P/E",TRUE)} -> #VALUE! | H108: {=_FV(Table13456789[[#This Row],[Company]],"Beta")} -> #VALUE! | I108: =Table13456789[[#This Row],[MarketCap]]/Table13456789[[#This Row],[Employees]] -> #VALUE! | J108: =Table13456789[[#This Row],[Value]] / SUM(Table13456789[Value]) -> 0
B109: {=_FV(A109,"Price")} -> #VALUE! | C109: 6 | D109: =IFERROR(Table13456789[[#This Row],[Price]]*Table13456789[[#This Row],[Number of shares]],0) -> 0 | E109: {=_FV(Table13456789[[#This Row],[Company]],"Employees")} -> #VALUE! | F109: {=_FV(Table13456789[[#This Row],[Company]],"Market cap",TRUE)} -> #VALUE! | G109: {=_FV(Table13456789[[#This Row],[Company]],"P/E",TRUE)} -> #VALUE! | H109: {=_FV(Table13456789[[#This Row],[Company]],"Beta")} -> #VALUE! | I109: =Table13456789[[#This Row],[MarketCap]]/Table13456789[[#This Row],[Employees]] -> #VALUE! | J109: =Table13456789[[#This Row],[Value]] / SUM(Table13456789[Value]) -> 0
A113: Health Care
A114: Company | B114: Price | C114: Number of shares | D114: Value | E114: Employees | F114: MarketCap | G114: P/E | H114: Beta | I114: Marketcap per employee | J114: Share of Portfolio
A115: #VALUE! | B115: {=_FV(A115,"Price")} -> 3.22 | C115: 240 | D115: =IFERROR(Table134567810[[#This Row],[Price]]*Table134567810[[#This Row],[Number of shares]],0) -> 772.8 | E115: {=_FV(Table134567810[[#This Row],[Company]],"Employees")} -> 158 | F115: {=_FV(Table134567810[[#This Row],[Company]],"Market cap",TRUE)} -> 172552265 | G115: {=_FV(Table134567810[[#This Row],[Company]],"P/E",TRUE)} -> 0 | H115: {=_FV(Table134567810[[#This Row],[Company]],"Beta")} -> 0.3185 | I115: =Table134567810[[#This Row],[MarketCap]]/Table134567810[[#This Row],[Employees]] -> 1092102.9 | J115: =Table134567810[[#This Row],[Value]] / SUM(Table134567810[Value]) -> 0.12282611
A116: #VALUE! | B116: {=_FV(A116,"Price")} -> 2.85 | C116: 200 | D116: =IFERROR(Table134567810[[#This Row],[Price]]*Table134567810[[#This Row],[Number of shares]],0) -> 570 | E116: {=_FV(Table134567810[[#This Row],[Company]],"Employees")} -> 389 | F116: {=_FV(Table134567810[[#This Row],[Company]],"Market cap",TRUE)} -> 177944509 | G116: {=_FV(Table134567810[[#This Row],[Company]],"P/E",TRUE)} -> 0 | H116: {=_FV(Table134567810[[#This Row],[Company]],"Beta")} -> 2.2854 | I116: =Table134567810[[#This Row],[MarketCap]]/Table134567810[[#This Row],[Employees]] -> 457440.9 | J116: =Table134567810[[#This Row],[Value]] / SUM(Table134567810[Value]) -> 0.090593793
A117: #VALUE! | B117: {=_FV(A117,"Price")} -> 0.3168 | C117: 600 | D117: =IFERROR(Table134567810[[#This Row],[Price]]*Table134567810[[#This Row],[Number of shares]],0) -> 190.08 | E117: {=_FV(Table134567810[[#This Row],[Company]],"Employees")} -> 1945 | F117: {=_FV(Table134567810[[#This Row],[Company]],"Market cap",TRUE)} -> 10896326 | G117: {=_FV(Table134567810[[#This Row],[Company]],"P/E",TRUE)} -> 0 | H117: {=_FV(Table134567810[[#This Row],[Company]],"Beta")} -> 4.0211 | I117: =Table134567810[[#This Row],[MarketCap]]/Table134567810[[#This Row],[Employees]] -> 5602.2242 | J117: =Table134567810[[#This Row],[Value]] / SUM(Table134567810[Value]) -> 0.030210646
A118: #VALUE! | B118: {=_FV(A118,"Price")} -> 2.94 | C118: 150 | D118: =IFERROR(Table134567810[[#This Row],[Price]]*Table134567810[[#This Row],[Number of shares]],0) -> 441 | E118: {=_FV(Table134567810[[#This Row],[Company]],"Employees")} -> 216 | F118: {=_FV(Table134567810[[#This Row],[Company]],"Market cap",TRUE)} -> 70715996 | G118: {=_FV(Table134567810[[#This Row],[Company]],"P/E",TRUE)} -> 0 | H118: {=_FV(Table134567810[[#This Row],[Company]],"Beta")} -> 1.9721 | I118: =Table134567810[[#This Row],[MarketCap]]/Table134567810[[#This Row],[Employees]] -> 327388.87 | J118: =Table134567810[[#This Row],[Value]] / SUM(Table134567810[Value]) -> 0.070090987
A119: #VALUE! | B119: {=_FV(A119,"Price")} -> 4.11 | C119: 220 | D119: =IFERROR(Table134567810[[#This Row],[Price]]*Table134567810[[#This Row],[Number of shares]],0) -> 904.2 | E119: {=_FV(Table134567810[[#This Row],[Company]],"Employees")} -> 450 | F119: {=_FV(Table134567810[[#This Row],[Company]],"Market cap",TRUE)} -> 192923276 | G119: {=_FV(Table134567810[[#This Row],[Company]],"P/E",TRUE)} -> 0 | H119: {=_FV(Table134567810[[#This Row],[Company]],"Beta")} -> 1.2841 | I119: =Table134567810[[#This Row],[MarketCap]]/Table134567810[[#This Row],[Employees]] -> 428718.39 | J119: =Table134567810[[#This Row],[Value]] / SUM(Table134567810[Value]) -> 0.14371036
A120: #VALUE! | B120: {=_FV(A120,"Price")} -> 48.7601 | C120: 18 | D120: =IFERROR(Table134567810[[#This Row],[Price]]*Table134567810[[#This Row],[Number of shares]],0) -> 877.6818 | E120: {=_FV(Table134567810[[#This Row],[Company]],"Employees")} -> 3800 | F120: {=_FV(Table134567810[[#This Row],[Company]],"Market cap",TRUE)} -> 8717023489 | G120: {=_FV(Table134567810[[#This Row],[Company]],"P/E",TRUE)} -> 0 | H120: {=_FV(Table134567810[[#This Row],[Company]],"Beta")} -> 3.179 | I120: =Table134567810[[#This Row],[MarketCap]]/Table134567810[[#This Row],[Employees]] -> 2293953.5 | J120: =Table134567810[[#This Row],[Value]] / SUM(Table134567810[Value]) -> 0.13949565
A121: #VALUE! | B121: {=_FV(A121,"Price")} -> 1.4202 | C121: 300 | D121: =IFERROR(Table134567810[[#This Row],[Price]]*Table134567810[[#This Row],[Number of shares]],0) -> 426.06 | E121: {=_FV(Table134567810[[#This Row],[Company]],"Employees")} -> 658 | F121: {=_FV(Table134567810[[#This Row],[Company]],"Market cap",TRUE)} -> 98386613 | G121: {=_FV(Table134567810[[#This Row],[Company]],"P/E",TRUE)} -> 0 | H121: {=_FV(Table134567810[[#This Row],[Company]],"Beta")} -> 0.8752 | I121: =Table134567810[[#This Row],[MarketCap]]/Table134567810[[#This Row],[Employees]] -> 149523.73 | J121: =Table134567810[[#This Row],[Value]] / SUM(Table134567810[Value]) -> 0.067716476
A122: #VALUE! | B122: {=_FV(A122,"Price")} -> 3.26 | C122: 300 | D122: =IFERROR(Table134567810[[#This Row],[Price]]*Table134567810[[#This Row],[Number of shares]],0) -> 978 | E122: {=_FV(Table134567810[[#This Row],[Company]],"Employees")} -> 641 | F122: {=_FV(Table134567810[[#This Row],[Company]],"Market cap",TRUE)} -> 322215596 | G122: {=_FV(Table134567810[[#This Row],[Company]],"P/E",TRUE)} -> 0 | H122: {=_FV(Table134567810[[#This Row],[Company]],"Beta")} -> 0.1904 | I122: =Table134567810[[#This Row],[MarketCap]]/Table134567810[[#This Row],[Employees]] -> 502676.44 | J122: =Table134567810[[#This Row],[Value]] / SUM(Table134567810[Value]) -> 0.15543988
...

Sheet Secondary Theme
A1: Secondary Theme Analysis
D2: =SUM(Table33[Target]) -> 0
A4: Secondary theme | B4: Stock Exposure | C4: Percentage of Stock Exposure | D4: Target | E4: Option Exposure | F4: Combined Exposure | G4: Percentage of Total
A5: Health Care: Value Care | B5: =SUMIF(Table19[Secondary theme],Table33[[#This Row],[Secondary theme]],Table19[Stock Exposure]) -> 5396.705 | C5: =Table33[[#This Row],[Stock Exposure]]/'Primary Theme'!$D$5 -> 0.041205242 | E5: =SUMIF(Table19[Secondary theme],Table33[[#This Row],[Secondary theme]],Table19[Option Exposure]) -> 0 | F5: =Table33[[#This Row],[Stock Exposure]]+Table33[[#This Row],[Option Exposure]] -> 5396.705 | G5: =Table33[[#This Row],[Combined Exposure]]/'Primary Theme'!$D$4 -> 0.034015973
A6: Technology | B6: =SUMIF(Table19[Secondary theme],Table33[[#This Row],[Secondary theme]],Table19[Stock Exposure]) -> 8853.1435 | C6: =Table33[[#This Row],[Stock Exposure]]/'Primary Theme'!$D$5 -> 0.067596046 | E6: =SUMIF(Table19[Secondary theme],Table33[[#This Row],[Secondary theme]],Table19[Option Exposure]) -> 0 | F6: =Table33[[#This Row],[Stock Exposure]]+Table33[[#This Row],[Option Exposure]] -> 8853.1435 | G6: =Table33[[#This Row],[Combined Exposure]]/'Primary Theme'!$D$4 -> 0.055802252
A7: Industrials | B7: =SUMIF(Table19[Secondary theme],Table33[[#This Row],[Secondary theme]],Table19[Stock Exposure]) -> 15939.239 | C7: =Table33[[#This Row],[Stock Exposure]]/'Primary Theme'!$D$5 -> 0.12170023 | E7: =SUMIF(Table19[Secondary theme],Table33[[#This Row],[Secondary theme]],Table19[Option Exposure]) -> 0 | F7: =Table33[[#This Row],[Stock Exposure]]+Table33[[#This Row],[Option Exposure]] -> 15939.239 | G7: =Table33[[#This Row],[Combined Exposure]]/'Primary Theme'!$D$4 -> 0.10046663
A8: Crypto | B8: =SUMIF(Table19[Secondary theme],Table33[[#This Row],[Secondary theme]],Table19[Stock Exposure]) -> 1843.7925 | C8: =Table33[[#This Row],[Stock Exposure]]/'Primary Theme'!$D$5 -> 0.014077834 | E8: =SUMIF(Table19[Secondary theme],Table33[[#This Row],[Secondary theme]],Table19[Option Exposure]) -> 0 | F8: =Table33[[#This Row],[Stock Exposure]]+Table33[[#This Row],[Option Exposure]] -> 1843.7925 | G8: =Table33[[#This Row],[Combined Exposure]]/'Primary Theme'!$D$4 -> 0.011621609
A9: Drone | B9: =SUMIF(Table19[Secondary theme],Table33[[#This Row],[Secondary theme]],Table19[Stock Exposure]) -> 4265.405 | C9: =Table33[[#This Row],[Stock Exposure]]/'Primary Theme'!$D$5 -> 0.032567473 | E9: =SUMIF(Table19[Secondary theme],Table33[[#This Row],[Secondary theme]],Table19[Option Exposure]) -> 0 | F9: =Table33[[#This Row],[Stock Exposure]]+Table33[[#This Row],[Option Exposure]] -> 4265.405 | G9: =Table33[[#This Row],[Combined Exposure]]/'Primary Theme'!$D$4 -> 0.026885276
A10: Health Care | B10: =SUMIF(Table19[Secondary theme],Table33[[#This Row],[Secondary theme]],Table19[Stock Exposure]) -> 1911.8083 | C10: =Table33[[#This Row],[Stock Exposure]]/'Primary Theme'!$D$5 -> 0.014597152 | E10: =SUMIF(Table19[Secondary theme],Table33[[#This Row],[Secondary theme]],Table19[Option Exposure]) -> 0 | F10: =Table33[[#This Row],[Stock Exposure]]+Table33[[#This Row],[Option Exposure]] -> 1911.8083 | G10: =Table33[[#This Row],[Combined Exposure]]/'Primary Theme'!$D$4 -> 0.012050319
A11: Energy | B11: =SUMIF(Table19[Secondary theme],Table33[[#This Row],[Secondary theme]],Table19[Stock Exposure]) -> 18756.008 | C11: =Table33[[#This Row],[Stock Exposure]]/'Primary Theme'!$D$5 -> 0.14320699 | E11: =SUMIF(Table19[Secondary theme],Table33[[#This Row],[Secondary theme]],Table19[Option Exposure]) -> 4766.1976 | F11: =Table33[[#This Row],[Stock Exposure]]+Table33[[#This Row],[Option Exposure]] -> 23522.206 | G11: =Table33[[#This Row],[Combined Exposure]]/'Primary Theme'!$D$4 -> 0.14826282
A12: AI | B12: =SUMIF(Table19[Secondary theme],Table33[[#This Row],[Secondary theme]],Table19[Stock Exposure]) -> 15131.783 | C12: =Table33[[#This Row],[Stock Exposure]]/'Primary Theme'!$D$5 -> 0.11553509 | E12: =SUMIF(Table19[Secondary theme],Table33[[#This Row],[Secondary theme]],Table19[Option Exposure]) -> 0 | F12: =Table33[[#This Row],[Stock Exposure]]+Table33[[#This Row],[Option Exposure]] -> 15131.783 | G12: =Table33[[#This Row],[Combined Exposure]]/'Primary Theme'!$D$4 -> 0.095377146
A13: Auto | B13: =SUMIF(Table19[Secondary theme],Table33[[#This Row],[Secondary theme]],Table19[Stock Exposure]) -> 3718.09 | C13: =Table33[[#This Row],[Stock Exposure]]/'Primary Theme'!$D$5 -> 0.028388581 | E13: =SUMIF(Table19[Secondary theme],Table33[[#This Row],[Secondary theme]],Table19[Option Exposure]) -> 0 | F13: =Table33[[#This Row],[Stock Exposure]]+Table33[[#This Row],[Option Exposure]] -> 3718.09 | G13: =Table33[[#This Row],[Combined Exposure]]/'Primary Theme'!$D$4 -> 0.023435494
A14: Semiconductor | B14: =SUMIF(Table19[Secondary theme],Table33[[#This Row],[Secondary theme]],Table19[Stock Exposure]) -> 20302.661 | C14: =Table33[[#This Row],[Stock Exposure]]/'Primary Theme'!$D$5 -> 0.15501608 | E14: =SUMIF(Table19[Secondary theme],Table33[[#This Row],[Secondary theme]],Table19[Option Exposure]) -> 7135.6592 | F14: =Table33[[#This Row],[Stock Exposure]]+Table33[[#This Row],[Option Exposure]] -> 27438.32 | G14: =Table33[[#This Row],[Combined Exposure]]/'Primary Theme'!$D$4 -> 0.17294649
A15: Robotics | B15: =SUMIF(Table19[Secondary theme],Table33[[#This Row],[Secondary theme]],Table19[Stock Exposure]) -> 786.93 | C15: =Table33[[#This Row],[Stock Exposure]]/'Primary Theme'!$D$5 -> 0.0060084146 | E15: =SUMIF(Table19[Secondary theme],Table33[[#This Row],[Secondary theme]],Table19[Option Exposure]) -> 0 | F15: =Table33[[#This Row],[Stock Exposure]]+Table33[[#This Row],[Option Exposure]] -> 786.93 | G15: =Table33[[#This Row],[Combined Exposure]]/'Primary Theme'!$D$4 -> 0.0049600987
A16: Financials | B16: =SUMIF(Table19[Secondary theme],Table33[[#This Row],[Secondary theme]],Table19[Stock Exposure]) -> 0 | C16: =Table33[[#This Row],[Stock Exposure]]/'Primary Theme'!$D$5 -> 0 | E16: =SUMIF(Table19[Secondary theme],Table33[[#This Row],[Secondary theme]],Table19[Option Exposure]) -> 0 | F16: =Table33[[#This Row],[Stock Exposure]]+Table33[[#This Row],[Option Exposure]] -> 0 | G16: =Table33[[#This Row],[Combined Exposure]]/'Primary Theme'!$D$4 -> 0
... A93: Semiconductor: Materials | B93: =SUMIF(Table19[Secondary theme],Table33[[#This Row],[Secondary theme]],Table19[Stock Exposure]) -> 1413.798 | C93: =Table33[[#This Row],[Stock Exposure]]/'Primary Theme'!$D$5 -> 0.010794714 | E93: =SUMIF(Table19[Secondary theme],Table33[[#This Row],[Secondary theme]],Table19[Option Exposure]) -> 0 | F93: =Table33[[#This Row],[Stock Exposure]]+Table33[[#This Row],[Option Exposure]] -> 1413.798 | G93: =Table33[[#This Row],[Combined Exposure]]/'Primary Theme'!$D$4 -> 0.0089113106

Sheet Option Report
A1: Assets | B1: Ticker | C1: Asset type | D1: 52 week low | E1: Dis to 52 week low | F1: Current Price | G1: Dis to 52w high | H1: 52 week high | I1: Bullish | J1: Bearish | K1: Next Earning | L1: From Support | M1: From Resistance | N1: Latest Update | O1: Theme | P1: Signal
A2: {=_xlfn.UNIQUE(Table41[Asset Name],FALSE,FALSE)} -> #VALUE! | B2: =VLOOKUP(A2,Table41[#All],2,FALSE) -> MAG | C2: =VLOOKUP(A2,Table41[#All],20,FALSE) -> Stock | D2: {=_FV(A2,"52 week low",TRUE)} -> 11.72 | E2: =(Table44[[#This Row],[Current Price]]-Table44[[#This Row],[52 week low]])/Table44[[#This Row],[52 week low]] -> 1.087884 | F2: =VLOOKUP(A2,Table41[#All],15,FALSE) -> 24.47 | G2: =(Table44[[#This Row],[52 week high]]-Table44[[#This Row],[Current Price]])/Table44[[#This Row],[Current Price]] -> 0.025337148 | H2: {=_FV(A2,"52 week high",TRUE)} -> 25.09 | I2: =VLOOKUP(A2,Table41[#All],17,FALSE) -> FALSE | J2: =VLOOKUP(A2,Table41[#All],18,FALSE) -> TRUE | K2: =VLOOKUP(A2,Table41[#All],21,FALSE) -> 45588 | L2: =VLOOKUP(A2,Table41[#All],26,FALSE) -> 0.9576 | M2: =VLOOKUP(A2,Table41[#All],27,FALSE) -> 0.63133333 | N2: =HLOOKUP(Table44[[#This Row],[Theme]],Table46[#All],2,FALSE) -> 45567 | O2: =VLOOKUP(A2,Table41[#All],22,FALSE) -> Gold and Silver | P2: =VLOOKUP(A2,Table41[#All],25,FALSE) -> 🔻
A3: #VALUE! | B3: =VLOOKUP(A3,Table41[#All],2,FALSE) -> CLS | C3: =VLOOKUP(A3,Table41[#All],20,FALSE) -> Stock | D3: {=_FV(A3,"52 week low",TRUE)} -> 58.05 | E3: =(Table44[[#This Row],[Current Price]]-Table44[[#This Row],[52 week low]])/Table44[[#This Row],[52 week low]] -> 4.2944014 | F3: =VLOOKUP(A3,Table41[#All],15,FALSE) -> 307.34 | G3: =(Table44[[#This Row],[52 week high]]-Table44[[#This Row],[Current Price]])/Table44[[#This Row],[Current Price]] -> 0.18240385 | H3: {=_FV(A3,"52 week high",TRUE)} -> 363.4 | I3: =VLOOKUP(A3,Table41[#All],17,FALSE) -> FALSE | J3: =VLOOKUP(A3,Table41[#All],18,FALSE) -> TRUE | K3: =VLOOKUP(A3,Table41[#All],21,FALSE) -> 45588 | L3: =VLOOKUP(A3,Table41[#All],26,FALSE) -> 0 | M3: =VLOOKUP(A3,Table41[#All],27,FALSE) -> 2.84175 | N3: =HLOOKUP(Table44[[#This Row],[Theme]],Table46[#All],2,FALSE) -> 45587 | O3: =VLOOKUP(A3,Table41[#All],22,FALSE) -> AI | P3: =VLOOKUP(A3,Table41[#All],25,FALSE) -> 🔻
A4: #VALUE! | B4: =VLOOKUP(A4,Table41[#All],2,FALSE) -> SNAP | C4: =VLOOKUP(A4,Table41[#All],20,FALSE) -> Stock | D4: {=_FV(A4,"52 week low",TRUE)} -> 4.31 | E4: =(Table44[[#This Row],[Current Price]]-Table44[[#This Row],[52 week low]])/Table44[[#This Row],[52 week low]] -> 0.056844548 | F4: =VLOOKUP(A4,Table41[#All],15,FALSE) -> 4.555 | G4: =(Table44[[#This Row],[52 week high]]-Table44[[#This Row],[Current Price]])/Table44[[#This Row],[Current Price]] -> 1.2854007 | H4: {=_FV(A4,"52 week high",TRUE)} -> 10.41 | I4: =VLOOKUP(A4,Table41[#All],17,FALSE) -> TRUE | J4: =VLOOKUP(A4,Table41[#All],18,FALSE) -> FALSE | K4: =VLOOKUP(A4,Table41[#All],21,FALSE) -> 0 | L4: =VLOOKUP(A4,Table41[#All],26,FALSE) -> -0.5445 | M4: =VLOOKUP(A4,Table41[#All],27,FALSE) -> -0.67464286 | N4: =HLOOKUP(Table44[[#This Row],[Theme]],Table46[#All],2,FALSE) -> 45594 | O4: =VLOOKUP(A4,Table41[#All],22,FALSE) -> Technology | P4: =VLOOKUP(A4,Table41[#All],25,FALSE) -> ✅
A5: #VALUE! | B5: =VLOOKUP(A5,Table41[#All],2,FALSE) -> SPY | C5: =VLOOKUP(A5,Table41[#All],20,FALSE) -> ETF | D5: {=_FV(A5,"52 week low",TRUE)} -> 481.8 | E5: =(Table44[[#This Row],[Current Price]]-Table44[[#This Row],[52 week low]])/Table44[[#This Row],[52 week low]] -> 0.36693649 | F5: =VLOOKUP(A5,Table41[#All],15,FALSE) -> 658.59 | G5: =(Table44[[#This Row],[52 week high]]-Table44[[#This Row],[Current Price]])/Table44[[#This Row],[Current Price]] -> 0.059597018 | H5: {=_FV(A5,"52 week high",TRUE)} -> 697.84 | I5: =VLOOKUP(A5,Table41[#All],17,FALSE) -> FALSE | J5: =VLOOKUP(A5,Table41[#All],18,FALSE) -> TRUE | K5: =VLOOKUP(A5,Table41[#All],21,FALSE) -> 0 | L5: =VLOOKUP(A5,Table41[#All],26,FALSE) -> 0.17605357 | M5: =VLOOKUP(A5,Table41[#All],27,FALSE) -> 0.11625424 | N5: =HLOOKUP(Table44[[#This Row],[Theme]],Table46[#All],2,FALSE) -> 45564 | O5: =VLOOKUP(A5,Table41[#All],22,FALSE) -> Market | P5: =VLOOKUP(A5,Table41[#All],25,FALSE) -> 🔻
A6: #VALUE! | B6: =VLOOKUP(A6,Table41[#All],2,FALSE) -> RMBS | C6: =VLOOKUP(A6,Table41[#All],20,FALSE) -> Stock | D6: {=_FV(A6,"52 week low",TRUE)} -> 40.12 | E6: =(Table44[[#This Row],[Current Price]]-Table44[[#This Row],[52 week low]])/Table44[[#This Row],[52 week low]] -> 1.3199153 | F6: =VLOOKUP(A6,Table41[#All],15,FALSE) -> 93.075 | G6: =(Table44[[#This Row],[52 week high]]-Table44[[#This Row],[Current Price]])/Table44[[#This Row],[Current Price]] -> 0.45850121 | H6: {=_FV(A6,"52 week high",TRUE)} -> 135.75 | I6: =VLOOKUP(A6,Table41[#All],17,FALSE) -> FALSE | J6: =VLOOKUP(A6,Table41[#All],18,FALSE) -> TRUE | K6: =VLOOKUP(A6,Table41[#All],21,FALSE) -> 45593 | L6: =VLOOKUP(A6,Table41[#All],26,FALSE) -> 0.95947368 | M6: =VLOOKUP(A6,Table41[#All],27,FALSE) -> 0.77285714 | N6: =HLOOKUP(Table44[[#This Row],[Theme]],Table46[#All],2,FALSE) -> 45580 | O6: =VLOOKUP(A6,Table41[#All],22,FALSE) -> Semiconductor | P6: =VLOOKUP(A6,Table41[#All],25,FALSE) -> 🔻
A7: #VALUE! | B7: =VLOOKUP(A7,Table41[#All],2,FALSE) -> AG | C7: =VLOOKUP(A7,Table41[#All],20,FALSE) -> Stock | D7: {=_FV(A7,"52 week low",TRUE)} -> 5.185 | E7: =(Table44[[#This Row],[Current Price]]-Table44[[#This Row],[52 week low]])/Table44[[#This Row],[52 week low]] -> 3.0086789 | F7: =VLOOKUP(A7,Table41[#All],15,FALSE) -> 20.785 | G7: =(Table44[[#This Row],[52 week high]]-Table44[[#This Row],[Current Price]])/Table44[[#This Row],[Current Price]] -> 0.54125571 | H7: {=_FV(A7,"52 week high",TRUE)} -> 32.035 | I7: =VLOOKUP(A7,Table41[#All],17,FALSE) -> FALSE | J7: =VLOOKUP(A7,Table41[#All],18,FALSE) -> TRUE | K7: =VLOOKUP(A7,Table41[#All],21,FALSE) -> 45603 | L7: =VLOOKUP(A7,Table41[#All],26,FALSE) -> 3.157 | M7: =VLOOKUP(A7,Table41[#All],27,FALSE) -> 1.9692857 | N7: =HLOOKUP(Table44[[#This Row],[Theme]],Table46[#All],2,FALSE) -> 45567 | O7: =VLOOKUP(A7,Table41[#All],22,FALSE) -> Gold and Silver | P7: =VLOOKUP(A7,Table41[#All],25,FALSE) -> 🔻
A8: #VALUE! | B8: =VLOOKUP(A8,Table41[#All],2,FALSE) -> VIX | C8: =VLOOKUP(A8,Table41[#All],20,FALSE) -> Index | D8: {=_FV(A8,"52 week low",TRUE)} -> 13.38 | E8: =(Table44[[#This Row],[Current Price]]-Table44[[#This Row],[52 week low]])/Table44[[#This Row],[52 week low]] -> 0.89312407 | F8: =VLOOKUP(A8,Table41[#All],15,FALSE) -> 25.33 | G8: =(Table44[[#This Row],[52 week high]]-Table44[[#This Row],[Current Price]])/Table44[[#This Row],[Current Price]] -> 1.373865 | H8: {=_FV(A8,"52 week high",TRUE)} -> 60.13 | I8: =VLOOKUP(A8,Table41[#All],17,FALSE) -> FALSE | J8: =VLOOKUP(A8,Table41[#All],18,FALSE) -> TRUE | K8: =VLOOKUP(A8,Table41[#All],21,FALSE) -> 0 | L8: =VLOOKUP(A8,Table41[#All],26,FALSE) -> 0 | M8: =VLOOKUP(A8,Table41[#All],27,FALSE) -> 0.2665 | N8: =HLOOKUP(Table44[[#This Row],[Theme]],Table46[#All],2,FALSE) -> 45564 | O8: =VLOOKUP(A8,Table41[#All],22,FALSE) -> Market | P8: =VLOOKUP(A8,Table41[#All],25,FALSE) -> 🔻
A9: #VALUE! | B9: =VLOOKUP(A9,Table41[#All],2,FALSE) -> CSCO | C9: =VLOOKUP(A9,Table41[#All],20,FALSE) -> Stock | D9: {=_FV(A9,"52 week low",TRUE)} -> 52.11 | E9: =(Table44[[#This Row],[Current Price]]-Table44[[#This Row],[52 week low]])/Table44[[#This Row],[52 week low]] -> 0.58558818 | F9: =VLOOKUP(A9,Table41[#All],15,FALSE) -> 82.625 | G9: =(Table44[[#This Row],[52 week high]]-Table44[[#This Row],[Current Price]])/Table44[[#This Row],[Current Price]] -> 0.067291982 | H9: {=_FV(A9,"52 week high",TRUE)} -> 88.185 | I9: =VLOOKUP(A9,Table41[#All],17,FALSE) -> FALSE | J9: =VLOOKUP(A9,Table41[#All],18,FALSE) -> TRUE | K9: =VLOOKUP(A9,Table41[#All],21,FALSE) -> 45609 | L9: =VLOOKUP(A9,Table41[#All],26,FALSE) -> 0.6525 | M9: =VLOOKUP(A9,Table41[#All],27,FALSE) -> 0.43695652 | N9: =HLOOKUP(Table44[[#This Row],[Theme]],Table46[#All],2,FALSE) -> 45602 | O9: =VLOOKUP(A9,Table41[#All],22,FALSE) -> Connectivity | P9: =VLOOKUP(A9,Table41[#All],25,FALSE) -> 🔻
A10: #VALUE! | B10: =VLOOKUP(A10,Table41[#All],2,FALSE) -> FNV | C10: =VLOOKUP(A10,Table41[#All],20,FALSE) -> Stock | D10: {=_FV(A10,"52 week low",TRUE)} -> 140.03 | E10: =(Table44[[#This Row],[Current Price]]-Table44[[#This Row],[52 week low]])/Table44[[#This Row],[52 week low]] -> 0.68013997 | F10: =VLOOKUP(A10,Table41[#All],15,FALSE) -> 235.27 | G10: =(Table44[[#This Row],[52 week high]]-Table44[[#This Row],[Current Price]])/Table44[[#This Row],[Current Price]] -> 0.21422196 | H10: {=_FV(A10,"52 week high",TRUE)} -> 285.67 | I10: =VLOOKUP(A10,Table41[#All],17,FALSE) -> FALSE | J10: =VLOOKUP(A10,Table41[#All],18,FALSE) -> TRUE | K10: =VLOOKUP(A10,Table41[#All],21,FALSE) -> 45610 | L10: =VLOOKUP(A10,Table41[#All],26,FALSE) -> 0.96058333 | M10: =VLOOKUP(A10,Table41[#All],27,FALSE) -> 0.80976923 | N10: =HLOOKUP(Table44[[#This Row],[Theme]],Table46[#All],2,FALSE) -> 45567 | O10: =VLOOKUP(A10,Table41[#All],22,FALSE) -> Gold and Silver | P10: =VLOOKUP(A10,Table41[#All],25,FALSE) -> 🔻
A11: #VALUE! | B11: =VLOOKUP(A11,Table41[#All],2,FALSE) -> URA | C11: =VLOOKUP(A11,Table41[#All],20,FALSE) -> ETF | D11: {=_FV(A11,"52 week low",TRUE)} -> 19.5 | E11: =(Table44[[#This Row],[Current Price]]-Table44[[#This Row],[52 week low]])/Table44[[#This Row],[52 week low]] -> 1.5595846 | F11: =VLOOKUP(A11,Table41[#All],15,FALSE) -> 49.9119 | G11: =(Table44[[#This Row],[52 week high]]-Table44[[#This Row],[Current Price]])/Table44[[#This Row],[Current Price]] -> 0.24779862 | H11: {=_FV(A11,"52 week high",TRUE)} -> 62.28 | I11: =VLOOKUP(A11,Table41[#All],17,FALSE) -> FALSE | J11: =VLOOKUP(A11,Table41[#All],18,FALSE) -> TRUE | K11: =VLOOKUP(A11,Table41[#All],21,FALSE) -> 0 | L11: =VLOOKUP(A11,Table41[#All],26,FALSE) -> 1.3767571 | M11: =VLOOKUP(A11,Table41[#All],27,FALSE) -> 0.66373 | N11: =HLOOKUP(Table44[[#This Row],[Theme]],Table46[#All],2,FALSE) -> 45569 | O11: =VLOOKUP(A11,Table41[#All],22,FALSE) -> Nuclear | P11: =VLOOKUP(A11,Table41[#All],25,FALSE) -> 🔻
A12: #VALUE! | B12: =VLOOKUP(A12,Table41[#All],2,FALSE) -> SMR | C12: =VLOOKUP(A12,Table41[#All],20,FALSE) -> Stock | D12: {=_FV(A12,"52 week low",TRUE)} -> 11.08 | E12: =(Table44[[#This Row],[Current Price]]-Table44[[#This Row],[52 week low]])/Table44[[#This Row],[52 week low]] -> 0.067680505 | F12: =VLOOKUP(A12,Table41[#All],15,FALSE) -> 11.8299 | G12: =(Table44[[#This Row],[52 week high]]-Table44[[#This Row],[Current Price]])/Table44[[#This Row],[Current Price]] -> 3.8538027 | H12: {=_FV(A12,"52 week high",TRUE)} -> 57.42 | I12: =VLOOKUP(A12,Table41[#All],17,FALSE) -> TRUE | J12: =VLOOKUP(A12,Table41[#All],18,FALSE) -> FALSE | K12: =VLOOKUP(A12,Table41[#All],21,FALSE) -> 45603 | L12: =VLOOKUP(A12,Table41[#All],26,FALSE) -> -0.26063125 | M12: =VLOOKUP(A12,Table41[#All],27,FALSE) -> -0.408505 | N12: =HLOOKUP(Table44[[#This Row],[Theme]],Table46[#All],2,FALSE) -> 45569 | O12: =VLOOKUP(A12,Table41[#All],22,FALSE) -> Nuclear | P12: =VLOOKUP(A12,Table41[#All],25,FALSE) -> ✅
A13: #VALUE! | B13: =VLOOKUP(A13,Table41[#All],2,FALSE) -> GM | C13: =VLOOKUP(A13,Table41[#All],20,FALSE) -> Stock | D13: {=_FV(A13,"52 week low",TRUE)} -> 41.6 | E13: =(Table44[[#This Row],[Current Price]]-Table44[[#This Row],[52 week low]])/Table44[[#This Row],[52 week low]] -> 0.87127404 | F13: =VLOOKUP(A13,Table41[#All],15,FALSE) -> 77.845 | G13: =(Table44[[#This Row],[52 week high]]-Table44[[#This Row],[Current Price]])/Table44[[#This Row],[Current Price]] -> 0.12557004 | H13: {=_FV(A13,"52 week high",TRUE)} -> 87.62 | I13: =VLOOKUP(A13,Table41[#All],17,FALSE) -> FALSE | J13: =VLOOKUP(A13,Table41[#All],18,FALSE) -> TRUE | K13: =VLOOKUP(A13,Table41[#All],21,FALSE) -> 0 | L13: =VLOOKUP(A13,Table41[#All],26,FALSE) -> 0 | M13: =VLOOKUP(A13,Table41[#All],27,FALSE) -> 0.5569 | N13: =HLOOKUP(Table44[[#This Row],[Theme]],Table46[#All],2,FALSE) -> 45575 | O13: =VLOOKUP(A13,Table41[#All],22,FALSE) -> Auto | P13: =VLOOKUP(A13,Table41[#All],25,FALSE) -> 🔻
A14: #VALUE! | B14: =VLOOKUP(A14,Table41[#All],2,FALSE) -> GDX | C14: =VLOOKUP(A14,Table41[#All],20,FALSE) -> ETF | D14: {=_FV(A14,"52 week low",TRUE)} -> 40.26 | E14: =(Table44[[#This Row],[Current Price]]-Table44[[#This Row],[52 week low]])/Table44[[#This Row],[52 week low]] -> 1.1624441 | F14: =VLOOKUP(A14,Table41[#All],15,FALSE) -> 87.06 | G14: =(Table44[[#This Row],[52 week high]]-Table44[[#This Row],[Current Price]])/Table44[[#This Row],[Current Price]] -> 0.34591087 | H14: {=_FV(A14,"52 week high",TRUE)} -> 117.175 | I14: =VLOOKUP(A14,Table41[#All],17,FALSE) -> FALSE | J14: =VLOOKUP(A14,Table41[#All],18,FALSE) -> TRUE | K14: =VLOOKUP(A14,Table41[#All],21,FALSE) -> 0 | L14: =VLOOKUP(A14,Table41[#All],26,FALSE) -> 1.2323077 | M14: =VLOOKUP(A14,Table41[#All],27,FALSE) -> 1.1765 | N14: =HLOOKUP(Table44[[#This Row],[Theme]],Table46[#All],2,FALSE) -> 45567 | O14: =VLOOKUP(A14,Table41[#All],22,FALSE) -> Gold and Silver | P14: =VLOOKUP(A14,Table41[#All],25,FALSE) -> 🔻
... A122: #VALUE! | B122: =VLOOKUP(A122,Table41[#All],2,FALSE) -> ACHC | C122: =VLOOKUP(A122,Table41[#All],20,FALSE) -> Stock | D122: {=_FV(A122,"52 week low",TRUE)} -> 11.43 | E122: =(Table44[[#This Row],[Current Price]]-Table44[[#This Row],[52 week low]])/Table44[[#This Row],[52 week low]] -> 1.0804899 | F122: =VLOOKUP(A122,Table41[#All],15,FALSE) -> 23.78 | G122: =(Table44[[#This Row],[52 week high]]-Table44[[#This Row],[Current Price]])/Table44[[#This Row],[Current Price]] -> 0.30529857 | H122: {=_FV(A122,"52 week high",TRUE)} -> 31.04 | I122: =VLOOKUP(A122,Table41[#All],17,FALSE) -> FALSE | J122: =VLOOKUP(A122,Table41[#All],18,FALSE) -> TRUE | K122: =VLOOKUP(A122,Table41[#All],21,FALSE) -> 0 | L122: =VLOOKUP(A122,Table41[#All],26,FALSE) -> 0 | M122: =VLOOKUP(A122,Table41[#All],27,FALSE) -> #DIV/0! | N122: =HLOOKUP(Table44[[#This Row],[Theme]],Table46[#All],2,FALSE) -> 45567 | O122: =VLOOKUP(A122,Table41[#All],22,FALSE) -> Health Care | P122: =VLOOKUP(A122,Table41[#All],25,FALSE) -> 🔻

Sheet Primary Theme
A1: Primary Theme Analysis
B3: Primary | C3: Secondary | D3: From Equity Portfolio
A4: Total Exposure | B4: =SUM(Table21[[#All],[Combined Exposure]]) -> 156139.91 | C4: =C5+C6 -> 159591.92 | D4: =EquityPortfolio!B8 -> 158652.08
A5: Stock Exposure | B5: =SUM(Table21[[#All],[Stock Exposure]]) -> 128459.15 | C5: =SUM(Table33[[#All],[Stock Exposure]]) -> 131911.16 | D5: =EquityPortfolio!B9 -> 130971.32
A6: Option Exposure | B6: =SUM(Table21[[#All],[Option Exposure]]) -> 27680.762 | C6: =SUM(Table33[Option Exposure]) -> 27680.762 | D6: =EquityPortfolio!B10 -> 27680.762
D8: =SUM(Table21[Percentage of Stock Exposure]) -> 0.98081893 | E8: =SUM(Table21[Target]) -> 1.02 | H8: =SUM(Table21[Realized Profit]) -> 12649.953 | I8: =SUM(Table21[Unrealized Profit]) -> 33713.259
A10: Primary theme | B10: Stock Exposure | C10: Cost basis | D10: Percentage of Stock Exposure | E10: Target | F10: Option Exposure | G10: Combined Exposure | H10: Percentage of Total | I10: Realized Profit | J10: Unrealized Profit | K10: Percentage in profit | L10: Over allocated
A11: AI | B11: =SUMIF(Table19[[#All],[Primary theme]],Table21[[#This Row],[Primary theme]],Table19[[#All],[Stock Exposure]]) -> 25215.576 | C11: =SUMIF(Table19[[#All],[Primary theme]],Table21[[#This Row],[Primary theme]],Table19[[#All],[Cost of current position]]) -> 18075.068 | D11: =Table21[[#This Row],[Stock Exposure]]/$D$5 -> 0.19252746 | E11: 0.1 | F11: =SUMIF(Table19[[#All],[Primary theme]],Table21[[#This Row],[Primary theme]],Table19[[#All],[Option Exposure]]) -> 7135.6592 | G11: =Table21[[#This Row],[Option Exposure]]+Table21[[#This Row],[Stock Exposure]] -> 32351.235 | H11: =Table21[[#This Row],[Combined Exposure]]/$D$4 -> 0.20391308 | I11: =SUMIF(Table19[Primary theme],Table21[[#This Row],[Primary theme]],Table19[Realized Profit]) -> 1333.1755 | J11: =SUMIF(Table19[Primary theme],Table21[[#This Row],[Primary theme]],Table19[Unrealized Profit]) -> 7140.5085 | K11: =IFERROR(Table21[[#This Row],[Unrealized Profit]]/Table21[[#This Row],[Cost basis]],"") -> 0.39504741 | L11: =IF(Table21[[#This Row],[Percentage of Stock Exposure]]>Table21[[#This Row],[Target]],TRUE,FALSE) -> TRUE
A12: Health Care | B12: =SUMIF(Table19[[#All],[Primary theme]],Table21[[#This Row],[Primary theme]],Table19[[#All],[Stock Exposure]]) -> 10338.291 | C12: =SUMIF(Table19[[#All],[Primary theme]],Table21[[#This Row],[Primary theme]],Table19[[#All],[Cost of current position]]) -> 12782.789 | D12: =Table21[[#This Row],[Stock Exposure]]/$D$5 -> 0.078935535 | E12: 0.2 | F12: =SUMIF(Table19[[#All],[Primary theme]],Table21[[#This Row],[Primary theme]],Table19[[#All],[Option Exposure]]) -> 0 | G12: =Table21[[#This Row],[Option Exposure]]+Table21[[#This Row],[Stock Exposure]] -> 10338.291 | H12: =Table21[[#This Row],[Combined Exposure]]/$D$4 -> 0.065163287 | I12: =SUMIF(Table19[Primary theme],Table21[[#This Row],[Primary theme]],Table19[Realized Profit]) -> -6397.8231 | J12: =SUMIF(Table19[Primary theme],Table21[[#This Row],[Primary theme]],Table19[Unrealized Profit]) -> -2444.4974 | K12: =IFERROR(Table21[[#This Row],[Unrealized Profit]]/Table21[[#This Row],[Cost basis]],"") -> -0.1912335 | L12: =IF(Table21[[#This Row],[Percentage of Stock Exposure]]>Table21[[#This Row],[Target]],TRUE,FALSE) -> FALSE
A13: Energy | B13: =SUMIF(Table19[[#All],[Primary theme]],Table21[[#This Row],[Primary theme]],Table19[[#All],[Stock Exposure]]) -> 22092.808 | C13: =SUMIF(Table19[[#All],[Primary theme]],Table21[[#This Row],[Primary theme]],Table19[[#All],[Cost of current position]]) -> 15400.002 | D13: =Table21[[#This Row],[Stock Exposure]]/$D$5 -> 0.16868432 | E13: 0.1 | F13: =SUMIF(Table19[[#All],[Primary theme]],Table21[[#This Row],[Primary theme]],Table19[[#All],[Option Exposure]]) -> 4766.1976 | G13: =Table21[[#This Row],[Option Exposure]]+Table21[[#This Row],[Stock Exposure]] -> 26859.006 | H13: =Table21[[#This Row],[Combined Exposure]]/$D$4 -> 0.16929501 | I13: =SUMIF(Table19[Primary theme],Table21[[#This Row],[Primary theme]],Table19[Realized Profit]) -> -2134.8569 | J13: =SUMIF(Table19[Primary theme],Table21[[#This Row],[Primary theme]],Table19[Unrealized Profit]) -> 6692.8064 | K13: =IFERROR(Table21[[#This Row],[Unrealized Profit]]/Table21[[#This Row],[Cost basis]],"") -> 0.43459777 | L13: =IF(Table21[[#This Row],[Percentage of Stock Exposure]]>Table21[[#This Row],[Target]],TRUE,FALSE) -> TRUE
A14: Semiconductor | B14: =SUMIF(Table19[[#All],[Primary theme]],Table21[[#This Row],[Primary theme]],Table19[[#All],[Stock Exposure]]) -> 17535.553 | C14: =SUMIF(Table19[[#All],[Primary theme]],Table21[[#This Row],[Primary theme]],Table19[[#All],[Cost of current position]]) -> 12052.078 | D14: =Table21[[#This Row],[Stock Exposure]]/$D$5 -> 0.13388849 | E14: 0.03 | F14: =SUMIF(Table19[[#All],[Primary theme]],Table21[[#This Row],[Primary theme]],Table19[[#All],[Option Exposure]]) -> 0 | G14: =Table21[[#This Row],[Option Exposure]]+Table21[[#This Row],[Stock Exposure]] -> 17535.553 | H14: =Table21[[#This Row],[Combined Exposure]]/$D$4 -> 0.11052835 | I14: =SUMIF(Table19[Primary theme],Table21[[#This Row],[Primary theme]],Table19[Realized Profit]) -> 814.83797 | J14: =SUMIF(Table19[Primary theme],Table21[[#This Row],[Primary theme]],Table19[Unrealized Profit]) -> 5483.475 | K14: =IFERROR(Table21[[#This Row],[Unrealized Profit]]/Table21[[#This Row],[Cost basis]],"") -> 0.45498171 | L14: =IF(Table21[[#This Row],[Percentage of Stock Exposure]]>Table21[[#This Row],[Target]],TRUE,FALSE) -> TRUE
A15: Bitcoin mining | B15: =SUMIF(Table19[[#All],[Primary theme]],Table21[[#This Row],[Primary theme]],Table19[[#All],[Stock Exposure]]) -> 10475.983 | C15: =SUMIF(Table19[[#All],[Primary theme]],Table21[[#This Row],[Primary theme]],Table19[[#All],[Cost of current position]]) -> 8324.4266 | D15: =Table21[[#This Row],[Stock Exposure]]/$D$5 -> 0.079986846 | E15: 0.07 | F15: =SUMIF(Table19[[#All],[Primary theme]],Table21[[#This Row],[Primary theme]],Table19[[#All],[Option Exposure]]) -> 0 | G15: =Table21[[#This Row],[Option Exposure]]+Table21[[#This Row],[Stock Exposure]] -> 10475.983 | H15: =Table21[[#This Row],[Combined Exposure]]/$D$4 -> 0.066031171 | I15: =SUMIF(Table19[Primary theme],Table21[[#This Row],[Primary theme]],Table19[Realized Profit]) -> -2987.3734 | J15: =SUMIF(Table19[Primary theme],Table21[[#This Row],[Primary theme]],Table19[Unrealized Profit]) -> 2151.5563 | K15: =IFERROR(Table21[[#This Row],[Unrealized Profit]]/Table21[[#This Row],[Cost basis]],"") -> 0.258463 | L15: =IF(Table21[[#This Row],[Percentage of Stock Exposure]]>Table21[[#This Row],[Target]],TRUE,FALSE) -> TRUE
A16: Defense | B16: =SUMIF(Table19[[#All],[Primary theme]],Table21[[#This Row],[Primary theme]],Table19[[#All],[Stock Exposure]]) -> 13867.132 | C16: =SUMIF(Table19[[#All],[Primary theme]],Table21[[#This Row],[Primary theme]],Table19[[#All],[Cost of current position]]) -> 9228.18 | D16: =Table21[[#This Row],[Stock Exposure]]/$D$5 -> 0.10587915 | E16: 0 | F16: =SUMIF(Table19[[#All],[Primary theme]],Table21[[#This Row],[Primary theme]],Table19[[#All],[Option Exposure]]) -> 0 | G16: =Table21[[#This Row],[Option Exposure]]+Table21[[#This Row],[Stock Exposure]] -> 13867.132 | H16: =Table21[[#This Row],[Combined Exposure]]/$D$4 -> 0.087405922 | I16: =SUMIF(Table19[Primary theme],Table21[[#This Row],[Primary theme]],Table19[Realized Profit]) -> 8124.921 | J16: =SUMIF(Table19[Primary theme],Table21[[#This Row],[Primary theme]],Table19[Unrealized Profit]) -> 4638.9516 | K16: =IFERROR(Table21[[#This Row],[Unrealized Profit]]/Table21[[#This Row],[Cost basis]],"") -> 0.50269409 | L16: =IF(Table21[[#This Row],[Percentage of Stock Exposure]]>Table21[[#This Row],[Target]],TRUE,FALSE) -> TRUE
A17: Robotics | B17: =SUMIF(Table19[[#All],[Primary theme]],Table21[[#This Row],[Primary theme]],Table19[[#All],[Stock Exposure]]) -> 8640.34 | C17: =SUMIF(Table19[[#All],[Primary theme]],Table21[[#This Row],[Primary theme]],Table19[[#All],[Cost of current position]]) -> 3859.0748 | D17: =Table21[[#This Row],[Stock Exposure]]/$D$5 -> 0.065971237 | E17: 0 | F17: =SUMIF(Table19[[#All],[Primary theme]],Table21[[#This Row],[Primary theme]],Table19[[#All],[Option Exposure]]) -> 0 | G17: =Table21[[#This Row],[Option Exposure]]+Table21[[#This Row],[Stock Exposure]] -> 8640.34 | H17: =Table21[[#This Row],[Combined Exposure]]/$D$4 -> 0.05446093 | I17: =SUMIF(Table19[Primary theme],Table21[[#This Row],[Primary theme]],Table19[Realized Profit]) -> 3101.7748 | J17: =SUMIF(Table19[Primary theme],Table21[[#This Row],[Primary theme]],Table19[Unrealized Profit]) -> 4854.2352 | K17: =IFERROR(Table21[[#This Row],[Unrealized Profit]]/Table21[[#This Row],[Cost basis]],"") -> 1.2578754 | L17: =IF(Table21[[#This Row],[Percentage of Stock Exposure]]>Table21[[#This Row],[Target]],TRUE,FALSE) -> TRUE
A18: Industrials | B18: =SUMIF(Table19[[#All],[Primary theme]],Table21[[#This Row],[Primary theme]],Table19[[#All],[Stock Exposure]]) -> 12136.151 | C18: =SUMIF(Table19[[#All],[Primary theme]],Table21[[#This Row],[Primary theme]],Table19[[#All],[Cost of current position]]) -> 10123.803 | D18: =Table21[[#This Row],[Stock Exposure]]/$D$5 -> 0.09266266 | E18: 0.03 | F18: =SUMIF(Table19[[#All],[Primary theme]],Table21[[#This Row],[Primary theme]],Table19[[#All],[Option Exposure]]) -> 0 | G18: =Table21[[#This Row],[Option Exposure]]+Table21[[#This Row],[Stock Exposure]] -> 12136.151 | H18: =Table21[[#This Row],[Combined Exposure]]/$D$4 -> 0.076495377 | I18: =SUMIF(Table19[Primary theme],Table21[[#This Row],[Primary theme]],Table19[Realized Profit]) -> 1143.9931 | J18: =SUMIF(Table19[Primary theme],Table21[[#This Row],[Primary theme]],Table19[Unrealized Profit]) -> 2012.3479 | K18: =IFERROR(Table21[[#This Row],[Unrealized Profit]]/Table21[[#This Row],[Cost basis]],"") -> 0.19877391 | L18: =IF(Table21[[#This Row],[Percentage of Stock Exposure]]>Table21[[#This Row],[Target]],TRUE,FALSE) -> TRUE
A19: Technology | B19: =SUMIF(Table19[[#All],[Primary theme]],Table21[[#This Row],[Primary theme]],Table19[[#All],[Stock Exposure]]) -> 1713.505 | C19: =SUMIF(Table19[[#All],[Primary theme]],Table21[[#This Row],[Primary theme]],Table19[[#All],[Cost of current position]]) -> 1891.1596 | D19: =Table21[[#This Row],[Stock Exposure]]/$D$5 -> 0.013083055 | E19: 0.02 | F19: =SUMIF(Table19[[#All],[Primary theme]],Table21[[#This Row],[Primary theme]],Table19[[#All],[Option Exposure]]) -> 0 | G19: =Table21[[#This Row],[Option Exposure]]+Table21[[#This Row],[Stock Exposure]] -> 1713.505 | H19: =Table21[[#This Row],[Combined Exposure]]/$D$4 -> 0.010800394 | I19: =SUMIF(Table19[Primary theme],Table21[[#This Row],[Primary theme]],Table19[Realized Profit]) -> 903.4596 | J19: =SUMIF(Table19[Primary theme],Table21[[#This Row],[Primary theme]],Table19[Unrealized Profit]) -> 677.5954 | K19: =IFERROR(Table21[[#This Row],[Unrealized Profit]]/Table21[[#This Row],[Cost basis]],"") -> 0.35829626 | L19: =IF(Table21[[#This Row],[Percentage of Stock Exposure]]>Table21[[#This Row],[Target]],TRUE,FALSE) -> FALSE
A20: Financials | B20: =SUMIF(Table19[[#All],[Primary theme]],Table21[[#This Row],[Primary theme]],Table19[[#All],[Stock Exposure]]) -> 1932.4775 | C20: =SUMIF(Table19[[#All],[Primary theme]],Table21[[#This Row],[Primary theme]],Table19[[#All],[Cost of current position]]) -> 1068.3817 | D20: =Table21[[#This Row],[Stock Exposure]]/$D$5 -> 0.014754967 | E20: 0.03 | F20: =SUMIF(Table19[[#All],[Primary theme]],Table21[[#This Row],[Primary theme]],Table19[[#All],[Option Exposure]]) -> 0 | G20: =Table21[[#This Row],[Option Exposure]]+Table21[[#This Row],[Stock Exposure]] -> 1932.4775 | H20: =Table21[[#This Row],[Combined Exposure]]/$D$4 -> 0.0121806 | I20: =SUMIF(Table19[Primary theme],Table21[[#This Row],[Primary theme]],Table19[Realized Profit]) -> -1483.1683 | J20: =SUMIF(Table19[Primary theme],Table21[[#This Row],[Primary theme]],Table19[Unrealized Profit]) -> 864.09582 | K20: =IFERROR(Table21[[#This Row],[Unrealized Profit]]/Table21[[#This Row],[Cost basis]],"") -> 0.80878944 | L20: =IF(Table21[[#This Row],[Percentage of Stock Exposure]]>Table21[[#This Row],[Target]],TRUE,FALSE) -> FALSE
A21: Nuclear | B21: =SUMIF(Table19[[#All],[Primary theme]],Table21[[#This Row],[Primary theme]],Table19[[#All],[Stock Exposure]]) -> 2898.4066 | C21: =SUMIF(Table19[[#All],[Primary theme]],Table21[[#This Row],[Primary theme]],Table19[[#All],[Cost of current position]]) -> 2933.9418 | D21: =Table21[[#This Row],[Stock Exposure]]/$D$5 -> 0.022130086 | E21: 0.06 | F21: =SUMIF(Table19[[#All],[Primary theme]],Table21[[#This Row],[Primary theme]],Table19[[#All],[Option Exposure]]) -> 0 | G21: =Table21[[#This Row],[Option Exposure]]+Table21[[#This Row],[Stock Exposure]] -> 2898.4066 | H21: =Table21[[#This Row],[Combined Exposure]]/$D$4 -> 0.018268948 | I21: =SUMIF(Table19[Primary theme],Table21[[#This Row],[Primary theme]],Table19[Realized Profit]) -> 1380.5718 | J21: =SUMIF(Table19[Primary theme],Table21[[#This Row],[Primary theme]],Table19[Unrealized Profit]) -> -35.535206 | K21: =IFERROR(Table21[[#This Row],[Unrealized Profit]]/Table21[[#This Row],[Cost basis]],"") -> -0.012111762 | L21: =IF(Table21[[#This Row],[Percentage of Stock Exposure]]>Table21[[#This Row],[Target]],TRUE,FALSE) -> FALSE
A22: Connectivity | B22: =SUMIF(Table19[[#All],[Primary theme]],Table21[[#This Row],[Primary theme]],Table19[[#All],[Stock Exposure]]) -> 1113.4235 | C22: =SUMIF(Table19[[#All],[Primary theme]],Table21[[#This Row],[Primary theme]],Table19[[#All],[Cost of current position]]) -> 700.35805 | D22: =Table21[[#This Row],[Stock Exposure]]/$D$5 -> 0.0085012772 | E22: 0.05 | F22: =SUMIF(Table19[[#All],[Primary theme]],Table21[[#This Row],[Primary theme]],Table19[[#All],[Option Exposure]]) -> 0 | G22: =Table21[[#This Row],[Option Exposure]]+Table21[[#This Row],[Stock Exposure]] -> 1113.4235 | H22: =Table21[[#This Row],[Combined Exposure]]/$D$4 -> 0.00701802 | I22: =SUMIF(Table19[Primary theme],Table21[[#This Row],[Primary theme]],Table19[Realized Profit]) -> 103.44805 | J22: =SUMIF(Table19[Primary theme],Table21[[#This Row],[Primary theme]],Table19[Unrealized Profit]) -> 413.06545 | K22: =IFERROR(Table21[[#This Row],[Unrealized Profit]]/Table21[[#This Row],[Cost basis]],"") -> 0.58979182 | L22: =IF(Table21[[#This Row],[Percentage of Stock Exposure]]>Table21[[#This Row],[Target]],TRUE,FALSE) -> FALSE
... A50: Materials | B50: =SUMIF(Table19[[#All],[Primary theme]],Table21[[#This Row],[Primary theme]],Table19[[#All],[Stock Exposure]]) -> -296.88 | C50: =SUMIF(Table19[[#All],[Primary theme]],Table21[[#This Row],[Primary theme]],Table19[[#All],[Cost of current position]]) -> 0 | D50: =Table21[[#This Row],[Stock Exposure]]/$D$5 -> -0.0022667558 | E50: 0 | F50: =SUMIF(Table19[[#All],[Primary theme]],Table21[[#This Row],[Primary theme]],Table19[[#All],[Option Exposure]]) -> 0 | G50: =Table21[[#This Row],[Option Exposure]]+Table21[[#This Row],[Stock Exposure]] -> -296.88 | H50: =Table21[[#This Row],[Combined Exposure]]/$D$4 -> -0.0018712644 | I50: =SUMIF(Table19[Primary theme],Table21[[#This Row],[Primary theme]],Table19[Realized Profit]) -> 0 | J50: =SUMIF(Table19[Primary theme],Table21[[#This Row],[Primary theme]],Table19[Unrealized Profit]) -> 0 | K50: =IFERROR(Table21[[#This Row],[Unrealized Profit]]/Table21[[#This Row],[Cost basis]],"") | L50: =IF(Table21[[#This Row],[Percentage of Stock Exposure]]>Table21[[#This Row],[Target]],TRUE,FALSE) -> FALSE

Sheet CryptoPortfolio
A1: Crypto Portfolio | C1: Total CryptoPortfolio Value | D1: =SUM(Table26[[#All],[Current Exposure]]) -> 37073.169 | F1: Total Realized: | G1: =SUM(Table228[Realized Profit]) -> -2062874.7
A3: 1 | B3: 2 | C3: 3 | D3: 4 | E3: 5 | F3: 6 | G3: 7 | H3: 8 | I3: 9 | J3: 10
A4: Asset | B4: Theme | C4: Realized Profit | D4: Unrealized Profit | E4: Blockchain | F4: Current Exposure | G4: Average Entry | H4: How many tokens | I4: Distance from entry | J4: Current Price
A5: SOL | B5: Layer 1 | C5: =IFERROR(VLOOKUP(Table26[[#This Row],[Asset]],Table228[],19,FALSE),0) -> -38.51938 | D5: =IFERROR(VLOOKUP(Table26[[#This Row],[Asset]],Table228[#All],20,FALSE),0) -> 1671.0622 | E5: Solana | F5: =Table26[[#This Row],[How many tokens]]*Table26[[#This Row],[Current Price]] -> 12792.772 | G5: =IFERROR(VLOOKUP(Table26[[#This Row],[Asset]],Table228[#All],16,FALSE),0) -> 147.79366 | H5: =IFERROR(VLOOKUP(Table26[[#This Row],[Asset]],Table228[#All],18,FALSE),0) -> 75.2516 | I5: =IFERROR((Table26[[#This Row],[Current Price]]-Table26[[#This Row],[Average Entry]])/Table26[[#This Row],[Average Entry]],0) -> 0.15025228 | J5: 170
A6: KMNO | B6: Defi | C6: =IFERROR(VLOOKUP(Table26[[#This Row],[Asset]],Table228[],19,FALSE),0) -> -3799.3442 | D6: =IFERROR(VLOOKUP(Table26[[#This Row],[Asset]],Table228[#All],20,FALSE),0) -> 440.80882 | E6: Solana | F6: =Table26[[#This Row],[How many tokens]]*Table26[[#This Row],[Current Price]] -> -859.57882 | G6: =IFERROR(VLOOKUP(Table26[[#This Row],[Asset]],Table228[#All],16,FALSE),0) -> 0.064768343 | H6: =IFERROR(VLOOKUP(Table26[[#This Row],[Asset]],Table228[#All],18,FALSE),0) -> -20077.519 | I6: =IFERROR((Table26[[#This Row],[Current Price]]-Table26[[#This Row],[Average Entry]])/Table26[[#This Row],[Average Entry]],0) -> -0.33898263 | J6: 0.042813
A7: VRTX | B7: Perpetual Exchange | C7: =IFERROR(VLOOKUP(Table26[[#This Row],[Asset]],Table228[],19,FALSE),0) -> -3890.4228 | D7: =IFERROR(VLOOKUP(Table26[[#This Row],[Asset]],Table228[#All],20,FALSE),0) -> -0.044737623 | E7: Arbitrum | F7: =Table26[[#This Row],[How many tokens]]*Table26[[#This Row],[Current Price]] -> 0.0159025 | G7: =IFERROR(VLOOKUP(Table26[[#This Row],[Asset]],Table228[#All],16,FALSE),0) -> 0.095331117 | H7: =IFERROR(VLOOKUP(Table26[[#This Row],[Asset]],Table228[#All],18,FALSE),0) -> 0.6361 | I7: =IFERROR((Table26[[#This Row],[Current Price]]-Table26[[#This Row],[Average Entry]])/Table26[[#This Row],[Average Entry]],0) -> -0.73775614 | J7: 0.025
A8: Jto/jitoSol | C8: =IFERROR(VLOOKUP(Table26[[#This Row],[Asset]],Table228[],19,FALSE),0) -> 0 | D8: =IFERROR(VLOOKUP(Table26[[#This Row],[Asset]],Table228[#All],20,FALSE),0) -> -630 | E8: Solana | F8: =Table26[[#This Row],[How many tokens]]*Table26[[#This Row],[Current Price]] -> 4290 | G8: =IFERROR(VLOOKUP(Table26[[#This Row],[Asset]],Table228[#All],16,FALSE),0) -> 4920 | H8: =IFERROR(VLOOKUP(Table26[[#This Row],[Asset]],Table228[#All],18,FALSE),0) -> 1 | I8: =IFERROR((Table26[[#This Row],[Current Price]]-Table26[[#This Row],[Average Entry]])/Table26[[#This Row],[Average Entry]],0) -> -0.12804878 | J8: 4290
A9: Famous Fox | B9: NFT | C9: =IFERROR(VLOOKUP(Table26[[#This Row],[Asset]],Table228[],19,FALSE),0) -> -4089.5824 | D9: =IFERROR(VLOOKUP(Table26[[#This Row],[Asset]],Table228[#All],20,FALSE),0) -> 0 | E9: Solana | F9: =Table26[[#This Row],[How many tokens]]*Table26[[#This Row],[Current Price]] -> 0 | G9: =IFERROR(VLOOKUP(Table26[[#This Row],[Asset]],Table228[#All],16,FALSE),0) -> 927.90565 | H9: =IFERROR(VLOOKUP(Table26[[#This Row],[Asset]],Table228[#All],18,FALSE),0) -> 0 | I9: =IFERROR((Table26[[#This Row],[Current Price]]-Table26[[#This Row],[Average Entry]])/Table26[[#This Row],[Average Entry]],0) -> -0.31889627 | J9: 632
A10: SEND | B10: AI agent | C10: =IFERROR(VLOOKUP(Table26[[#This Row],[Asset]],Table228[],19,FALSE),0) -> -12004.723 | D10: =IFERROR(VLOOKUP(Table26[[#This Row],[Asset]],Table228[#All],20,FALSE),0) -> 0.0033201484 | E10: Solana | F10: =Table26[[#This Row],[How many tokens]]*Table26[[#This Row],[Current Price]] -> -0.001872871 | G10: =IFERROR(VLOOKUP(Table26[[#This Row],[Asset]],Table228[#All],16,FALSE),0) -> 0.030500346 | H10: =IFERROR(VLOOKUP(Table26[[#This Row],[Asset]],Table228[#All],18,FALSE),0) -> -0.170261 | I10: =IFERROR((Table26[[#This Row],[Current Price]]-Table26[[#This Row],[Average Entry]])/Table26[[#This Row],[Average Entry]],0) -> -0.63934835 | J10: 0.011
A11: MOTHER | B11: Meme | C11: =IFERROR(VLOOKUP(Table26[[#This Row],[Asset]],Table228[],19,FALSE),0) -> -813.51459 | D11: =IFERROR(VLOOKUP(Table26[[#This Row],[Asset]],Table228[#All],20,FALSE),0) -> -2.3737985e-06 | E11: Solana | F11: =Table26[[#This Row],[How many tokens]]*Table26[[#This Row],[Current Price]] -> -2.8936299e-05 | G11: =IFERROR(VLOOKUP(Table26[[#This Row],[Asset]],Table228[#All],16,FALSE),0) -> 0.048560332 | H11: =IFERROR(VLOOKUP(Table26[[#This Row],[Asset]],Table228[#All],18,FALSE),0) -> -0.00054699997 | I11: =IFERROR((Table26[[#This Row],[Current Price]]-Table26[[#This Row],[Average Entry]])/Table26[[#This Row],[Average Entry]],0) -> 0.08936653 | J11: 0.0529
A12: KMNO/JitoSOL | B12: Defi | C12: =IFERROR(VLOOKUP(Table26[[#This Row],[Asset]],Table228[],19,FALSE),0) -> 4550 | D12: =IFERROR(VLOOKUP(Table26[[#This Row],[Asset]],Table228[#All],20,FALSE),0) -> -210 | E12: Solana | F12: =Table26[[#This Row],[How many tokens]]*Table26[[#This Row],[Current Price]] -> 2190 | G12: =IFERROR(VLOOKUP(Table26[[#This Row],[Asset]],Table228[#All],16,FALSE),0) -> 4800 | H12: =IFERROR(VLOOKUP(Table26[[#This Row],[Asset]],Table228[#All],18,FALSE),0) -> 0.5 | I12: =IFERROR((Table26[[#This Row],[Current Price]]-Table26[[#This Row],[Average Entry]])/Table26[[#This Row],[Average Entry]],0) -> -0.0875 | J12: 4380
A13: AR | C13: =IFERROR(VLOOKUP(Table26[[#This Row],[Asset]],Table228[],19,FALSE),0) -> 0 | D13: =IFERROR(VLOOKUP(Table26[[#This Row],[Asset]],Table228[#All],20,FALSE),0) -> -1436.7318 | F13: =Table26[[#This Row],[How many tokens]]*Table26[[#This Row],[Current Price]] -> 440.19018 | G13: =IFERROR(VLOOKUP(Table26[[#This Row],[Asset]],Table228[#All],16,FALSE),0) -> 23.025 | H13: =IFERROR(VLOOKUP(Table26[[#This Row],[Asset]],Table228[#All],18,FALSE),0) -> 81.5167 | I13: =IFERROR((Table26[[#This Row],[Current Price]]-Table26[[#This Row],[Average Entry]])/Table26[[#This Row],[Average Entry]],0) -> -0.76547231 | J13: 5.4
A14: HOLD | C14: =IFERROR(VLOOKUP(Table26[[#This Row],[Asset]],Table228[],19,FALSE),0) -> -1405.149 | D14: =IFERROR(VLOOKUP(Table26[[#This Row],[Asset]],Table228[#All],20,FALSE),0) -> 0 | F14: =Table26[[#This Row],[How many tokens]]*Table26[[#This Row],[Current Price]] -> 0 | G14: =IFERROR(VLOOKUP(Table26[[#This Row],[Asset]],Table228[#All],16,FALSE),0) -> 3.5654726 | H14: =IFERROR(VLOOKUP(Table26[[#This Row],[Asset]],Table228[#All],18,FALSE),0) -> 0 | I14: =IFERROR((Table26[[#This Row],[Current Price]]-Table26[[#This Row],[Average Entry]])/Table26[[#This Row],[Average Entry]],0) -> -0.11933133 | J14: 3.14
A15: ZEX/JitoSol | B15: Perpetual Exchange | C15: =IFERROR(VLOOKUP(Table26[[#This Row],[Asset]],Table228[],19,FALSE),0) -> 361.19 | D15: =IFERROR(VLOOKUP(Table26[[#This Row],[Asset]],Table228[#All],20,FALSE),0) -> 51.19 | E15: Solana | F15: =Table26[[#This Row],[How many tokens]]*Table26[[#This Row],[Current Price]] -> 1800 | G15: =IFERROR(VLOOKUP(Table26[[#This Row],[Asset]],Table228[#All],16,FALSE),0) -> 1748.81 | H15: =IFERROR(VLOOKUP(Table26[[#This Row],[Asset]],Table228[#All],18,FALSE),0) -> 1 | I15: =IFERROR((Table26[[#This Row],[Current Price]]-Table26[[#This Row],[Average Entry]])/Table26[[#This Row],[Average Entry]],0) -> 0.029271333 | J15: 1800
A16: USDC | B16: Cash | C16: =IFERROR(VLOOKUP(Table26[[#This Row],[Asset]],Table228[],19,FALSE),0) -> 437.15661 | D16: =IFERROR(VLOOKUP(Table26[[#This Row],[Asset]],Table228[#All],20,FALSE),0) -> 61.893393 | E16: Multi | F16: =Table26[[#This Row],[How many tokens]]*Table26[[#This Row],[Current Price]] -> 1798.83 | G16: =IFERROR(VLOOKUP(Table26[[#This Row],[Asset]],Table228[#All],16,FALSE),0) -> 0.96559242 | H16: =IFERROR(VLOOKUP(Table26[[#This Row],[Asset]],Table228[#All],18,FALSE),0) -> 1798.83 | I16: =IFERROR((Table26[[#This Row],[Current Price]]-Table26[[#This Row],[Average Entry]])/Table26[[#This Row],[Average Entry]],0) -> 0.035633651 | J16: 1
A17: PYTH | B17: Defi | C17: =IFERROR(VLOOKUP(Table26[[#This Row],[Asset]],Table228[],19,FALSE),0) -> -3460.231 | D17: =IFERROR(VLOOKUP(Table26[[#This Row],[Asset]],Table228[#All],20,FALSE),0) -> 0.037855753 | E17: Solana | F17: =Table26[[#This Row],[How many tokens]]*Table26[[#This Row],[Current Price]] -> -0.10677366 | G17: =IFERROR(VLOOKUP(Table26[[#This Row],[Asset]],Table228[#All],16,FALSE),0) -> 0.24381757 | H17: =IFERROR(VLOOKUP(Table26[[#This Row],[Asset]],Table228[#All],18,FALSE),0) -> -0.593187 | I17: =IFERROR((Table26[[#This Row],[Current Price]]-Table26[[#This Row],[Average Entry]])/Table26[[#This Row],[Average Entry]],0) -> -0.26174312 | J17: 0.18
A18: Aero | B18: Defi | C18: =IFERROR(VLOOKUP(Table26[[#This Row],[Asset]],Table228[],19,FALSE),0) -> 0 | D18: =IFERROR(VLOOKUP(Table26[[#This Row],[Asset]],Table228[#All],20,FALSE),0) -> 1324.1624 | E18: Base | F18: =Table26[[#This Row],[How many tokens]]*Table26[[#This Row],[Current Price]] -> 1508.998 | G18: =IFERROR(VLOOKUP(Table26[[#This Row],[Asset]],Table228[#All],16,FALSE),0) -> 0.1 | H18: =IFERROR(VLOOKUP(Table26[[#This Row],[Asset]],Table228[#All],18,FALSE),0) -> 1848.3562 | I18: =IFERROR((Table26[[#This Row],[Current Price]]-Table26[[#This Row],[Average Entry]])/Table26[[#This Row],[Average Entry]],0) -> 7.164 | J18: 0.8164
A19: Osmo | B19: Defi | C19: =IFERROR(VLOOKUP(Table26[[#This Row],[Asset]],Table228[],19,FALSE),0) -> -5865.8448 | D19: =IFERROR(VLOOKUP(Table26[[#This Row],[Asset]],Table228[#All],20,FALSE),0) -> -155.83225 | E19: Osmosis | F19: =Table26[[#This Row],[How many tokens]]*Table26[[#This Row],[Current Price]] -> 161.76065 | G19: =IFERROR(VLOOKUP(Table26[[#This Row],[Asset]],Table228[#All],16,FALSE),0) -> 0.75 | H19: =IFERROR(VLOOKUP(Table26[[#This Row],[Asset]],Table228[#All],18,FALSE),0) -> 423.4572 | I19: =IFERROR((Table26[[#This Row],[Current Price]]-Table26[[#This Row],[Average Entry]])/Table26[[#This Row],[Average Entry]],0) -> -0.49066667 | J19: 0.382
A20: DAG | B20: Enterprise | C20: =IFERROR(VLOOKUP(Table26[[#This Row],[Asset]],Table228[],19,FALSE),0) -> 55.03 | D20: =IFERROR(VLOOKUP(Table26[[#This Row],[Asset]],Table228[#All],20,FALSE),0) -> -0.049593906 | E20: Constellations | F20: =Table26[[#This Row],[How many tokens]]*Table26[[#This Row],[Current Price]] -> 0.20508209 | G20: =IFERROR(VLOOKUP(Table26[[#This Row],[Asset]],Table228[#All],16,FALSE),0) -> 0.03 | H20: =IFERROR(VLOOKUP(Table26[[#This Row],[Asset]],Table228[#All],18,FALSE),0) -> 8.4892 | I20: =IFERROR((Table26[[#This Row],[Current Price]]-Table26[[#This Row],[Average Entry]])/Table26[[#This Row],[Average Entry]],0) -> -0.19473333 | J20: 0.024158
A21: PatronNFT | B21: NFT | C21: =IFERROR(VLOOKUP(Table26[[#This Row],[Asset]],Table228[],19,FALSE),0) -> 0 | D21: =IFERROR(VLOOKUP(Table26[[#This Row],[Asset]],Table228[#All],20,FALSE),0) -> 0 | E21: Arbitrum | F21: =Table26[[#This Row],[How many tokens]]*Table26[[#This Row],[Current Price]] -> 1250 | G21: =IFERROR(VLOOKUP(Table26[[#This Row],[Asset]],Table228[#All],16,FALSE),0) -> 1250 | H21: =IFERROR(VLOOKUP(Table26[[#This Row],[Asset]],Table228[#All],18,FALSE),0) -> 1 | I21: =IFERROR((Table26[[#This Row],[Current Price]]-Table26[[#This Row],[Average Entry]])/Table26[[#This Row],[Average Entry]],0) -> 0 | J21: 1250
A22: JitoSOL | C22: =IFERROR(VLOOKUP(Table26[[#This Row],[Asset]],Table228[],19,FALSE),0) -> 0 | D22: =IFERROR(VLOOKUP(Table26[[#This Row],[Asset]],Table228[#All],20,FALSE),0) -> 0 | F22: =Table26[[#This Row],[How many tokens]]*Table26[[#This Row],[Current Price]] -> 1158.4 | G22: =IFERROR(VLOOKUP(Table26[[#This Row],[Asset]],Table228[#All],16,FALSE),0) -> 128 | H22: =IFERROR(VLOOKUP(Table26[[#This Row],[Asset]],Table228[#All],18,FALSE),0) -> 9.05 | I22: =IFERROR((Table26[[#This Row],[Current Price]]-Table26[[#This Row],[Average Entry]])/Table26[[#This Row],[Average Entry]],0) -> 0 | J22: 128
A23: Drift | B23: Perpetual Exchange | C23: =IFERROR(VLOOKUP(Table26[[#This Row],[Asset]],Table228[],19,FALSE),0) -> -602.24235 | D23: =IFERROR(VLOOKUP(Table26[[#This Row],[Asset]],Table228[#All],20,FALSE),0) -> 0 | E23: Solana | F23: =Table26[[#This Row],[How many tokens]]*Table26[[#This Row],[Current Price]] -> 0 | G23: =IFERROR(VLOOKUP(Table26[[#This Row],[Asset]],Table228[#All],16,FALSE),0) -> 0.44 | H23: =IFERROR(VLOOKUP(Table26[[#This Row],[Asset]],Table228[#All],18,FALSE),0) -> 0 | I23: =IFERROR((Table26[[#This Row],[Current Price]]-Table26[[#This Row],[Average Entry]])/Table26[[#This Row],[Average Entry]],0) -> 0 | J23: 0.44
A24: ARB | B24: Layer 2 | C24: =IFERROR(VLOOKUP(Table26[[#This Row],[Asset]],Table228[],19,FALSE),0) -> -412.05274 | D24: =IFERROR(VLOOKUP(Table26[[#This Row],[Asset]],Table228[#All],20,FALSE),0) -> 1202.8039 | E24: Arbitrum | F24: =Table26[[#This Row],[How many tokens]]*Table26[[#This Row],[Current Price]] -> 3169.9765 | G24: =IFERROR(VLOOKUP(Table26[[#This Row],[Asset]],Table228[#All],16,FALSE),0) -> 0.46542283 | H24: =IFERROR(VLOOKUP(Table26[[#This Row],[Asset]],Table228[#All],18,FALSE),0) -> 4226.6354 | I24: =IFERROR((Table26[[#This Row],[Current Price]]-Table26[[#This Row],[Average Entry]])/Table26[[#This Row],[Average Entry]],0) -> 0.61143793 | J24: 0.75
A25: KWEEN | B25: Meme | C25: =IFERROR(VLOOKUP(Table26[[#This Row],[Asset]],Table228[],19,FALSE),0) -> -1864.3976 | D25: =IFERROR(VLOOKUP(Table26[[#This Row],[Asset]],Table228[#All],20,FALSE),0) -> 3.7408311e-07 | E25: Solana | F25: =Table26[[#This Row],[How many tokens]]*Table26[[#This Row],[Current Price]] -> -2.6547493e-07 | G25: =IFERROR(VLOOKUP(Table26[[#This Row],[Asset]],Table228[#All],16,FALSE),0) -> 0.017285357 | H25: =IFERROR(VLOOKUP(Table26[[#This Row],[Asset]],Table228[#All],18,FALSE),0) -> -3.6999991e-05 | I25: =IFERROR((Table26[[#This Row],[Current Price]]-Table26[[#This Row],[Average Entry]])/Table26[[#This Row],[Average Entry]],0) -> -0.58490877 | J25: 0.007175
A26: SNX | B26: Defi | C26: =IFERROR(VLOOKUP(Table26[[#This Row],[Asset]],Table228[],19,FALSE),0) -> -265.5994 | D26: =IFERROR(VLOOKUP(Table26[[#This Row],[Asset]],Table228[#All],20,FALSE),0) -> 58.338839 | E26: Multi | F26: =Table26[[#This Row],[How many tokens]]*Table26[[#This Row],[Current Price]] -> 843.66936 | G26: =IFERROR(VLOOKUP(Table26[[#This Row],[Asset]],Table228[#All],16,FALSE),0) -> 1.75 | H26: =IFERROR(VLOOKUP(Table26[[#This Row],[Asset]],Table228[#All],18,FALSE),0) -> 448.7603 | I26: =IFERROR((Table26[[#This Row],[Current Price]]-Table26[[#This Row],[Average Entry]])/Table26[[#This Row],[Average Entry]],0) -> 0.074285714 | J26: 1.88
A27: FUTURE | B27: Meme | C27: =IFERROR(VLOOKUP(Table26[[#This Row],[Asset]],Table228[],19,FALSE),0) -> 275.89075 | D27: =IFERROR(VLOOKUP(Table26[[#This Row],[Asset]],Table228[#All],20,FALSE),0) -> 337.84322 | E27: Solana | F27: =Table26[[#This Row],[How many tokens]]*Table26[[#This Row],[Current Price]] -> 823.0952 | G27: =IFERROR(VLOOKUP(Table26[[#This Row],[Asset]],Table228[#All],16,FALSE),0) -> 0.00045 | H27: =IFERROR(VLOOKUP(Table26[[#This Row],[Asset]],Table228[#All],18,FALSE),0) -> 1078337.8 | I27: =IFERROR((Table26[[#This Row],[Current Price]]-Table26[[#This Row],[Average Entry]])/Table26[[#This Row],[Average Entry]],0) -> 0.69622222 | J27: 0.0007633
A28: Whales/SOL | B28: Defi | C28: =IFERROR(VLOOKUP(Table26[[#This Row],[Asset]],Table228[],19,FALSE),0) -> 0 | D28: =IFERROR(VLOOKUP(Table26[[#This Row],[Asset]],Table228[#All],20,FALSE),0) -> -691.29 | E28: Solana | F28: =Table26[[#This Row],[How many tokens]]*Table26[[#This Row],[Current Price]] -> 779.72 | G28: =IFERROR(VLOOKUP(Table26[[#This Row],[Asset]],Table228[#All],16,FALSE),0) -> 1471.01 | H28: =IFERROR(VLOOKUP(Table26[[#This Row],[Asset]],Table228[#All],18,FALSE),0) -> 1 | I28: =IFERROR((Table26[[#This Row],[Current Price]]-Table26[[#This Row],[Average Entry]])/Table26[[#This Row],[Average Entry]],0) -> -0.46994242 | J28: 779.72
A29: TNSR | B29: Defi | C29: =IFERROR(VLOOKUP(Table26[[#This Row],[Asset]],Table228[],19,FALSE),0) -> -3407.0483 | D29: =IFERROR(VLOOKUP(Table26[[#This Row],[Asset]],Table228[#All],20,FALSE),0) -> -365.46515 | F29: =Table26[[#This Row],[How many tokens]]*Table26[[#This Row],[Current Price]] -> 200.34759 | G29: =IFERROR(VLOOKUP(Table26[[#This Row],[Asset]],Table228[#All],16,FALSE),0) -> 0.28241554 | H29: =IFERROR(VLOOKUP(Table26[[#This Row],[Asset]],Table228[#All],18,FALSE),0) -> 2003.4759 | I29: =IFERROR((Table26[[#This Row],[Current Price]]-Table26[[#This Row],[Average Entry]])/Table26[[#This Row],[Average Entry]],0) -> -0.64591184 | J29: 0.1
A30: Bonk | B30: Meme | C30: =IFERROR(VLOOKUP(Table26[[#This Row],[Asset]],Table228[],19,FALSE),0) -> 0 | D30: =IFERROR(VLOOKUP(Table26[[#This Row],[Asset]],Table228[#All],20,FALSE),0) -> 660 | E30: Solana | F30: =Table26[[#This Row],[How many tokens]]*Table26[[#This Row],[Current Price]] -> 732.6 | G30: =IFERROR(VLOOKUP(Table26[[#This Row],[Asset]],Table228[#All],16,FALSE),0) -> 2.1801802 | H30: =IFERROR(VLOOKUP(Table26[[#This Row],[Asset]],Table228[#All],18,FALSE),0) -> 33.3 | I30: =IFERROR((Table26[[#This Row],[Current Price]]-Table26[[#This Row],[Average Entry]])/Table26[[#This Row],[Average Entry]],0) -> 9.0909091 | J30: 22
A31: Velo | B31: Defi | C31: =IFERROR(VLOOKUP(Table26[[#This Row],[Asset]],Table228[],19,FALSE),0) -> 0 | D31: =IFERROR(VLOOKUP(Table26[[#This Row],[Asset]],Table228[#All],20,FALSE),0) -> -1291.4935 | E31: Optimism | F31: =Table26[[#This Row],[How many tokens]]*Table26[[#This Row],[Current Price]] -> 712.31252 | G31: =IFERROR(VLOOKUP(Table26[[#This Row],[Asset]],Table228[#All],16,FALSE),0) -> 0.1796164 | H31: =IFERROR(VLOOKUP(Table26[[#This Row],[Asset]],Table228[#All],18,FALSE),0) -> 11156.03 | I31: =IFERROR((Table26[[#This Row],[Current Price]]-Table26[[#This Row],[Average Entry]])/Table26[[#This Row],[Average Entry]],0) -> -0.64452022 | J31: 0.06385
A32: JUP | B32: Defi | C32: =IFERROR(VLOOKUP(Table26[[#This Row],[Asset]],Table228[],19,FALSE),0) -> 0 | D32: =IFERROR(VLOOKUP(Table26[[#This Row],[Asset]],Table228[#All],20,FALSE),0) -> -2 | E32: Solana | F32: =Table26[[#This Row],[How many tokens]]*Table26[[#This Row],[Current Price]] -> 690 | G32: =IFERROR(VLOOKUP(Table26[[#This Row],[Asset]],Table228[#All],16,FALSE),0) -> 0.692 | H32: =IFERROR(VLOOKUP(Table26[[#This Row],[Asset]],Table228[#All],18,FALSE),0) -> 1000 | I32: =IFERROR((Table26[[#This Row],[Current Price]]-Table26[[#This Row],[Average Entry]])/Table26[[#This Row],[Average Entry]],0) -> -0.0028901734 | J32: 0.69
A33: MadScientist | B33: NFT | C33: =IFERROR(VLOOKUP(Table26[[#This Row],[Asset]],Table228[],19,FALSE),0) -> 0 | D33: =IFERROR(VLOOKUP(Table26[[#This Row],[Asset]],Table228[#All],20,FALSE),0) -> -888 | E33: Osmosis | F33: =Table26[[#This Row],[How many tokens]]*Table26[[#This Row],[Current Price]] -> 512 | G33: =IFERROR(VLOOKUP(Table26[[#This Row],[Asset]],Table228[#All],16,FALSE),0) -> 700 | H33: =IFERROR(VLOOKUP(Table26[[#This Row],[Asset]],Table228[#All],18,FALSE),0) -> 2 | I33: =IFERROR((Table26[[#This Row],[Current Price]]-Table26[[#This Row],[Average Entry]])/Table26[[#This Row],[Average Entry]],0) -> -0.63428571 | J33: 256
A34: ETH | B34: Layer 1 | C34: =IFERROR(VLOOKUP(Table26[[#This Row],[Asset]],Table228[],19,FALSE),0) -> 0 | D34: =IFERROR(VLOOKUP(Table26[[#This Row],[Asset]],Table228[#All],20,FALSE),0) -> 123.41199 | E34: Ethereum | F34: =Table26[[#This Row],[How many tokens]]*Table26[[#This Row],[Current Price]] -> 477.63699 | G34: =IFERROR(VLOOKUP(Table26[[#This Row],[Asset]],Table228[#All],16,FALSE),0) -> 2500 | H34: =IFERROR(VLOOKUP(Table26[[#This Row],[Asset]],Table228[#All],18,FALSE),0) -> 0.14169 | I34: =IFERROR((Table26[[#This Row],[Current Price]]-Table26[[#This Row],[Average Entry]])/Table26[[#This Row],[Average Entry]],0) -> 0.3484 | J34: 3371
A35: FAF | C35: =IFERROR(VLOOKUP(Table26[[#This Row],[Asset]],Table228[],19,FALSE),0) -> 0 | D35: =IFERROR(VLOOKUP(Table26[[#This Row],[Asset]],Table228[#All],20,FALSE),0) -> -72.645292 | F35: =Table26[[#This Row],[How many tokens]]*Table26[[#This Row],[Current Price]] -> 1586.2074 | G35: =IFERROR(VLOOKUP(Table26[[#This Row],[Asset]],Table228[#All],16,FALSE),0) -> 0.0028466624 | H35: =IFERROR(VLOOKUP(Table26[[#This Row],[Asset]],Table228[#All],18,FALSE),0) -> 582736 | I35: =IFERROR((Table26[[#This Row],[Current Price]]-Table26[[#This Row],[Average Entry]])/Table26[[#This Row],[Average Entry]],0) -> -0.043792492 | J35: 0.002722
A36: Ray/Sol | B36: Defi | C36: =IFERROR(VLOOKUP(Table26[[#This Row],[Asset]],Table228[],19,FALSE),0) -> 0 | D36: =IFERROR(VLOOKUP(Table26[[#This Row],[Asset]],Table228[#All],20,FALSE),0) -> 0 | E36: Solana | F36: =Table26[[#This Row],[How many tokens]]*Table26[[#This Row],[Current Price]] -> 393.32 | G36: =IFERROR(VLOOKUP(Table26[[#This Row],[Asset]],Table228[#All],16,FALSE),0) -> 393.32 | H36: =IFERROR(VLOOKUP(Table26[[#This Row],[Asset]],Table228[#All],18,FALSE),0) -> 1 | I36: =IFERROR((Table26[[#This Row],[Current Price]]-Table26[[#This Row],[Average Entry]])/Table26[[#This Row],[Average Entry]],0) -> 0 | J36: 393.32
A37: W/JitoSol | B37: Bridge | C37: =IFERROR(VLOOKUP(Table26[[#This Row],[Asset]],Table228[],19,FALSE),0) -> 0 | D37: =IFERROR(VLOOKUP(Table26[[#This Row],[Asset]],Table228[#All],20,FALSE),0) -> -3349.37 | E37: Solana | F37: =Table26[[#This Row],[How many tokens]]*Table26[[#This Row],[Current Price]] -> 370.55 | G37: =IFERROR(VLOOKUP(Table26[[#This Row],[Asset]],Table228[#All],16,FALSE),0) -> 3719.92 | H37: =IFERROR(VLOOKUP(Table26[[#This Row],[Asset]],Table228[#All],18,FALSE),0) -> 1 | I37: =IFERROR((Table26[[#This Row],[Current Price]]-Table26[[#This Row],[Average Entry]])/Table26[[#This Row],[Average Entry]],0) -> -0.90038764 | J37: 370.55
A38: Aero/USDC | B38: Defi | C38: =IFERROR(VLOOKUP(Table26[[#This Row],[Asset]],Table228[],19,FALSE),0) -> 0 | D38: =IFERROR(VLOOKUP(Table26[[#This Row],[Asset]],Table228[#All],20,FALSE),0) -> 0.1 | E38: Base | F38: =Table26[[#This Row],[How many tokens]]*Table26[[#This Row],[Current Price]] -> 346.67 | G38: =IFERROR(VLOOKUP(Table26[[#This Row],[Asset]],Table228[#All],16,FALSE),0) -> 346.57 | H38: =IFERROR(VLOOKUP(Table26[[#This Row],[Asset]],Table228[#All],18,FALSE),0) -> 1 | I38: =IFERROR((Table26[[#This Row],[Current Price]]-Table26[[#This Row],[Average Entry]])/Table26[[#This Row],[Average Entry]],0) -> 0.000288542 | J38: 346.67
A39: RBC | C39: =IFERROR(VLOOKUP(Table26[[#This Row],[Asset]],Table228[],19,FALSE),0) -> -150.13389 | D39: =IFERROR(VLOOKUP(Table26[[#This Row],[Asset]],Table228[#All],20,FALSE),0) -> -4.0287139 | F39: =Table26[[#This Row],[How many tokens]]*Table26[[#This Row],[Current Price]] -> 80.775256 | G39: =IFERROR(VLOOKUP(Table26[[#This Row],[Asset]],Table228[#All],16,FALSE),0) -> 0.024693074 | H39: =IFERROR(VLOOKUP(Table26[[#This Row],[Asset]],Table228[#All],18,FALSE),0) -> 3434.3221 | I39: =IFERROR((Table26[[#This Row],[Current Price]]-Table26[[#This Row],[Average Entry]])/Table26[[#This Row],[Average Entry]],0) -> -0.047506195 | J39: 0.02352
A40: GMX blueberry | C40: =IFERROR(VLOOKUP(Table26[[#This Row],[Asset]],Table228[],19,FALSE),0) -> 0 | D40: =IFERROR(VLOOKUP(Table26[[#This Row],[Asset]],Table228[#All],20,FALSE),0) -> -1636 | F40: =Table26[[#This Row],[How many tokens]]*Table26[[#This Row],[Current Price]] -> 224 | G40: =IFERROR(VLOOKUP(Table26[[#This Row],[Asset]],Table228[#All],16,FALSE),0) -> 1860 | H40: =IFERROR(VLOOKUP(Table26[[#This Row],[Asset]],Table228[#All],18,FALSE),0) -> 1 | I40: =IFERROR((Table26[[#This Row],[Current Price]]-Table26[[#This Row],[Average Entry]])/Table26[[#This Row],[Average Entry]],0) -> -0.87956989 | J40: 224
A41: TFF (Transdimensional Fox Federation) | B41: NFT | C41: =IFERROR(VLOOKUP(Table26[[#This Row],[Asset]],Table228[],19,FALSE),0) -> 0 | D41: =IFERROR(VLOOKUP(Table26[[#This Row],[Asset]],Table228[#All],20,FALSE),0) -> 0 | E41: Solana | F41: =Table26[[#This Row],[How many tokens]]*Table26[[#This Row],[Current Price]] -> 214 | G41: =IFERROR(VLOOKUP(Table26[[#This Row],[Asset]],Table228[#All],16,FALSE),0) -> 214 | H41: =IFERROR(VLOOKUP(Table26[[#This Row],[Asset]],Table228[#All],18,FALSE),0) -> 1 | I41: =IFERROR((Table26[[#This Row],[Current Price]]-Table26[[#This Row],[Average Entry]])/Table26[[#This Row],[Average Entry]],0) -> 0 | J41: 214
A42: Ovols | B42: NFT | C42: =IFERROR(VLOOKUP(Table26[[#This Row],[Asset]],Table228[],19,FALSE),0) -> 0 | D42: =IFERROR(VLOOKUP(Table26[[#This Row],[Asset]],Table228[#All],20,FALSE),0) -> -2810 | E42: Solana | F42: =Table26[[#This Row],[How many tokens]]*Table26[[#This Row],[Current Price]] -> 190 | G42: =IFERROR(VLOOKUP(Table26[[#This Row],[Asset]],Table228[#All],16,FALSE),0) -> 3000 | H42: =IFERROR(VLOOKUP(Table26[[#This Row],[Asset]],Table228[#All],18,FALSE),0) -> 1 | I42: =IFERROR((Table26[[#This Row],[Current Price]]-Table26[[#This Row],[Average Entry]])/Table26[[#This Row],[Average Entry]],0) -> -0.93666667 | J42: 190
A43: Saga Monkes | B43: NFT | C43: =IFERROR(VLOOKUP(Table26[[#This Row],[Asset]],Table228[],19,FALSE),0) -> 0 | D43: =IFERROR(VLOOKUP(Table26[[#This Row],[Asset]],Table228[#All],20,FALSE),0) -> 188 | E43: Solana | F43: =Table26[[#This Row],[How many tokens]]*Table26[[#This Row],[Current Price]] -> 188 | G43: =IFERROR(VLOOKUP(Table26[[#This Row],[Asset]],Table228[#All],16,FALSE),0) -> 0 | H43: =IFERROR(VLOOKUP(Table26[[#This Row],[Asset]],Table228[#All],18,FALSE),0) -> 1 | I43: =IFERROR((Table26[[#This Row],[Current Price]]-Table26[[#This Row],[Average Entry]])/Table26[[#This Row],[Average Entry]],0) -> 0 | J43: 188
A44: HMX | B44: Defi | C44: =IFERROR(VLOOKUP(Table26[[#This Row],[Asset]],Table228[],19,FALSE),0) -> 0 | D44: =IFERROR(VLOOKUP(Table26[[#This Row],[Asset]],Table228[#All],20,FALSE),0) -> -726.18 | E44: Arbitrum | F44: =Table26[[#This Row],[How many tokens]]*Table26[[#This Row],[Current Price]] -> 178.22 | G44: =IFERROR(VLOOKUP(Table26[[#This Row],[Asset]],Table228[#All],16,FALSE),0) -> 6.8 | H44: =IFERROR(VLOOKUP(Table26[[#This Row],[Asset]],Table228[#All],18,FALSE),0) -> 133 | I44: =IFERROR((Table26[[#This Row],[Current Price]]-Table26[[#This Row],[Average Entry]])/Table26[[#This Row],[Average Entry]],0) -> -0.80294118 | J44: 1.34
A45: Mars | B45: Defi | C45: =IFERROR(VLOOKUP(Table26[[#This Row],[Asset]],Table228[],19,FALSE),0) -> 0 | D45: =IFERROR(VLOOKUP(Table26[[#This Row],[Asset]],Table228[#All],20,FALSE),0) -> -3837.2 | E45: Osmosis | F45: =Table26[[#This Row],[How many tokens]]*Table26[[#This Row],[Current Price]] -> 162.8 | G45: =IFERROR(VLOOKUP(Table26[[#This Row],[Asset]],Table228[#All],16,FALSE),0) -> 1 | H45: =IFERROR(VLOOKUP(Table26[[#This Row],[Asset]],Table228[#All],18,FALSE),0) -> 4000 | I45: =IFERROR((Table26[[#This Row],[Current Price]]-Table26[[#This Row],[Average Entry]])/Table26[[#This Row],[Average Entry]],0) -> -0.9593 | J45: 0.0407
A46: TIA | B46: Connected blockchains | C46: =IFERROR(VLOOKUP(Table26[[#This Row],[Asset]],Table228[],19,FALSE),0) -> -457.9404 | D46: =IFERROR(VLOOKUP(Table26[[#This Row],[Asset]],Table228[#All],20,FALSE),0) -> 0 | E46: Celestia | F46: =Table26[[#This Row],[How many tokens]]*Table26[[#This Row],[Current Price]] -> 0 | G46: =IFERROR(VLOOKUP(Table26[[#This Row],[Asset]],Table228[#All],16,FALSE),0) -> 16 | H46: =IFERROR(VLOOKUP(Table26[[#This Row],[Asset]],Table228[#All],18,FALSE),0) -> 0 | I46: =IFERROR((Table26[[#This Row],[Current Price]]-Table26[[#This Row],[Average Entry]])/Table26[[#This Row],[Average Entry]],0) -> -0.703125 | J46: 4.75
A47: Atom | B47: Connected blockchains | C47: =IFERROR(VLOOKUP(Table26[[#This Row],[Asset]],Table228[],19,FALSE),0) -> -3552.5345 | D47: =IFERROR(VLOOKUP(Table26[[#This Row],[Asset]],Table228[#All],20,FALSE),0) -> 0 | E47: Cosmos | F47: =Table26[[#This Row],[How many tokens]]*Table26[[#This Row],[Current Price]] -> 0 | G47: =IFERROR(VLOOKUP(Table26[[#This Row],[Asset]],Table228[#All],16,FALSE),0) -> 11 | H47: =IFERROR(VLOOKUP(Table26[[#This Row],[Asset]],Table228[#All],18,FALSE),0) -> 0 | I47: =IFERROR((Table26[[#This Row],[Current Price]]-Table26[[#This Row],[Average Entry]])/Table26[[#This Row],[Average Entry]],0) -> -0.53972727 | J47: 5.063
A48: WINR | B48: Gambling | C48: =IFERROR(VLOOKUP(Table26[[#This Row],[Asset]],Table228[],19,FALSE),0) -> -149.1503 | D48: =IFERROR(VLOOKUP(Table26[[#This Row],[Asset]],Table228[#All],20,FALSE),0) -> -185.70189 | E48: Arbitrum | F48: =Table26[[#This Row],[How many tokens]]*Table26[[#This Row],[Current Price]] -> 141.23806 | G48: =IFERROR(VLOOKUP(Table26[[#This Row],[Asset]],Table228[#All],16,FALSE),0) -> 0.06 | H48: =IFERROR(VLOOKUP(Table26[[#This Row],[Asset]],Table228[#All],18,FALSE),0) -> 5448.9991 | I48: =IFERROR((Table26[[#This Row],[Current Price]]-Table26[[#This Row],[Average Entry]])/Table26[[#This Row],[Average Entry]],0) -> -0.568 | J48: 0.02592
A49: HXRO | B49: Perpetual Exchange | C49: =IFERROR(VLOOKUP(Table26[[#This Row],[Asset]],Table228[],19,FALSE),0) -> 0 | D49: =IFERROR(VLOOKUP(Table26[[#This Row],[Asset]],Table228[#All],20,FALSE),0) -> -2075.3828 | E49: Solana | F49: =Table26[[#This Row],[How many tokens]]*Table26[[#This Row],[Current Price]] -> 138.35885 | G49: =IFERROR(VLOOKUP(Table26[[#This Row],[Asset]],Table228[#All],16,FALSE),0) -> 0.08 | H49: =IFERROR(VLOOKUP(Table26[[#This Row],[Asset]],Table228[#All],18,FALSE),0) -> 27671.77 | I49: =IFERROR((Table26[[#This Row],[Current Price]]-Table26[[#This Row],[Average Entry]])/Table26[[#This Row],[Average Entry]],0) -> -0.9375 | J49: 0.005
A50: ZEX | B50: Perpetual Exchange | C50: =IFERROR(VLOOKUP(Table26[[#This Row],[Asset]],Table228[],19,FALSE),0) -> 2.80111 | D50: =IFERROR(VLOOKUP(Table26[[#This Row],[Asset]],Table228[#All],20,FALSE),0) -> -66.71874 | E50: Solana | F50: =Table26[[#This Row],[How many tokens]]*Table26[[#This Row],[Current Price]] -> 115.24146 | G50: =IFERROR(VLOOKUP(Table26[[#This Row],[Asset]],Table228[#All],16,FALSE),0) -> 0.09 | H50: =IFERROR(VLOOKUP(Table26[[#This Row],[Asset]],Table228[#All],18,FALSE),0) -> 2021.78 | I50: =IFERROR((Table26[[#This Row],[Current Price]]-Table26[[#This Row],[Average Entry]])/Table26[[#This Row],[Average Entry]],0) -> -0.36666667 | J50: 0.057
A51: MutantMon | B51: NFT | C51: =IFERROR(VLOOKUP(Table26[[#This Row],[Asset]],Table228[],19,FALSE),0) -> -6418.6296 | D51: =IFERROR(VLOOKUP(Table26[[#This Row],[Asset]],Table228[#All],20,FALSE),0) -> -69.37037 | E51: Solana | F51: =Table26[[#This Row],[How many tokens]]*Table26[[#This Row],[Current Price]] -> 111 | G51: =IFERROR(VLOOKUP(Table26[[#This Row],[Asset]],Table228[#All],16,FALSE),0) -> 180.37037 | H51: =IFERROR(VLOOKUP(Table26[[#This Row],[Asset]],Table228[#All],18,FALSE),0) -> 1 | I51: =IFERROR((Table26[[#This Row],[Current Price]]-Table26[[#This Row],[Average Entry]])/Table26[[#This Row],[Average Entry]],0) -> -0.38459959 | J51: 111
A52: SEI | B52: Layer 1 | C52: =IFERROR(VLOOKUP(Table26[[#This Row],[Asset]],Table228[],19,FALSE),0) -> -120.6 | D52: =IFERROR(VLOOKUP(Table26[[#This Row],[Asset]],Table228[#All],20,FALSE),0) -> 0 | E52: Sei Network | F52: =Table26[[#This Row],[How many tokens]]*Table26[[#This Row],[Current Price]] -> 0 | G52: =IFERROR(VLOOKUP(Table26[[#This Row],[Asset]],Table228[#All],16,FALSE),0) -> 0.3 | H52: =IFERROR(VLOOKUP(Table26[[#This Row],[Asset]],Table228[#All],18,FALSE),0) -> 0 | I52: =IFERROR((Table26[[#This Row],[Current Price]]-Table26[[#This Row],[Average Entry]])/Table26[[#This Row],[Average Entry]],0) -> -0.16766667 | J52: 0.2497
... A61: BAT APE combined | B61: NFT | C61: =IFERROR(VLOOKUP(Table26[[#This Row],[Asset]],Table228[],19,FALSE),0) -> 0 | D61: =IFERROR(VLOOKUP(Table26[[#This Row],[Asset]],Table228[#All],20,FALSE),0) -> -1999 | E61: Solana | F61: =Table26[[#This Row],[How many tokens]]*Table26[[#This Row],[Current Price]] -> 1 | G61: =IFERROR(VLOOKUP(Table26[[#This Row],[Asset]],Table228[#All],16,FALSE),0) -> 2000 | H61: =IFERROR(VLOOKUP(Table26[[#This Row],[Asset]],Table228[#All],18,FALSE),0) -> 1 | I61: =IFERROR((Table26[[#This Row],[Current Price]]-Table26[[#This Row],[Average Entry]])/Table26[[#This Row],[Average Entry]],0) -> -0.9995 | J61: 1
A62: M3M3/SOL | C62: =IFERROR(VLOOKUP(Table26[[#This Row],[Asset]],Table228[],19,FALSE),0) -> 1345.615 | D62: =IFERROR(VLOOKUP(Table26[[#This Row],[Asset]],Table228[#All],20,FALSE),0) -> -3453.385 | F62: =Table26[[#This Row],[How many tokens]]*Table26[[#This Row],[Current Price]] -> 1 | G62: =IFERROR(VLOOKUP(Table26[[#This Row],[Asset]],Table228[#All],16,FALSE),0) -> 3454.385 | H62: =IFERROR(VLOOKUP(Table26[[#This Row],[Asset]],Table228[#All],18,FALSE),0) -> 1 | I62: =IFERROR((Table26[[#This Row],[Current Price]]-Table26[[#This Row],[Average Entry]])/Table26[[#This Row],[Average Entry]],0) -> -0.99971051 | J62: 1
A63: TRUMP | B63: Meme | C63: =IFERROR(VLOOKUP(Table26[[#This Row],[Asset]],Table228[],19,FALSE),0) -> -577.9372 | D63: =IFERROR(VLOOKUP(Table26[[#This Row],[Asset]],Table228[#All],20,FALSE),0) -> -0.014374103 | E63: Solana | F63: =Table26[[#This Row],[How many tokens]]*Table26[[#This Row],[Current Price]] -> 0.005032 | G63: =IFERROR(VLOOKUP(Table26[[#This Row],[Asset]],Table228[#All],16,FALSE),0) -> 7.7130776 | H63: =IFERROR(VLOOKUP(Table26[[#This Row],[Asset]],Table228[#All],18,FALSE),0) -> 0.002516 | I63: =IFERROR((Table26[[#This Row],[Current Price]]-Table26[[#This Row],[Average Entry]])/Table26[[#This Row],[Average Entry]],0) -> -0.74070013 | J63: 2
A64: zerebro | B64: AI agent | C64: =IFERROR(VLOOKUP(Table26[[#This Row],[Asset]],Table228[],19,FALSE),0) -> 581.47536 | D64: =IFERROR(VLOOKUP(Table26[[#This Row],[Asset]],Table228[#All],20,FALSE),0) -> -6.776e-07 | F64: =Table26[[#This Row],[How many tokens]]*Table26[[#This Row],[Current Price]] -> 7.72948e-05 | G64: =IFERROR(VLOOKUP(Table26[[#This Row],[Asset]],Table228[#All],16,FALSE),0) -> 0.3222 | H64: =IFERROR(VLOOKUP(Table26[[#This Row],[Asset]],Table228[#All],18,FALSE),0) -> 0.000242 | I64: =IFERROR((Table26[[#This Row],[Current Price]]-Table26[[#This Row],[Average Entry]])/Table26[[#This Row],[Average Entry]],0) -> -0.0086902545 | J64: 0.3194
A65: STEP | C65: =IFERROR(VLOOKUP(Table26[[#This Row],[Asset]],Table228[],19,FALSE),0) -> -2148.4966 | D65: =IFERROR(VLOOKUP(Table26[[#This Row],[Asset]],Table228[#All],20,FALSE),0) -> -4.3437765e-08 | F65: =Table26[[#This Row],[How many tokens]]*Table26[[#This Row],[Current Price]] -> 3.1998254e-07 | G65: =IFERROR(VLOOKUP(Table26[[#This Row],[Asset]],Table228[#All],16,FALSE),0) -> 0.1347 | H65: =IFERROR(VLOOKUP(Table26[[#This Row],[Asset]],Table228[#All],18,FALSE),0) -> 2.6979978e-06 | I65: =IFERROR((Table26[[#This Row],[Current Price]]-Table26[[#This Row],[Average Entry]])/Table26[[#This Row],[Average Entry]],0) -> -0.11952487 | J65: 0.1186
A66: TrumpWinElection | B66: PredictionMarket | C66: =IFERROR(VLOOKUP(Table26[[#This Row],[Asset]],Table228[],19,FALSE),0) -> 9742.6982 | D66: =IFERROR(VLOOKUP(Table26[[#This Row],[Asset]],Table228[#All],20,FALSE),0) -> 0 | E66: Polygon | F66: =Table26[[#This Row],[How many tokens]]*Table26[[#This Row],[Current Price]] -> 0 | G66: =IFERROR(VLOOKUP(Table26[[#This Row],[Asset]],Table228[#All],16,FALSE),0) -> 0.6211476 | H66: =IFERROR(VLOOKUP(Table26[[#This Row],[Asset]],Table228[#All],18,FALSE),0) -> 0 | I66: =IFERROR((Table26[[#This Row],[Current Price]]-Table26[[#This Row],[Average Entry]])/Table26[[#This Row],[Average Entry]],0) -> 0.59382408 | J66: 0.99
A67: TAO | C67: =IFERROR(VLOOKUP(Table26[[#This Row],[Asset]],Table228[],19,FALSE),0) -> 168.48398 | D67: =IFERROR(VLOOKUP(Table26[[#This Row],[Asset]],Table228[#All],20,FALSE),0) -> 0 | F67: =Table26[[#This Row],[How many tokens]]*Table26[[#This Row],[Current Price]] -> 0 | G67: =IFERROR(VLOOKUP(Table26[[#This Row],[Asset]],Table228[#All],16,FALSE),0) -> 352.03288 | H67: =IFERROR(VLOOKUP(Table26[[#This Row],[Asset]],Table228[#All],18,FALSE),0) -> 0 | I67: =IFERROR((Table26[[#This Row],[Current Price]]-Table26[[#This Row],[Average Entry]])/Table26[[#This Row],[Average Entry]],0) -> 0.079444615 | J67: 380
A68: LUNA | B68: Connected blockchains | C68: =IFERROR(VLOOKUP(Table26[[#This Row],[Asset]],Table228[],19,FALSE),0) -> -377458.53 | D68: =IFERROR(VLOOKUP(Table26[[#This Row],[Asset]],Table228[#All],20,FALSE),0) -> 0 | E68: Terra Network | F68: =Table26[[#This Row],[How many tokens]]*Table26[[#This Row],[Current Price]] -> 0 | G68: =IFERROR(VLOOKUP(Table26[[#This Row],[Asset]],Table228[#All],16,FALSE),0) -> 20.101132 | H68: =IFERROR(VLOOKUP(Table26[[#This Row],[Asset]],Table228[#All],18,FALSE),0) -> 0 | I68: =IFERROR((Table26[[#This Row],[Current Price]]-Table26[[#This Row],[Average Entry]])/Table26[[#This Row],[Average Entry]],0) -> -0.98894092 | J68: 0.2223
A69: FLP | B69: Perpetual Exchange | C69: =IFERROR(VLOOKUP(Table26[[#This Row],[Asset]],Table228[],19,FALSE),0) -> 388.63849 | D69: =IFERROR(VLOOKUP(Table26[[#This Row],[Asset]],Table228[#All],20,FALSE),0) -> -2.7782841 | E69: Solana | F69: =Table26[[#This Row],[How many tokens]]*Table26[[#This Row],[Current Price]] -> 108 | G69: =IFERROR(VLOOKUP(Table26[[#This Row],[Asset]],Table228[#All],16,FALSE),0) -> 0.92315237 | H69: =IFERROR(VLOOKUP(Table26[[#This Row],[Asset]],Table228[#All],18,FALSE),0) -> 120 | I69: =IFERROR((Table26[[#This Row],[Current Price]]-Table26[[#This Row],[Average Entry]])/Table26[[#This Row],[Average Entry]],0) -> -0.025079682 | J69: 0.9
A70: Velo/USDC | B70: Defi | C70: =IFERROR(VLOOKUP(Table26[[#This Row],[Asset]],Table228[],19,FALSE),0) -> 476 | D70: =IFERROR(VLOOKUP(Table26[[#This Row],[Asset]],Table228[#All],20,FALSE),0) -> 0 | E70: Optimism | F70: =Table26[[#This Row],[How many tokens]]*Table26[[#This Row],[Current Price]] -> 0 | G70: =IFERROR(VLOOKUP(Table26[[#This Row],[Asset]],Table228[#All],16,FALSE),0) -> 2122 | H70: =IFERROR(VLOOKUP(Table26[[#This Row],[Asset]],Table228[#All],18,FALSE),0) -> 0 | I70: =IFERROR((Table26[[#This Row],[Current Price]]-Table26[[#This Row],[Average Entry]])/Table26[[#This Row],[Average Entry]],0) -> 0.64938737 | J70: 3500
A71: FTM | B71: Layer 1 | C71: =IFERROR(VLOOKUP(Table26[[#This Row],[Asset]],Table228[],19,FALSE),0) -> 3889.99 | D71: =IFERROR(VLOOKUP(Table26[[#This Row],[Asset]],Table228[#All],20,FALSE),0) -> 0 | E71: Fantom | F71: =Table26[[#This Row],[How many tokens]]*Table26[[#This Row],[Current Price]] -> 0 | G71: =IFERROR(VLOOKUP(Table26[[#This Row],[Asset]],Table228[#All],16,FALSE),0) -> 0.41 | H71: =IFERROR(VLOOKUP(Table26[[#This Row],[Asset]],Table228[#All],18,FALSE),0) -> 0 | I71: =IFERROR((Table26[[#This Row],[Current Price]]-Table26[[#This Row],[Average Entry]])/Table26[[#This Row],[Average Entry]],0) -> 0 | J71: 0.41
A72: Sol/Wen | B72: Meme | C72: =IFERROR(VLOOKUP(Table26[[#This Row],[Asset]],Table228[],19,FALSE),0) -> 403.77 | D72: =IFERROR(VLOOKUP(Table26[[#This Row],[Asset]],Table228[#All],20,FALSE),0) -> 0 | E72: Solana | F72: =Table26[[#This Row],[How many tokens]]*Table26[[#This Row],[Current Price]] -> 0 | G72: =IFERROR(VLOOKUP(Table26[[#This Row],[Asset]],Table228[#All],16,FALSE),0) -> 520.35 | H72: =IFERROR(VLOOKUP(Table26[[#This Row],[Asset]],Table228[#All],18,FALSE),0) -> 0 | I72: =IFERROR((Table26[[#This Row],[Current Price]]-Table26[[#This Row],[Average Entry]])/Table26[[#This Row],[Average Entry]],0) -> 0 | J72: 520.35
A73: Flash Trade | B73: NFT | C73: =IFERROR(VLOOKUP(Table26[[#This Row],[Asset]],Table228[],19,FALSE),0) -> -4941 | D73: =IFERROR(VLOOKUP(Table26[[#This Row],[Asset]],Table228[#All],20,FALSE),0) -> 0 | E73: Solana | F73: =Table26[[#This Row],[How many tokens]]*Table26[[#This Row],[Current Price]] -> 0 | G73: =IFERROR(VLOOKUP(Table26[[#This Row],[Asset]],Table228[#All],16,FALSE),0) -> 925 | H73: =IFERROR(VLOOKUP(Table26[[#This Row],[Asset]],Table228[#All],18,FALSE),0) -> 0 | I73: =IFERROR((Table26[[#This Row],[Current Price]]-Table26[[#This Row],[Average Entry]])/Table26[[#This Row],[Average Entry]],0) -> -0.23243243 | J73: 710
A74: Frogana | B74: NFT | C74: =IFERROR(VLOOKUP(Table26[[#This Row],[Asset]],Table228[],19,FALSE),0) -> 468 | D74: =IFERROR(VLOOKUP(Table26[[#This Row],[Asset]],Table228[#All],20,FALSE),0) -> 0 | E74: Solana | F74: =Table26[[#This Row],[How many tokens]]*Table26[[#This Row],[Current Price]] -> 0 | G74: =IFERROR(VLOOKUP(Table26[[#This Row],[Asset]],Table228[#All],16,FALSE),0) -> 80 | H74: =IFERROR(VLOOKUP(Table26[[#This Row],[Asset]],Table228[#All],18,FALSE),0) -> 0 | I74: =IFERROR((Table26[[#This Row],[Current Price]]-Table26[[#This Row],[Average Entry]])/Table26[[#This Row],[Average Entry]],0) -> 2.5875 | J74: 287
A75: BAT APE | B75: NFT | C75: =IFERROR(VLOOKUP(Table26[[#This Row],[Asset]],Table228[],19,FALSE),0) -> -235 | D75: =IFERROR(VLOOKUP(Table26[[#This Row],[Asset]],Table228[#All],20,FALSE),0) -> 0 | E75: Solana | F75: =Table26[[#This Row],[How many tokens]]*Table26[[#This Row],[Current Price]] -> 0 | G75: =IFERROR(VLOOKUP(Table26[[#This Row],[Asset]],Table228[#All],16,FALSE),0) -> 50 | H75: =IFERROR(VLOOKUP(Table26[[#This Row],[Asset]],Table228[#All],18,FALSE),0) -> 0 | I75: =IFERROR((Table26[[#This Row],[Current Price]]-Table26[[#This Row],[Average Entry]])/Table26[[#This Row],[Average Entry]],0) -> -0.432 | J75: 28.4
A76: Marms | B76: NFT | C76: =IFERROR(VLOOKUP(Table26[[#This Row],[Asset]],Table228[],19,FALSE),0) -> 0 | D76: =IFERROR(VLOOKUP(Table26[[#This Row],[Asset]],Table228[#All],20,FALSE),0) -> 0 | E76: Solana | F76: =Table26[[#This Row],[How many tokens]]*Table26[[#This Row],[Current Price]] -> 0 | G76: =IFERROR(VLOOKUP(Table26[[#This Row],[Asset]],Table228[#All],16,FALSE),0) -> 0 | H76: =IFERROR(VLOOKUP(Table26[[#This Row],[Asset]],Table228[#All],18,FALSE),0) -> 0 | I76: =IFERROR((Table26[[#This Row],[Current Price]]-Table26[[#This Row],[Average Entry]])/Table26[[#This Row],[Average Entry]],0) -> 0 | J76: 32.57
A77: Node Aliens | B77: NFT | C77: =IFERROR(VLOOKUP(Table26[[#This Row],[Asset]],Table228[],19,FALSE),0) -> -2552 | D77: =IFERROR(VLOOKUP(Table26[[#This Row],[Asset]],Table228[#All],20,FALSE),0) -> 0 | E77: Solana | F77: =Table26[[#This Row],[How many tokens]]*Table26[[#This Row],[Current Price]] -> 0 | G77: =IFERROR(VLOOKUP(Table26[[#This Row],[Asset]],Table228[#All],16,FALSE),0) -> 30 | H77: =IFERROR(VLOOKUP(Table26[[#This Row],[Asset]],Table228[#All],18,FALSE),0) -> 0 | I77: =IFERROR((Table26[[#This Row],[Current Price]]-Table26[[#This Row],[Average Entry]])/Table26[[#This Row],[Average Entry]],0) -> -0.90533333 | J77: 2.84
A78: FUTURE/SOL | B78: Meme | C78: =IFERROR(VLOOKUP(Table26[[#This Row],[Asset]],Table228[],19,FALSE),0) -> -8.64 | D78: =IFERROR(VLOOKUP(Table26[[#This Row],[Asset]],Table228[#All],20,FALSE),0) -> 0 | E78: Solana | F78: =Table26[[#This Row],[How many tokens]]*Table26[[#This Row],[Current Price]] -> 0 | G78: =IFERROR(VLOOKUP(Table26[[#This Row],[Asset]],Table228[#All],16,FALSE),0) -> 763.64 | H78: =IFERROR(VLOOKUP(Table26[[#This Row],[Asset]],Table228[#All],18,FALSE),0) -> 0 | I78: =IFERROR((Table26[[#This Row],[Current Price]]-Table26[[#This Row],[Average Entry]])/Table26[[#This Row],[Average Entry]],0) -> -0.011314232 | J78: 755
A79: BAT | B79: Advertising | C79: =IFERROR(VLOOKUP(Table26[[#This Row],[Asset]],Table228[],19,FALSE),0) -> -1318.0364 | D79: =IFERROR(VLOOKUP(Table26[[#This Row],[Asset]],Table228[#All],20,FALSE),0) -> 0 | E79: Ethereum | F79: =Table26[[#This Row],[How many tokens]]*Table26[[#This Row],[Current Price]] -> 0 | G79: =IFERROR(VLOOKUP(Table26[[#This Row],[Asset]],Table228[#All],16,FALSE),0) -> 0.29432184 | H79: =IFERROR(VLOOKUP(Table26[[#This Row],[Asset]],Table228[#All],18,FALSE),0) -> 0 | I79: =IFERROR((Table26[[#This Row],[Current Price]]-Table26[[#This Row],[Average Entry]])/Table26[[#This Row],[Average Entry]],0) -> -0.34595407 | J79: 0.1925
... A93: BadKid | B93: NFT | C93: =IFERROR(VLOOKUP(Table26[[#This Row],[Asset]],Table228[],19,FALSE),0) -> 0 | D93: =IFERROR(VLOOKUP(Table26[[#This Row],[Asset]],Table228[#All],20,FALSE),0) -> 0 | E93: Stargaze | F93: =Table26[[#This Row],[How many tokens]]*Table26[[#This Row],[Current Price]] -> 0 | G93: =IFERROR(VLOOKUP(Table26[[#This Row],[Asset]],Table228[#All],16,FALSE),0) -> 0 | H93: =IFERROR(VLOOKUP(Table26[[#This Row],[Asset]],Table228[#All],18,FALSE),0) -> 0 | I93: =IFERROR((Table26[[#This Row],[Current Price]]-Table26[[#This Row],[Average Entry]])/Table26[[#This Row],[Average Entry]],0) -> 0 | J93: 0
A94: USDS/JitoSOL | C94: =IFERROR(VLOOKUP(Table26[[#This Row],[Asset]],Table228[],19,FALSE),0) -> -120 | D94: =IFERROR(VLOOKUP(Table26[[#This Row],[Asset]],Table228[#All],20,FALSE),0) -> 0 | F94: =Table26[[#This Row],[How many tokens]]*Table26[[#This Row],[Current Price]] -> 0 | G94: =IFERROR(VLOOKUP(Table26[[#This Row],[Asset]],Table228[#All],16,FALSE),0) -> 1790 | H94: =IFERROR(VLOOKUP(Table26[[#This Row],[Asset]],Table228[#All],18,FALSE),0) -> 0 | I94: =IFERROR((Table26[[#This Row],[Current Price]]-Table26[[#This Row],[Average Entry]])/Table26[[#This Row],[Average Entry]],0) -> 0 | J94: 1790
A95: HYPE | C95: =IFERROR(VLOOKUP(Table26[[#This Row],[Asset]],Table228[],19,FALSE),0) -> 0 | D95: =IFERROR(VLOOKUP(Table26[[#This Row],[Asset]],Table228[#All],20,FALSE),0) -> 0 | F95: =Table26[[#This Row],[How many tokens]]*Table26[[#This Row],[Current Price]] -> 0 | G95: =IFERROR(VLOOKUP(Table26[[#This Row],[Asset]],Table228[#All],16,FALSE),0) -> 0 | H95: =IFERROR(VLOOKUP(Table26[[#This Row],[Asset]],Table228[#All],18,FALSE),0) -> 0 | I95: =IFERROR((Table26[[#This Row],[Current Price]]-Table26[[#This Row],[Average Entry]])/Table26[[#This Row],[Average Entry]],0) -> 0 | J95: 5.93
A96: FORTH | C96: =IFERROR(VLOOKUP(Table26[[#This Row],[Asset]],Table228[],19,FALSE),0) -> -171.73791 | D96: =IFERROR(VLOOKUP(Table26[[#This Row],[Asset]],Table228[#All],20,FALSE),0) -> 0 | F96: =Table26[[#This Row],[How many tokens]]*Table26[[#This Row],[Current Price]] -> 0 | G96: =IFERROR(VLOOKUP(Table26[[#This Row],[Asset]],Table228[#All],16,FALSE),0) -> 4.56 | H96: =IFERROR(VLOOKUP(Table26[[#This Row],[Asset]],Table228[#All],18,FALSE),0) -> 0 | I96: =IFERROR((Table26[[#This Row],[Current Price]]-Table26[[#This Row],[Average Entry]])/Table26[[#This Row],[Average Entry]],0) -> 0 | J96: 4.56
A97: NEXT (CLEAR) | C97: =IFERROR(VLOOKUP(Table26[[#This Row],[Asset]],Table228[],19,FALSE),0) -> -248.9408 | D97: =IFERROR(VLOOKUP(Table26[[#This Row],[Asset]],Table228[#All],20,FALSE),0) -> 0 | F97: =Table26[[#This Row],[How many tokens]]*Table26[[#This Row],[Current Price]] -> 0 | G97: =IFERROR(VLOOKUP(Table26[[#This Row],[Asset]],Table228[#All],16,FALSE),0) -> 0.1385802 | H97: =IFERROR(VLOOKUP(Table26[[#This Row],[Asset]],Table228[#All],18,FALSE),0) -> 0 | I97: =IFERROR((Table26[[#This Row],[Current Price]]-Table26[[#This Row],[Average Entry]])/Table26[[#This Row],[Average Entry]],0) -> 0.0037508705 | J97: 0.1391
A98: PYTHENIAN | B98: NFT | C98: =IFERROR(VLOOKUP(Table26[[#This Row],[Asset]],Table228[],19,FALSE),0) -> -918.0998 | D98: =IFERROR(VLOOKUP(Table26[[#This Row],[Asset]],Table228[#All],20,FALSE),0) -> 0 | F98: =Table26[[#This Row],[How many tokens]]*Table26[[#This Row],[Current Price]] -> 0 | G98: =IFERROR(VLOOKUP(Table26[[#This Row],[Asset]],Table228[#All],16,FALSE),0) -> 1422.0998 | H98: =IFERROR(VLOOKUP(Table26[[#This Row],[Asset]],Table228[#All],18,FALSE),0) -> 0 | I98: =IFERROR((Table26[[#This Row],[Current Price]]-Table26[[#This Row],[Average Entry]])/Table26[[#This Row],[Average Entry]],0) -> -7.0177916e-05 | J98: 1422
A99: griffain | B99: AI agent | C99: =IFERROR(VLOOKUP(Table26[[#This Row],[Asset]],Table228[],19,FALSE),0) -> 904.85911 | D99: =IFERROR(VLOOKUP(Table26[[#This Row],[Asset]],Table228[#All],20,FALSE),0) -> 0 | F99: =Table26[[#This Row],[How many tokens]]*Table26[[#This Row],[Current Price]] -> 0 | G99: =IFERROR(VLOOKUP(Table26[[#This Row],[Asset]],Table228[#All],16,FALSE),0) -> 0.206 | H99: =IFERROR(VLOOKUP(Table26[[#This Row],[Asset]],Table228[#All],18,FALSE),0) -> 0 | I99: =IFERROR((Table26[[#This Row],[Current Price]]-Table26[[#This Row],[Average Entry]])/Table26[[#This Row],[Average Entry]],0) -> -0.004368932 | J99: 0.2051
A100: Tensorian | B100: NFT | C100: =IFERROR(VLOOKUP(Table26[[#This Row],[Asset]],Table228[],19,FALSE),0) -> -2549.9 | D100: =IFERROR(VLOOKUP(Table26[[#This Row],[Asset]],Table228[#All],20,FALSE),0) -> 0 | F100: =Table26[[#This Row],[How many tokens]]*Table26[[#This Row],[Current Price]] -> 0 | G100: =IFERROR(VLOOKUP(Table26[[#This Row],[Asset]],Table228[#All],16,FALSE),0) -> 1476.5 | H100: =IFERROR(VLOOKUP(Table26[[#This Row],[Asset]],Table228[#All],18,FALSE),0) -> 0 | I100: =IFERROR((Table26[[#This Row],[Current Price]]-Table26[[#This Row],[Average Entry]])/Table26[[#This Row],[Average Entry]],0) -> -0.030816119 | J100: 1431
A101: L24AI | C101: =IFERROR(VLOOKUP(Table26[[#This Row],[Asset]],Table228[],19,FALSE),0) -> -73.450228 | D101: =IFERROR(VLOOKUP(Table26[[#This Row],[Asset]],Table228[#All],20,FALSE),0) -> 0 | F101: =Table26[[#This Row],[How many tokens]]*Table26[[#This Row],[Current Price]] -> 0 | G101: =IFERROR(VLOOKUP(Table26[[#This Row],[Asset]],Table228[#All],16,FALSE),0) -> 0.00116405 | H101: =IFERROR(VLOOKUP(Table26[[#This Row],[Asset]],Table228[#All],18,FALSE),0) -> 0 | I101: =IFERROR((Table26[[#This Row],[Current Price]]-Table26[[#This Row],[Average Entry]])/Table26[[#This Row],[Average Entry]],0) -> -0.026674112 | J101: 0.001133
A102: FOMO | C102: =IFERROR(VLOOKUP(Table26[[#This Row],[Asset]],Table228[],19,FALSE),0) -> -84.667488 | D102: =IFERROR(VLOOKUP(Table26[[#This Row],[Asset]],Table228[#All],20,FALSE),0) -> 0 | E102: Solana | F102: =Table26[[#This Row],[How many tokens]]*Table26[[#This Row],[Current Price]] -> 0 | G102: =IFERROR(VLOOKUP(Table26[[#This Row],[Asset]],Table228[#All],16,FALSE),0) -> 0.0003949 | H102: =IFERROR(VLOOKUP(Table26[[#This Row],[Asset]],Table228[#All],18,FALSE),0) -> 0 | I102: =IFERROR((Table26[[#This Row],[Current Price]]-Table26[[#This Row],[Average Entry]])/Table26[[#This Row],[Average Entry]],0) -> 0 | J102: 0.0003949
A103: CATF | C103: =IFERROR(VLOOKUP(Table26[[#This Row],[Asset]],Table228[],19,FALSE),0) -> 598 | D103: =IFERROR(VLOOKUP(Table26[[#This Row],[Asset]],Table228[#All],20,FALSE),0) -> 0 | E103: Solana | F103: =Table26[[#This Row],[How many tokens]]*Table26[[#This Row],[Current Price]] -> 0 | G103: =IFERROR(VLOOKUP(Table26[[#This Row],[Asset]],Table228[#All],16,FALSE),0) -> 0.0027 | H103: =IFERROR(VLOOKUP(Table26[[#This Row],[Asset]],Table228[#All],18,FALSE),0) -> 0 | I103: =IFERROR((Table26[[#This Row],[Current Price]]-Table26[[#This Row],[Average Entry]])/Table26[[#This Row],[Average Entry]],0) -> -0.061481481 | J103: 0.002534
A104: HNT | B104: DePIN | C104: =IFERROR(VLOOKUP(Table26[[#This Row],[Asset]],Table228[],19,FALSE),0) -> -25.590831 | D104: =IFERROR(VLOOKUP(Table26[[#This Row],[Asset]],Table228[#All],20,FALSE),0) -> 0.00218127 | E104: Solana | F104: =Table26[[#This Row],[How many tokens]]*Table26[[#This Row],[Current Price]] -> -0.12319593 | G104: =IFERROR(VLOOKUP(Table26[[#This Row],[Asset]],Table228[#All],16,FALSE),0) -> 6.84 | H104: =IFERROR(VLOOKUP(Table26[[#This Row],[Asset]],Table228[#All],18,FALSE),0) -> -0.01833 | I104: =IFERROR((Table26[[#This Row],[Current Price]]-Table26[[#This Row],[Average Entry]])/Table26[[#This Row],[Average Entry]],0) -> -0.017397661 | J104: 6.721
A105: ai16z | B105: AI agent | C105: =IFERROR(VLOOKUP(Table26[[#This Row],[Asset]],Table228[],19,FALSE),0) -> 1515.2518 | D105: =IFERROR(VLOOKUP(Table26[[#This Row],[Asset]],Table228[#All],20,FALSE),0) -> -0.065107401 | F105: =Table26[[#This Row],[How many tokens]]*Table26[[#This Row],[Current Price]] -> -0.20584806 | G105: =IFERROR(VLOOKUP(Table26[[#This Row],[Asset]],Table228[#All],16,FALSE),0) -> 0.22562475 | H105: =IFERROR(VLOOKUP(Table26[[#This Row],[Asset]],Table228[#All],18,FALSE),0) -> -0.623782 | I105: =IFERROR((Table26[[#This Row],[Current Price]]-Table26[[#This Row],[Average Entry]])/Table26[[#This Row],[Average Entry]],0) -> 0.46260549 | J105: 0.33
A106: STRD | B106: Liquid Staking | C106: =IFERROR(VLOOKUP(Table26[[#This Row],[Asset]],Table228[],19,FALSE),0) -> -203.22563 | D106: =IFERROR(VLOOKUP(Table26[[#This Row],[Asset]],Table228[#All],20,FALSE),0) -> 156.9648 | E106: Cosmos | F106: =Table26[[#This Row],[How many tokens]]*Table26[[#This Row],[Current Price]] -> -65.1552 | G106: =IFERROR(VLOOKUP(Table26[[#This Row],[Asset]],Table228[#All],16,FALSE),0) -> 3 | H106: =IFERROR(VLOOKUP(Table26[[#This Row],[Asset]],Table228[#All],18,FALSE),0) -> -74.04 | I106: =IFERROR((Table26[[#This Row],[Current Price]]-Table26[[#This Row],[Average Entry]])/Table26[[#This Row],[Average Entry]],0) -> -0.70666667 | J106: 0.88
A107: FUNGI | C107: =IFERROR(VLOOKUP(Table26[[#This Row],[Asset]],Table228[],19,FALSE),0) -> 2072.1533 | D107: =IFERROR(VLOOKUP(Table26[[#This Row],[Asset]],Table228[#All],20,FALSE),0) -> 28.017552 | F107: =Table26[[#This Row],[How many tokens]]*Table26[[#This Row],[Current Price]] -> -116.52926 | G107: =IFERROR(VLOOKUP(Table26[[#This Row],[Asset]],Table228[#All],16,FALSE),0) -> 0.0022203762 | H107: =IFERROR(VLOOKUP(Table26[[#This Row],[Asset]],Table228[#All],18,FALSE),0) -> -65100.145 | I107: =IFERROR((Table26[[#This Row],[Current Price]]-Table26[[#This Row],[Average Entry]])/Table26[[#This Row],[Average Entry]],0) -> -0.1938303 | J107: 0.00179
A108: ME | C108: =IFERROR(VLOOKUP(Table26[[#This Row],[Asset]],Table228[],19,FALSE),0) -> 2048.6905 | D108: =IFERROR(VLOOKUP(Table26[[#This Row],[Asset]],Table228[#All],20,FALSE),0) -> -1294.2474 | F108: =Table26[[#This Row],[How many tokens]]*Table26[[#This Row],[Current Price]] -> -1294.2474 | G108: =IFERROR(VLOOKUP(Table26[[#This Row],[Asset]],Table228[#All],16,FALSE),0) -> 0 | H108: =IFERROR(VLOOKUP(Table26[[#This Row],[Asset]],Table228[#All],18,FALSE),0) -> -227.46 | I108: =IFERROR((Table26[[#This Row],[Current Price]]-Table26[[#This Row],[Average Entry]])/Table26[[#This Row],[Average Entry]],0) -> 0 | J108: 5.69
A109: MPLX | B109: NFT | C109: =IFERROR(VLOOKUP(Table26[[#This Row],[Asset]],Table228[],19,FALSE),0) -> -3505.0881 | D109: =IFERROR(VLOOKUP(Table26[[#This Row],[Asset]],Table228[#All],20,FALSE),0) -> 631.23979 | E109: Solana | F109: =Table26[[#This Row],[How many tokens]]*Table26[[#This Row],[Current Price]] -> -1328.6974 | G109: =IFERROR(VLOOKUP(Table26[[#This Row],[Asset]],Table228[#All],16,FALSE),0) -> 0.29501633 | H109: =IFERROR(VLOOKUP(Table26[[#This Row],[Asset]],Table228[#All],18,FALSE),0) -> -6643.4871 | I109: =IFERROR((Table26[[#This Row],[Current Price]]-Table26[[#This Row],[Average Entry]])/Table26[[#This Row],[Average Entry]],0) -> -0.32207143 | J109: 0.2
A110: JLP | B110: Perpetual Exchange | C110: =IFERROR(VLOOKUP(Table26[[#This Row],[Asset]],Table228[],19,FALSE),0) -> 4538.39 | D110: =IFERROR(VLOOKUP(Table26[[#This Row],[Asset]],Table228[#All],20,FALSE),0) -> -403.08573 | E110: Solana | F110: =Table26[[#This Row],[How many tokens]]*Table26[[#This Row],[Current Price]] -> -1460.244 | G110: =IFERROR(VLOOKUP(Table26[[#This Row],[Asset]],Table228[#All],16,FALSE),0) -> 2.4469848 | H110: =IFERROR(VLOOKUP(Table26[[#This Row],[Asset]],Table228[#All],18,FALSE),0) -> -432.02484 | I110: =IFERROR((Table26[[#This Row],[Current Price]]-Table26[[#This Row],[Average Entry]])/Table26[[#This Row],[Average Entry]],0) -> 0.38129177 | J110: 3.38
A111: NMR | B111: Decentralized Hedge Fund | C111: =IFERROR(VLOOKUP(Table26[[#This Row],[Asset]],Table228[],19,FALSE),0) -> -517.13771 | D111: =IFERROR(VLOOKUP(Table26[[#This Row],[Asset]],Table228[#All],20,FALSE),0) -> 0.005272347 | F111: =Table26[[#This Row],[How many tokens]]*Table26[[#This Row],[Current Price]] -> -0.18669 | G111: =IFERROR(VLOOKUP(Table26[[#This Row],[Asset]],Table228[#All],16,FALSE),0) -> 15.115145 | H111: =IFERROR(VLOOKUP(Table26[[#This Row],[Asset]],Table228[#All],18,FALSE),0) -> -0.0127 | I111: =IFERROR((Table26[[#This Row],[Current Price]]-Table26[[#This Row],[Average Entry]])/Table26[[#This Row],[Average Entry]],0) -> -0.027465527 | J111: 14.7
A112: PUMP | B112: Defi | C112: =IFERROR(VLOOKUP(Table26[[#This Row],[Asset]],Table228[],19,FALSE),0) -> -60.079127 | D112: =IFERROR(VLOOKUP(Table26[[#This Row],[Asset]],Table228[#All],20,FALSE),0) -> 461.36195 | F112: =Table26[[#This Row],[How many tokens]]*Table26[[#This Row],[Current Price]] -> 1108.4853 | G112: =IFERROR(VLOOKUP(Table26[[#This Row],[Asset]],Table228[#All],16,FALSE),0) -> 0.0041560055 | H112: =IFERROR(VLOOKUP(Table26[[#This Row],[Asset]],Table228[#All],18,FALSE),0) -> 155708 | I112: =IFERROR((Table26[[#This Row],[Current Price]]-Table26[[#This Row],[Average Entry]])/Table26[[#This Row],[Average Entry]],0) -> 0.71294288 | J112: 0.007119
A113: ElizaOs | B113: AI agent | C113: =IFERROR(VLOOKUP(Table26[[#This Row],[Asset]],Table228[],19,FALSE),0) -> -608.74787 | D113: =IFERROR(VLOOKUP(Table26[[#This Row],[Asset]],Table228[#All],20,FALSE),0) -> 0 | F113: =Table26[[#This Row],[How many tokens]]*Table26[[#This Row],[Current Price]] -> 0 | G113: =IFERROR(VLOOKUP(Table26[[#This Row],[Asset]],Table228[#All],16,FALSE),0) -> 0.0079 | H113: =IFERROR(VLOOKUP(Table26[[#This Row],[Asset]],Table228[#All],18,FALSE),0) -> 0 | I113: =IFERROR((Table26[[#This Row],[Current Price]]-Table26[[#This Row],[Average Entry]])/Table26[[#This Row],[Average Entry]],0) -> -0.11392405 | J113: 0.007

Sheet Crypto_Trades
A1: Transactions:
A2: 1 | B2: 2 | C2: 3 | D2: 4 | E2: 5 | F2: 6 | G2: 7 | H2: 8 | I2: 9 | J2: 10 | K2: 11 | L2: 12 | M2: 13 | N2: 14 | O2: 15 | P2: 16 | Q2: 17 | R2: 18 | S2: 19 | T2: 20 | U2: 21
A3: Asset | B3: Date | C3: State | D3: Platform | E3: Specific wallet | F3: Price | G3: Number | H3: Bought number | I3: Sold Number | J3: Bought amount | K3: Sold amount | L3: Total bought Number | M3: Total Sold Number | N3: Total bought Amount | O3: Total Sold Amount | P3: Ave Entry price | Q3: Ave exit price | R3: How many tokens now | S3: Realized Profit | T3: Unrealized Profit | U3: Current Price
A4: PSY | B4: 45292 | C4: Staked | D4: Wallet | E4: Phantom 2 | F4: 0.005 | G4: =30000+96087.42 -> 126087.42 | H4: =IF(G4>0,G4,0) -> 126087.42 | I4: =IF(G4<0,ABS(G4),0) -> 0 | J4: =H4*F4 -> 630.4371 | K4: =I4*F4 -> 0 | L4: =SUMIF(Table228[[#All],[Asset]],Table228[[#This Row],[Asset]],Table228[[#All],[Bought number]]) -> 126087.42 | M4: =SUMIF(Table228[[#All],[Asset]],Table228[[#This Row],[Asset]],Table228[[#All],[Sold Number]]) -> 96094.429 | N4: =SUMIF(Table228[[#All],[Asset]],Table228[[#This Row],[Asset]],Table228[[#All],[Bought amount]]) -> 630.4371 | O4: =SUMIF(Table228[[#All],[Asset]],Table228[[#This Row],[Asset]],Table228[[#All],[Sold amount]]) -> 60.60508 | P4: =Table228[[#This Row],[Total bought Amount]]/Table228[[#This Row],[Total bought Number]] -> 0.005 | Q4: =IFERROR(Table228[[#This Row],[Total Sold Amount]]/Table228[[#This Row],[Total Sold Number]],0) -> 0.00063068256 | R4: =Table228[[#This Row],[Total bought Number]]-Table228[[#This Row],[Total Sold Number]] -> 29992.991 | S4: =(Table228[[#This Row],[Ave exit price]]-Table228[[#This Row],[Ave Entry price]])*Table228[[#This Row],[Total Sold Number]] -> -419.86707 | T4: =(Table228[[#This Row],[Current Price]]-Table228[[#This Row],[Ave Entry price]])*Table228[[#This Row],[How many tokens now]] -> -120.27189 | U4: =VLOOKUP(Table228[[#This Row],[Asset]],Table26[#All],10,FALSE) -> 0.00099
A5: PSY | B5: 45292 | C5: Staked | D5: Wallet | E5: Phantom 2 | F5: 0.01 | G5: -7 | H5: =IF(G5>0,G5,0) -> 0 | I5: =IF(G5<0,ABS(G5),0) -> 7 | J5: =H5*F5 -> 0 | K5: =I5*F5 -> 0.07 | L5: =SUMIF(Table228[[#All],[Asset]],Table228[[#This Row],[Asset]],Table228[[#All],[Bought number]]) -> 126087.42 | M5: =SUMIF(Table228[[#All],[Asset]],Table228[[#This Row],[Asset]],Table228[[#All],[Sold Number]]) -> 96094.429 | N5: =SUMIF(Table228[[#All],[Asset]],Table228[[#This Row],[Asset]],Table228[[#All],[Bought amount]]) -> 630.4371 | O5: =SUMIF(Table228[[#All],[Asset]],Table228[[#This Row],[Asset]],Table228[[#All],[Sold amount]]) -> 60.60508 | P5: =Table228[[#This Row],[Total bought Amount]]/Table228[[#This Row],[Total bought Number]] -> 0.005 | Q5: =IFERROR(Table228[[#This Row],[Total Sold Amount]]/Table228[[#This Row],[Total Sold Number]],0) -> 0.00063068256 | R5: =Table228[[#This Row],[Total bought Number]]-Table228[[#This Row],[Total Sold Number]] -> 29992.991 | S5: =(Table228[[#This Row],[Ave exit price]]-Table228[[#This Row],[Ave Entry price]])*Table228[[#This Row],[Total Sold Number]] -> -419.86707 | T5: =(Table228[[#This Row],[Current Price]]-Table228[[#This Row],[Ave Entry price]])*Table228[[#This Row],[How many tokens now]] -> -120.27189 | U5: =VLOOKUP(Table228[[#This Row],[Asset]],Table26[#All],10,FALSE) -> 0.00099
A6: HXRO | B6: 45344 | C6: Staked | D6: Wallet | E6: Phantom 2 | F6: 0.08 | G6: 15422.77 | H6: =IF(G6>0,G6,0) -> 15422.77 | I6: =IF(G6<0,ABS(G6),0) -> 0 | J6: =H6*F6 -> 1233.8216 | K6: =I6*F6 -> 0 | L6: =SUMIF(Table228[[#All],[Asset]],Table228[[#This Row],[Asset]],Table228[[#All],[Bought number]]) -> 27671.77 | M6: =SUMIF(Table228[[#All],[Asset]],Table228[[#This Row],[Asset]],Table228[[#All],[Sold Number]]) -> 0 | N6: =SUMIF(Table228[[#All],[Asset]],Table228[[#This Row],[Asset]],Table228[[#All],[Bought amount]]) -> 2213.7416 | O6: =SUMIF(Table228[[#All],[Asset]],Table228[[#This Row],[Asset]],Table228[[#All],[Sold amount]]) -> 0 | P6: =Table228[[#This Row],[Total bought Amount]]/Table228[[#This Row],[Total bought Number]] -> 0.08 | Q6: =IFERROR(Table228[[#This Row],[Total Sold Amount]]/Table228[[#This Row],[Total Sold Number]],0) -> 0 | R6: =Table228[[#This Row],[Total bought Number]]-Table228[[#This Row],[Total Sold Number]] -> 27671.77 | S6: =(Table228[[#This Row],[Ave exit price]]-Table228[[#This Row],[Ave Entry price]])*Table228[[#This Row],[Total Sold Number]] -> 0 | T6: =(Table228[[#This Row],[Current Price]]-Table228[[#This Row],[Ave Entry price]])*Table228[[#This Row],[How many tokens now]] -> -2075.3828 | U6: =VLOOKUP(Table228[[#This Row],[Asset]],Table26[#All],10,FALSE) -> 0.005
A7: SOL | B7: 45444 | C7: JitoSol/SOL LP | D7: Kamino | E7: Phantom 2 | F7: 150 | G7: 96.3076 | H7: =IF(G7>0,G7,0) -> 96.3076 | I7: =IF(G7<0,ABS(G7),0) -> 0 | J7: =H7*F7 -> 14446.14 | K7: =I7*F7 -> 0 | L7: =SUMIF(Table228[[#All],[Asset]],Table228[[#This Row],[Asset]],Table228[[#All],[Bought number]]) -> 154.9266 | M7: =SUMIF(Table228[[#All],[Asset]],Table228[[#This Row],[Asset]],Table228[[#All],[Sold Number]]) -> 79.675 | N7: =SUMIF(Table228[[#All],[Asset]],Table228[[#This Row],[Asset]],Table228[[#All],[Bought amount]]) -> 22897.17 | O7: =SUMIF(Table228[[#All],[Asset]],Table228[[#This Row],[Asset]],Table228[[#All],[Sold amount]]) -> 11736.941 | P7: =Table228[[#This Row],[Total bought Amount]]/Table228[[#This Row],[Total bought Number]] -> 147.79366 | Q7: =IFERROR(Table228[[#This Row],[Total Sold Amount]]/Table228[[#This Row],[Total Sold Number]],0) -> 147.31021 | R7: =Table228[[#This Row],[Total bought Number]]-Table228[[#This Row],[Total Sold Number]] -> 75.2516 | S7: =(Table228[[#This Row],[Ave exit price]]-Table228[[#This Row],[Ave Entry price]])*Table228[[#This Row],[Total Sold Number]] -> -38.51938 | T7: =(Table228[[#This Row],[Current Price]]-Table228[[#This Row],[Ave Entry price]])*Table228[[#This Row],[How many tokens now]] -> 1671.0622 | U7: =VLOOKUP(Table228[[#This Row],[Asset]],Table26[#All],10,FALSE) -> 170
A8: KMNO/JitoSOL | B8: 45444 | C8: LP | D8: Kamino | E8: Phantom 2 | F8: 4680 | G8: 1 | H8: =IF(G8>0,G8,0) -> 1 | I8: =IF(G8<0,ABS(G8),0) -> 0 | J8: =H8*F8 -> 4680 | K8: =I8*F8 -> 0 | L8: =SUMIF(Table228[[#All],[Asset]],Table228[[#This Row],[Asset]],Table228[[#All],[Bought number]]) -> 2 | M8: =SUMIF(Table228[[#All],[Asset]],Table228[[#This Row],[Asset]],Table228[[#All],[Sold Number]]) -> 1.5 | N8: =SUMIF(Table228[[#All],[Asset]],Table228[[#This Row],[Asset]],Table228[[#All],[Bought amount]]) -> 9600 | O8: =SUMIF(Table228[[#All],[Asset]],Table228[[#This Row],[Asset]],Table228[[#All],[Sold amount]]) -> 11750 | P8: =Table228[[#This Row],[Total bought Amount]]/Table228[[#This Row],[Total bought Number]] -> 4800 | Q8: =IFERROR(Table228[[#This Row],[Total Sold Amount]]/Table228[[#This Row],[Total Sold Number]],0) -> 7833.3333 | R8: =Table228[[#This Row],[Total bought Number]]-Table228[[#This Row],[Total Sold Number]] -> 0.5 | S8: =(Table228[[#This Row],[Ave exit price]]-Table228[[#This Row],[Ave Entry price]])*Table228[[#This Row],[Total Sold Number]] -> 4550 | T8: =(Table228[[#This Row],[Current Price]]-Table228[[#This Row],[Ave Entry price]])*Table228[[#This Row],[How many tokens now]] -> -210 | U8: =VLOOKUP(Table228[[#This Row],[Asset]],Table26[#All],10,FALSE) -> 4380
A9: ZEX/JitoSol | B9: 45444 | C9: LP | D9: Kamino | E9: Phantom 2 | F9: 2560 | G9: 1 | H9: =IF(G9>0,G9,0) -> 1 | I9: =IF(G9<0,ABS(G9),0) -> 0 | J9: =H9*F9 -> 2560 | K9: =I9*F9 -> 0 | L9: =SUMIF(Table228[[#All],[Asset]],Table228[[#This Row],[Asset]],Table228[[#All],[Bought number]]) -> 2 | M9: =SUMIF(Table228[[#All],[Asset]],Table228[[#This Row],[Asset]],Table228[[#All],[Sold Number]]) -> 1 | N9: =SUMIF(Table228[[#All],[Asset]],Table228[[#This Row],[Asset]],Table228[[#All],[Bought amount]]) -> 3497.62 | O9: =SUMIF(Table228[[#All],[Asset]],Table228[[#This Row],[Asset]],Table228[[#All],[Sold amount]]) -> 2110 | P9: =Table228[[#This Row],[Total bought Amount]]/Table228[[#This Row],[Total bought Number]] -> 1748.81 | Q9: =IFERROR(Table228[[#This Row],[Total Sold Amount]]/Table228[[#This Row],[Total Sold Number]],0) -> 2110 | R9: =Table228[[#This Row],[Total bought Number]]-Table228[[#This Row],[Total Sold Number]] -> 1 | S9: =(Table228[[#This Row],[Ave exit price]]-Table228[[#This Row],[Ave Entry price]])*Table228[[#This Row],[Total Sold Number]] -> 361.19 | T9: =(Table228[[#This Row],[Current Price]]-Table228[[#This Row],[Ave Entry price]])*Table228[[#This Row],[How many tokens now]] -> 51.19 | U9: =VLOOKUP(Table228[[#This Row],[Asset]],Table26[#All],10,FALSE) -> 1800
A10: Whales/SOL | B10: 45444 | C10: LP | D10: Kamino | E10: Phantom 2 | F10: =777.4+693.61 -> 1471.01 | G10: 1 | H10: =IF(G10>0,G10,0) -> 1 | I10: =IF(G10<0,ABS(G10),0) -> 0 | J10: =H10*F10 -> 1471.01 | K10: =I10*F10 -> 0 | L10: =SUMIF(Table228[[#All],[Asset]],Table228[[#This Row],[Asset]],Table228[[#All],[Bought number]]) -> 1 | M10: =SUMIF(Table228[[#All],[Asset]],Table228[[#This Row],[Asset]],Table228[[#All],[Sold Number]]) -> 0 | N10: =SUMIF(Table228[[#All],[Asset]],Table228[[#This Row],[Asset]],Table228[[#All],[Bought amount]]) -> 1471.01 | O10: =SUMIF(Table228[[#All],[Asset]],Table228[[#This Row],[Asset]],Table228[[#All],[Sold amount]]) -> 0 | P10: =Table228[[#This Row],[Total bought Amount]]/Table228[[#This Row],[Total bought Number]] -> 1471.01 | Q10: =IFERROR(Table228[[#This Row],[Total Sold Amount]]/Table228[[#This Row],[Total Sold Number]],0) -> 0 | R10: =Table228[[#This Row],[Total bought Number]]-Table228[[#This Row],[Total Sold Number]] -> 1 | S10: =(Table228[[#This Row],[Ave exit price]]-Table228[[#This Row],[Ave Entry price]])*Table228[[#This Row],[Total Sold Number]] -> 0 | T10: =(Table228[[#This Row],[Current Price]]-Table228[[#This Row],[Ave Entry price]])*Table228[[#This Row],[How many tokens now]] -> -691.29 | U10: =VLOOKUP(Table228[[#This Row],[Asset]],Table26[#All],10,FALSE) -> 779.72
A11: W/JitoSol | B11: 45444 | C11: LP | D11: Kamino | E11: Phantom 2 | F11: =3349.53+370.39 -> 3719.92 | G11: 1 | H11: =IF(G11>0,G11,0) -> 1 | I11: =IF(G11<0,ABS(G11),0) -> 0 | J11: =H11*F11 -> 3719.92 | K11: =I11*F11 -> 0 | L11: =SUMIF(Table228[[#All],[Asset]],Table228[[#This Row],[Asset]],Table228[[#All],[Bought number]]) -> 1 | M11: =SUMIF(Table228[[#All],[Asset]],Table228[[#This Row],[Asset]],Table228[[#All],[Sold Number]]) -> 0 | N11: =SUMIF(Table228[[#All],[Asset]],Table228[[#This Row],[Asset]],Table228[[#All],[Bought amount]]) -> 3719.92 | O11: =SUMIF(Table228[[#All],[Asset]],Table228[[#This Row],[Asset]],Table228[[#All],[Sold amount]]) -> 0 | P11: =Table228[[#This Row],[Total bought Amount]]/Table228[[#This Row],[Total bought Number]] -> 3719.92 | Q11: =IFERROR(Table228[[#This Row],[Total Sold Amount]]/Table228[[#This Row],[Total Sold Number]],0) -> 0 | R11: =Table228[[#This Row],[Total bought Number]]-Table228[[#This Row],[Total Sold Number]] -> 1 | S11: =(Table228[[#This Row],[Ave exit price]]-Table228[[#This Row],[Ave Entry price]])*Table228[[#This Row],[Total Sold Number]] -> 0 | T11: =(Table228[[#This Row],[Current Price]]-Table228[[#This Row],[Ave Entry price]])*Table228[[#This Row],[How many tokens now]] -> -3349.37 | U11: =VLOOKUP(Table228[[#This Row],[Asset]],Table26[#All],10,FALSE) -> 370.55
A12: Velo | B12: 45292 | C12: Staked | D12: Velodrome | E12: Perp wallet | F12: 0.2 | G12: 10019.03 | H12: =IF(G12>0,G12,0) -> 10019.03 | I12: =IF(G12<0,ABS(G12),0) -> 0 | J12: =H12*F12 -> 2003.806 | K12: =I12*F12 -> 0 | L12: =SUMIF(Table228[[#All],[Asset]],Table228[[#This Row],[Asset]],Table228[[#All],[Bought number]]) -> 11156.03 | M12: =SUMIF(Table228[[#All],[Asset]],Table228[[#This Row],[Asset]],Table228[[#All],[Sold Number]]) -> 0 | N12: =SUMIF(Table228[[#All],[Asset]],Table228[[#This Row],[Asset]],Table228[[#All],[Bought amount]]) -> 2003.806 | O12: =SUMIF(Table228[[#All],[Asset]],Table228[[#This Row],[Asset]],Table228[[#All],[Sold amount]]) -> 0 | P12: =Table228[[#This Row],[Total bought Amount]]/Table228[[#This Row],[Total bought Number]] -> 0.1796164 | Q12: =IFERROR(Table228[[#This Row],[Total Sold Amount]]/Table228[[#This Row],[Total Sold Number]],0) -> 0 | R12: =Table228[[#This Row],[Total bought Number]]-Table228[[#This Row],[Total Sold Number]] -> 11156.03 | S12: =(Table228[[#This Row],[Ave exit price]]-Table228[[#This Row],[Ave Entry price]])*Table228[[#This Row],[Total Sold Number]] -> 0 | T12: =(Table228[[#This Row],[Current Price]]-Table228[[#This Row],[Ave Entry price]])*Table228[[#This Row],[How many tokens now]] -> -1291.4935 | U12: =VLOOKUP(Table228[[#This Row],[Asset]],Table26[#All],10,FALSE) -> 0.06385
A13: Velo/USDC | B13: 45292 | C13: LP | D13: Velodrome | E13: Perp wallet | F13: 2744 | G13: 1 | H13: =IF(G13>0,G13,0) -> 1 | I13: =IF(G13<0,ABS(G13),0) -> 0 | J13: =H13*F13 -> 2744 | K13: =I13*F13 -> 0 | L13: =SUMIF(Table228[[#All],[Asset]],Table228[[#This Row],[Asset]],Table228[[#All],[Bought number]]) -> 2 | M13: =SUMIF(Table228[[#All],[Asset]],Table228[[#This Row],[Asset]],Table228[[#All],[Sold Number]]) -> 2 | N13: =SUMIF(Table228[[#All],[Asset]],Table228[[#This Row],[Asset]],Table228[[#All],[Bought amount]]) -> 4244 | O13: =SUMIF(Table228[[#All],[Asset]],Table228[[#This Row],[Asset]],Table228[[#All],[Sold amount]]) -> 4720 | P13: =Table228[[#This Row],[Total bought Amount]]/Table228[[#This Row],[Total bought Number]] -> 2122 | Q13: =IFERROR(Table228[[#This Row],[Total Sold Amount]]/Table228[[#This Row],[Total Sold Number]],0) -> 2360 | R13: =Table228[[#This Row],[Total bought Number]]-Table228[[#This Row],[Total Sold Number]] -> 0 | S13: =(Table228[[#This Row],[Ave exit price]]-Table228[[#This Row],[Ave Entry price]])*Table228[[#This Row],[Total Sold Number]] -> 476 | T13: =(Table228[[#This Row],[Current Price]]-Table228[[#This Row],[Ave Entry price]])*Table228[[#This Row],[How many tokens now]] -> 0 | U13: =VLOOKUP(Table228[[#This Row],[Asset]],Table26[#All],10,FALSE) -> 3500
A14: FTM | B14: 45292 | C14: Staked | D14: Wallet | E14: Perp wallet | F14: 0.41 | G14: 10000 | H14: =IF(G14>0,G14,0) -> 10000 | I14: =IF(G14<0,ABS(G14),0) -> 0 | J14: =H14*F14 -> 4100 | K14: =I14*F14 -> 0 | L14: =SUMIF(Table228[[#All],[Asset]],Table228[[#This Row],[Asset]],Table228[[#All],[Bought number]]) -> 10000 | M14: =SUMIF(Table228[[#All],[Asset]],Table228[[#This Row],[Asset]],Table228[[#All],[Sold Number]]) -> 10000 | N14: =SUMIF(Table228[[#All],[Asset]],Table228[[#This Row],[Asset]],Table228[[#All],[Bought amount]]) -> 4100 | O14: =SUMIF(Table228[[#All],[Asset]],Table228[[#This Row],[Asset]],Table228[[#All],[Sold amount]]) -> 7989.99 | P14: =Table228[[#This Row],[Total bought Amount]]/Table228[[#This Row],[Total bought Number]] -> 0.41 | Q14: =IFERROR(Table228[[#This Row],[Total Sold Amount]]/Table228[[#This Row],[Total Sold Number]],0) -> 0.798999 | R14: =Table228[[#This Row],[Total bought Number]]-Table228[[#This Row],[Total Sold Number]] -> 0 | S14: =(Table228[[#This Row],[Ave exit price]]-Table228[[#This Row],[Ave Entry price]])*Table228[[#This Row],[Total Sold Number]] -> 3889.99 | T14: =(Table228[[#This Row],[Current Price]]-Table228[[#This Row],[Ave Entry price]])*Table228[[#This Row],[How many tokens now]] -> 0 | U14: =VLOOKUP(Table228[[#This Row],[Asset]],Table26[#All],10,FALSE) -> 0.41
A15: USDC | B15: 45292 | C15: Spot | D15: Infinex | E15: Infinex Wallet | F15: 1 | G15: 9000 | H15: =IF(G15>0,G15,0) -> 9000 | I15: =IF(G15<0,ABS(G15),0) -> 0 | J15: =H15*F15 -> 9000 | K15: =I15*F15 -> 0 | L15: =SUMIF(Table228[[#All],[Asset]],Table228[[#This Row],[Asset]],Table228[[#All],[Bought number]]) -> 14504.07 | M15: =SUMIF(Table228[[#All],[Asset]],Table228[[#This Row],[Asset]],Table228[[#All],[Sold Number]]) -> 12705.24 | N15: =SUMIF(Table228[[#All],[Asset]],Table228[[#This Row],[Asset]],Table228[[#All],[Bought amount]]) -> 14005.02 | O15: =SUMIF(Table228[[#All],[Asset]],Table228[[#This Row],[Asset]],Table228[[#All],[Sold amount]]) -> 12705.24 | P15: =Table228[[#This Row],[Total bought Amount]]/Table228[[#This Row],[Total bought Number]] -> 0.96559242 | Q15: =IFERROR(Table228[[#This Row],[Total Sold Amount]]/Table228[[#This Row],[Total Sold Number]],0) -> 1 | R15: =Table228[[#This Row],[Total bought Number]]-Table228[[#This Row],[Total Sold Number]] -> 1798.83 | S15: =(Table228[[#This Row],[Ave exit price]]-Table228[[#This Row],[Ave Entry price]])*Table228[[#This Row],[Total Sold Number]] -> 437.15661 | T15: =(Table228[[#This Row],[Current Price]]-Table228[[#This Row],[Ave Entry price]])*Table228[[#This Row],[How many tokens now]] -> 61.893393 | U15: =VLOOKUP(Table228[[#This Row],[Asset]],Table26[#All],10,FALSE) -> 1
A16: SBR | B16: 45292 | C16: Spot | D16: Wallet | E16: Phantom 2 | F16: 0.0015277 | G16: 17919.968 | H16: =IF(G16>0,G16,0) -> 17919.968 | I16: =IF(G16<0,ABS(G16),0) -> 0 | J16: =H16*F16 -> 27.376335 | K16: =I16*F16 -> 0 | L16: =SUMIF(Table228[[#All],[Asset]],Table228[[#This Row],[Asset]],Table228[[#All],[Bought number]]) -> 17919.968 | M16: =SUMIF(Table228[[#All],[Asset]],Table228[[#This Row],[Asset]],Table228[[#All],[Sold Number]]) -> 0 | N16: =SUMIF(Table228[[#All],[Asset]],Table228[[#This Row],[Asset]],Table228[[#All],[Bought amount]]) -> 27.376335 | O16: =SUMIF(Table228[[#All],[Asset]],Table228[[#This Row],[Asset]],Table228[[#All],[Sold amount]]) -> 0 | P16: =Table228[[#This Row],[Total bought Amount]]/Table228[[#This Row],[Total bought Number]] -> 0.0015277 | Q16: =IFERROR(Table228[[#This Row],[Total Sold Amount]]/Table228[[#This Row],[Total Sold Number]],0) -> 0 | R16: =Table228[[#This Row],[Total bought Number]]-Table228[[#This Row],[Total Sold Number]] -> 17919.968 | S16: =(Table228[[#This Row],[Ave exit price]]-Table228[[#This Row],[Ave Entry price]])*Table228[[#This Row],[Total Sold Number]] -> 0 | T16: =(Table228[[#This Row],[Current Price]]-Table228[[#This Row],[Ave Entry price]])*Table228[[#This Row],[How many tokens now]] -> -0.012543978 | U16: =VLOOKUP(Table228[[#This Row],[Asset]],Table26[#All],10,FALSE) -> 0.001527
A17: SOL | B17: 45474 | C17: Liquid Staked | D17: Drift | E17: Phantom 2 | F17: 150 | G17: 6.4 | H17: =IF(G17>0,G17,0) -> 6.4 | I17: =IF(G17<0,ABS(G17),0) -> 0 | J17: =H17*F17 -> 960 | K17: =I17*F17 -> 0 | L17: =SUMIF(Table228[[#All],[Asset]],Table228[[#This Row],[Asset]],Table228[[#All],[Bought number]]) -> 154.9266 | M17: =SUMIF(Table228[[#All],[Asset]],Table228[[#This Row],[Asset]],Table228[[#All],[Sold Number]]) -> 79.675 | N17: =SUMIF(Table228[[#All],[Asset]],Table228[[#This Row],[Asset]],Table228[[#All],[Bought amount]]) -> 22897.17 | O17: =SUMIF(Table228[[#All],[Asset]],Table228[[#This Row],[Asset]],Table228[[#All],[Sold amount]]) -> 11736.941 | P17: =Table228[[#This Row],[Total bought Amount]]/Table228[[#This Row],[Total bought Number]] -> 147.79366 | Q17: =IFERROR(Table228[[#This Row],[Total Sold Amount]]/Table228[[#This Row],[Total Sold Number]],0) -> 147.31021 | R17: =Table228[[#This Row],[Total bought Number]]-Table228[[#This Row],[Total Sold Number]] -> 75.2516 | S17: =(Table228[[#This Row],[Ave exit price]]-Table228[[#This Row],[Ave Entry price]])*Table228[[#This Row],[Total Sold Number]] -> -38.51938 | T17: =(Table228[[#This Row],[Current Price]]-Table228[[#This Row],[Ave Entry price]])*Table228[[#This Row],[How many tokens now]] -> 1671.0622 | U17: =VLOOKUP(Table228[[#This Row],[Asset]],Table26[#All],10,FALSE) -> 170
A18: PYTH | B18: 45292 | C18: Staked | D18: Pyth Network | E18: Phantom 2 | F18: 0.35 | G18: 10000 | H18: =IF(G18>0,G18,0) -> 10000 | I18: =IF(G18<0,ABS(G18),0) -> 0 | J18: =H18*F18 -> 3500 | K18: =I18*F18 -> 0 | L18: =SUMIF(Table228[[#All],[Asset]],Table228[[#This Row],[Asset]],Table228[[#All],[Bought number]]) -> 34194.468 | M18: =SUMIF(Table228[[#All],[Asset]],Table228[[#This Row],[Asset]],Table228[[#All],[Sold Number]]) -> 34195.061 | N18: =SUMIF(Table228[[#All],[Asset]],Table228[[#This Row],[Asset]],Table228[[#All],[Bought amount]]) -> 8337.2121 | O18: =SUMIF(Table228[[#All],[Asset]],Table228[[#This Row],[Asset]],Table228[[#All],[Sold amount]]) -> 4877.1258 | P18: =Table228[[#This Row],[Total bought Amount]]/Table228[[#This Row],[Total bought Number]] -> 0.24381757 | Q18: =IFERROR(Table228[[#This Row],[Total Sold Amount]]/Table228[[#This Row],[Total Sold Number]],0) -> 0.14262661 | R18: =Table228[[#This Row],[Total bought Number]]-Table228[[#This Row],[Total Sold Number]] -> -0.593187 | S18: =(Table228[[#This Row],[Ave exit price]]-Table228[[#This Row],[Ave Entry price]])*Table228[[#This Row],[Total Sold Number]] -> -3460.231 | T18: =(Table228[[#This Row],[Current Price]]-Table228[[#This Row],[Ave Entry price]])*Table228[[#This Row],[How many tokens now]] -> 0.037855753 | U18: =VLOOKUP(Table228[[#This Row],[Asset]],Table26[#All],10,FALSE) -> 0.18
A19: JUP | B19: 45292 | C19: Staked | D19: Jupiter | E19: Phantom 2 | F19: 0.692 | G19: 1000 | H19: =IF(G19>0,G19,0) -> 1000 | I19: =IF(G19<0,ABS(G19),0) -> 0 | J19: =H19*F19 -> 692 | K19: =I19*F19 -> 0 | L19: =SUMIF(Table228[[#All],[Asset]],Table228[[#This Row],[Asset]],Table228[[#All],[Bought number]]) -> 1000 | M19: =SUMIF(Table228[[#All],[Asset]],Table228[[#This Row],[Asset]],Table228[[#All],[Sold Number]]) -> 0 | N19: =SUMIF(Table228[[#All],[Asset]],Table228[[#This Row],[Asset]],Table228[[#All],[Bought amount]]) -> 692 | O19: =SUMIF(Table228[[#All],[Asset]],Table228[[#This Row],[Asset]],Table228[[#All],[Sold amount]]) -> 0 | P19: =Table228[[#This Row],[Total bought Amount]]/Table228[[#This Row],[Total bought Number]] -> 0.692 | Q19: =IFERROR(Table228[[#This Row],[Total Sold Amount]]/Table228[[#This Row],[Total Sold Number]],0) -> 0 | R19: =Table228[[#This Row],[Total bought Number]]-Table228[[#This Row],[Total Sold Number]] -> 1000 | S19: =(Table228[[#This Row],[Ave exit price]]-Table228[[#This Row],[Ave Entry price]])*Table228[[#This Row],[Total Sold Number]] -> 0 | T19: =(Table228[[#This Row],[Current Price]]-Table228[[#This Row],[Ave Entry price]])*Table228[[#This Row],[How many tokens now]] -> -2 | U19: =VLOOKUP(Table228[[#This Row],[Asset]],Table26[#All],10,FALSE) -> 0.69
A20: SOL | B20: 45444 | C20: Sol/vSOL LP | D20: Meteora | E20: Phantom 2 | F20: 150 | G20: 10.72 | H20: =IF(G20>0,G20,0) -> 10.72 | I20: =IF(G20<0,ABS(G20),0) -> 0 | J20: =H20*F20 -> 1608 | K20: =I20*F20 -> 0 | L20: =SUMIF(Table228[[#All],[Asset]],Table228[[#This Row],[Asset]],Table228[[#All],[Bought number]]) -> 154.9266 | M20: =SUMIF(Table228[[#All],[Asset]],Table228[[#This Row],[Asset]],Table228[[#All],[Sold Number]]) -> 79.675 | N20: =SUMIF(Table228[[#All],[Asset]],Table228[[#This Row],[Asset]],Table228[[#All],[Bought amount]]) -> 22897.17 | O20: =SUMIF(Table228[[#All],[Asset]],Table228[[#This Row],[Asset]],Table228[[#All],[Sold amount]]) -> 11736.941 | P20: =Table228[[#This Row],[Total bought Amount]]/Table228[[#This Row],[Total bought Number]] -> 147.79366 | Q20: =IFERROR(Table228[[#This Row],[Total Sold Amount]]/Table228[[#This Row],[Total Sold Number]],0) -> 147.31021 | R20: =Table228[[#This Row],[Total bought Number]]-Table228[[#This Row],[Total Sold Number]] -> 75.2516 | S20: =(Table228[[#This Row],[Ave exit price]]-Table228[[#This Row],[Ave Entry price]])*Table228[[#This Row],[Total Sold Number]] -> -38.51938 | T20: =(Table228[[#This Row],[Current Price]]-Table228[[#This Row],[Ave Entry price]])*Table228[[#This Row],[How many tokens now]] -> 1671.0622 | U20: =VLOOKUP(Table228[[#This Row],[Asset]],Table26[#All],10,FALSE) -> 170
A21: Sol/Wen | B21: 45292 | C21: LP | D21: Meteora | E21: Phantom 2 | F21: 520.35 | G21: 1 | H21: =IF(G21>0,G21,0) -> 1 | I21: =IF(G21<0,ABS(G21),0) -> 0 | J21: =H21*F21 -> 520.35 | K21: =I21*F21 -> 0 | L21: =SUMIF(Table228[[#All],[Asset]],Table228[[#This Row],[Asset]],Table228[[#All],[Bought number]]) -> 1 | M21: =SUMIF(Table228[[#All],[Asset]],Table228[[#This Row],[Asset]],Table228[[#All],[Sold Number]]) -> 1 | N21: =SUMIF(Table228[[#All],[Asset]],Table228[[#This Row],[Asset]],Table228[[#All],[Bought amount]]) -> 520.35 | O21: =SUMIF(Table228[[#All],[Asset]],Table228[[#This Row],[Asset]],Table228[[#All],[Sold amount]]) -> 924.12 | P21: =Table228[[#This Row],[Total bought Amount]]/Table228[[#This Row],[Total bought Number]] -> 520.35 | Q21: =IFERROR(Table228[[#This Row],[Total Sold Amount]]/Table228[[#This Row],[Total Sold Number]],0) -> 924.12 | R21: =Table228[[#This Row],[Total bought Number]]-Table228[[#This Row],[Total Sold Number]] -> 0 | S21: =(Table228[[#This Row],[Ave exit price]]-Table228[[#This Row],[Ave Entry price]])*Table228[[#This Row],[Total Sold Number]] -> 403.77 | T21: =(Table228[[#This Row],[Current Price]]-Table228[[#This Row],[Ave Entry price]])*Table228[[#This Row],[How many tokens now]] -> 0 | U21: =VLOOKUP(Table228[[#This Row],[Asset]],Table26[#All],10,FALSE) -> 520.35
A22: Ray/Sol | B22: 45292 | C22: LP | D22: Raydium | E22: Phantom 2 | F22: 393.32 | G22: 1 | H22: =IF(G22>0,G22,0) -> 1 | I22: =IF(G22<0,ABS(G22),0) -> 0 | J22: =H22*F22 -> 393.32 | K22: =I22*F22 -> 0 | L22: =SUMIF(Table228[[#All],[Asset]],Table228[[#This Row],[Asset]],Table228[[#All],[Bought number]]) -> 1 | M22: =SUMIF(Table228[[#All],[Asset]],Table228[[#This Row],[Asset]],Table228[[#All],[Sold Number]]) -> 0 | N22: =SUMIF(Table228[[#All],[Asset]],Table228[[#This Row],[Asset]],Table228[[#All],[Bought amount]]) -> 393.32 | O22: =SUMIF(Table228[[#All],[Asset]],Table228[[#This Row],[Asset]],Table228[[#All],[Sold amount]]) -> 0 | P22: =Table228[[#This Row],[Total bought Amount]]/Table228[[#This Row],[Total bought Number]] -> 393.32 | Q22: =IFERROR(Table228[[#This Row],[Total Sold Amount]]/Table228[[#This Row],[Total Sold Number]],0) -> 0 | R22: =Table228[[#This Row],[Total bought Number]]-Table228[[#This Row],[Total Sold Number]] -> 1 | S22: =(Table228[[#This Row],[Ave exit price]]-Table228[[#This Row],[Ave Entry price]])*Table228[[#This Row],[Total Sold Number]] -> 0 | T22: =(Table228[[#This Row],[Current Price]]-Table228[[#This Row],[Ave Entry price]])*Table228[[#This Row],[How many tokens now]] -> 0 | U22: =VLOOKUP(Table228[[#This Row],[Asset]],Table26[#All],10,FALSE) -> 393.32
A23: Drift | B23: 45444 | C23: Staked | D23: Drift | E23: Phantom 2 | F23: 0.44 | G23: 2307 | H23: =IF(G23>0,G23,0) -> 2307 | I23: =IF(G23<0,ABS(G23),0) -> 0 | J23: =H23*F23 -> 1015.08 | K23: =I23*F23 -> 0 | L23: =SUMIF(Table228[[#All],[Asset]],Table228[[#This Row],[Asset]],Table228[[#All],[Bought number]]) -> 2307 | M23: =SUMIF(Table228[[#All],[Asset]],Table228[[#This Row],[Asset]],Table228[[#All],[Sold Number]]) -> 2307 | N23: =SUMIF(Table228[[#All],[Asset]],Table228[[#This Row],[Asset]],Table228[[#All],[Bought amount]]) -> 1015.08 | O23: =SUMIF(Table228[[#All],[Asset]],Table228[[#This Row],[Asset]],Table228[[#All],[Sold amount]]) -> 412.83765 | P23: =Table228[[#This Row],[Total bought Amount]]/Table228[[#This Row],[Total bought Number]] -> 0.44 | Q23: =IFERROR(Table228[[#This Row],[Total Sold Amount]]/Table228[[#This Row],[Total Sold Number]],0) -> 0.17895 | R23: =Table228[[#This Row],[Total bought Number]]-Table228[[#This Row],[Total Sold Number]] -> 0 | S23: =(Table228[[#This Row],[Ave exit price]]-Table228[[#This Row],[Ave Entry price]])*Table228[[#This Row],[Total Sold Number]] -> -602.24235 | T23: =(Table228[[#This Row],[Current Price]]-Table228[[#This Row],[Ave Entry price]])*Table228[[#This Row],[How many tokens now]] -> 0 | U23: =VLOOKUP(Table228[[#This Row],[Asset]],Table26[#All],10,FALSE) -> 0.44
... A60: SOL | B60: 45487 | C60: Spot | D60: Wallet | E60: Iphone wallet | F60: 150 | G60: -1.5 | H60: =IF(G60>0,G60,0) -> 0 | I60: =IF(G60<0,ABS(G60),0) -> 1.5 | J60: =H60*F60 -> 0 | K60: =I60*F60 -> 225 | L60: =SUMIF(Table228[[#All],[Asset]],Table228[[#This Row],[Asset]],Table228[[#All],[Bought number]]) -> 154.9266 | M60: =SUMIF(Table228[[#All],[Asset]],Table228[[#This Row],[Asset]],Table228[[#All],[Sold Number]]) -> 79.675 | N60: =SUMIF(Table228[[#All],[Asset]],Table228[[#This Row],[Asset]],Table228[[#All],[Bought amount]]) -> 22897.17 | O60: =SUMIF(Table228[[#All],[Asset]],Table228[[#This Row],[Asset]],Table228[[#All],[Sold amount]]) -> 11736.941 | P60: =Table228[[#This Row],[Total bought Amount]]/Table228[[#This Row],[Total bought Number]] -> 147.79366 | Q60: =IFERROR(Table228[[#This Row],[Total Sold Amount]]/Table228[[#This Row],[Total Sold Number]],0) -> 147.31021 | R60: =Table228[[#This Row],[Total bought Number]]-Table228[[#This Row],[Total Sold Number]] -> 75.2516 | S60: =(Table228[[#This Row],[Ave exit price]]-Table228[[#This Row],[Ave Entry price]])*Table228[[#This Row],[Total Sold Number]] -> -38.51938 | T60: =(Table228[[#This Row],[Current Price]]-Table228[[#This Row],[Ave Entry price]])*Table228[[#This Row],[How many tokens now]] -> 1671.0622 | U60: =VLOOKUP(Table228[[#This Row],[Asset]],Table26[#All],10,FALSE) -> 170
A61: SEND | B61: 45487 | C61: Spot | D61: Wallet | E61: Iphone wallet | F61: =150*1.5/Table228[[#This Row],[Number]] -> 0.0079155673 | G61: 28425 | H61: =IF(G61>0,G61,0) -> 28425 | I61: =IF(G61<0,ABS(G61),0) -> 0 | J61: =H61*F61 -> 225 | K61: =I61*F61 -> 0 | L61: =SUMIF(Table228[[#All],[Asset]],Table228[[#This Row],[Asset]],Table228[[#All],[Bought number]]) -> 798337.87 | M61: =SUMIF(Table228[[#All],[Asset]],Table228[[#This Row],[Asset]],Table228[[#All],[Sold Number]]) -> 798338.04 | N61: =SUMIF(Table228[[#All],[Asset]],Table228[[#This Row],[Asset]],Table228[[#All],[Bought amount]]) -> 24349.581 | O61: =SUMIF(Table228[[#All],[Asset]],Table228[[#This Row],[Asset]],Table228[[#All],[Sold amount]]) -> 12344.863 | P61: =Table228[[#This Row],[Total bought Amount]]/Table228[[#This Row],[Total bought Number]] -> 0.030500346 | Q61: =IFERROR(Table228[[#This Row],[Total Sold Amount]]/Table228[[#This Row],[Total Sold Number]],0) -> 0.015463203 | R61: =Table228[[#This Row],[Total bought Number]]-Table228[[#This Row],[Total Sold Number]] -> -0.170261 | S61: =(Table228[[#This Row],[Ave exit price]]-Table228[[#This Row],[Ave Entry price]])*Table228[[#This Row],[Total Sold Number]] -> -12004.723 | T61: =(Table228[[#This Row],[Current Price]]-Table228[[#This Row],[Ave Entry price]])*Table228[[#This Row],[How many tokens now]] -> 0.0033201484 | U61: =VLOOKUP(Table228[[#This Row],[Asset]],Table26[#All],10,FALSE) -> 0.011
A62: Foxy | B62: 45488 | C62: Spot | D62: Wallet | E62: Phantom 2 | F62: 0.004 | G62: 16500 | H62: =IF(G62>0,G62,0) -> 16500 | I62: =IF(G62<0,ABS(G62),0) -> 0 | J62: =H62*F62 -> 66 | K62: =I62*F62 -> 0 | L62: =SUMIF(Table228[[#All],[Asset]],Table228[[#This Row],[Asset]],Table228[[#All],[Bought number]]) -> 16500 | M62: =SUMIF(Table228[[#All],[Asset]],Table228[[#This Row],[Asset]],Table228[[#All],[Sold Number]]) -> 0 | N62: =SUMIF(Table228[[#All],[Asset]],Table228[[#This Row],[Asset]],Table228[[#All],[Bought amount]]) -> 66 | O62: =SUMIF(Table228[[#All],[Asset]],Table228[[#This Row],[Asset]],Table228[[#All],[Sold amount]]) -> 0 | P62: =Table228[[#This Row],[Total bought Amount]]/Table228[[#This Row],[Total bought Number]] -> 0.004 | Q62: =IFERROR(Table228[[#This Row],[Total Sold Amount]]/Table228[[#This Row],[Total Sold Number]],0) -> 0 | R62: =Table228[[#This Row],[Total bought Number]]-Table228[[#This Row],[Total Sold Number]] -> 16500 | S62: =(Table228[[#This Row],[Ave exit price]]-Table228[[#This Row],[Ave Entry price]])*Table228[[#This Row],[Total Sold Number]] -> 0 | T62: =(Table228[[#This Row],[Current Price]]-Table228[[#This Row],[Ave Entry price]])*Table228[[#This Row],[How many tokens now]] -> -1.2705 | U62: =VLOOKUP(Table228[[#This Row],[Asset]],Table26[#All],10,FALSE) -> 0.003923
A63: MutantMon | B63: 45413 | C63: Spot | D63: Wallet | E63: MagicEden Wallet | F63: 180 | G63: 53 | H63: =IF(G63>0,G63,0) -> 53 | I63: =IF(G63<0,ABS(G63),0) -> 0 | J63: =H63*F63 -> 9540 | K63: =I63*F63 -> 0 | L63: =SUMIF(Table228[[#All],[Asset]],Table228[[#This Row],[Asset]],Table228[[#All],[Bought number]]) -> 54 | M63: =SUMIF(Table228[[#All],[Asset]],Table228[[#This Row],[Asset]],Table228[[#All],[Sold Number]]) -> 53 | N63: =SUMIF(Table228[[#All],[Asset]],Table228[[#This Row],[Asset]],Table228[[#All],[Bought amount]]) -> 9740 | O63: =SUMIF(Table228[[#All],[Asset]],Table228[[#This Row],[Asset]],Table228[[#All],[Sold amount]]) -> 3141 | P63: =Table228[[#This Row],[Total bought Amount]]/Table228[[#This Row],[Total bought Number]] -> 180.37037 | Q63: =IFERROR(Table228[[#This Row],[Total Sold Amount]]/Table228[[#This Row],[Total Sold Number]],0) -> 59.264151 | R63: =Table228[[#This Row],[Total bought Number]]-Table228[[#This Row],[Total Sold Number]] -> 1 | S63: =(Table228[[#This Row],[Ave exit price]]-Table228[[#This Row],[Ave Entry price]])*Table228[[#This Row],[Total Sold Number]] -> -6418.6296 | T63: =(Table228[[#This Row],[Current Price]]-Table228[[#This Row],[Ave Entry price]])*Table228[[#This Row],[How many tokens now]] -> -69.37037 | U63: =VLOOKUP(Table228[[#This Row],[Asset]],Table26[#All],10,FALSE) -> 111
A64: Flash Trade | B64: 45413 | C64: Spot | D64: Wallet | E64: MagicEden Wallet | F64: 700 | G64: 2 | H64: =IF(G64>0,G64,0) -> 2 | I64: =IF(G64<0,ABS(G64),0) -> 0 | J64: =H64*F64 -> 1400 | K64: =I64*F64 -> 0 | L64: =SUMIF(Table228[[#All],[Asset]],Table228[[#This Row],[Asset]],Table228[[#All],[Bought number]]) -> 6 | M64: =SUMIF(Table228[[#All],[Asset]],Table228[[#This Row],[Asset]],Table228[[#All],[Sold Number]]) -> 6 | N64: =SUMIF(Table228[[#All],[Asset]],Table228[[#This Row],[Asset]],Table228[[#All],[Bought amount]]) -> 5550 | O64: =SUMIF(Table228[[#All],[Asset]],Table228[[#This Row],[Asset]],Table228[[#All],[Sold amount]]) -> 609 | P64: =Table228[[#This Row],[Total bought Amount]]/Table228[[#This Row],[Total bought Number]] -> 925 | Q64: =IFERROR(Table228[[#This Row],[Total Sold Amount]]/Table228[[#This Row],[Total Sold Number]],0) -> 101.5 | R64: =Table228[[#This Row],[Total bought Number]]-Table228[[#This Row],[Total Sold Number]] -> 0 | S64: =(Table228[[#This Row],[Ave exit price]]-Table228[[#This Row],[Ave Entry price]])*Table228[[#This Row],[Total Sold Number]] -> -4941 | T64: =(Table228[[#This Row],[Current Price]]-Table228[[#This Row],[Ave Entry price]])*Table228[[#This Row],[How many tokens now]] -> 0 | U64: =VLOOKUP(Table228[[#This Row],[Asset]],Table26[#All],10,FALSE) -> 710
A65: Frogana | B65: 45474 | C65: Spot | D65: Wallet | E65: MagicEden Wallet | F65: 80 | G65: 4 | H65: =IF(G65>0,G65,0) -> 4 | I65: =IF(G65<0,ABS(G65),0) -> 0 | J65: =H65*F65 -> 320 | K65: =I65*F65 -> 0 | L65: =SUMIF(Table228[[#All],[Asset]],Table228[[#This Row],[Asset]],Table228[[#All],[Bought number]]) -> 4 | M65: =SUMIF(Table228[[#All],[Asset]],Table228[[#This Row],[Asset]],Table228[[#All],[Sold Number]]) -> 4 | N65: =SUMIF(Table228[[#All],[Asset]],Table228[[#This Row],[Asset]],Table228[[#All],[Bought amount]]) -> 320 | O65: =SUMIF(Table228[[#All],[Asset]],Table228[[#This Row],[Asset]],Table228[[#All],[Sold amount]]) -> 788 | P65: =Table228[[#This Row],[Total bought Amount]]/Table228[[#This Row],[Total bought Number]] -> 80 | Q65: =IFERROR(Table228[[#This Row],[Total Sold Amount]]/Table228[[#This Row],[Total Sold Number]],0) -> 197 | R65: =Table228[[#This Row],[Total bought Number]]-Table228[[#This Row],[Total Sold Number]] -> 0 | S65: =(Table228[[#This Row],[Ave exit price]]-Table228[[#This Row],[Ave Entry price]])*Table228[[#This Row],[Total Sold Number]] -> 468 | T65: =(Table228[[#This Row],[Current Price]]-Table228[[#This Row],[Ave Entry price]])*Table228[[#This Row],[How many tokens now]] -> 0 | U65: =VLOOKUP(Table228[[#This Row],[Asset]],Table26[#All],10,FALSE) -> 287
A66: Node Aliens | B66: 45413 | C66: Spot | D66: Wallet | E66: MagicEden Wallet | F66: 30 | G66: 70 | H66: =IF(G66>0,G66,0) -> 70 | I66: =IF(G66<0,ABS(G66),0) -> 0 | J66: =H66*F66 -> 2100 | K66: =I66*F66 -> 0 | L66: =SUMIF(Table228[[#All],[Asset]],Table228[[#This Row],[Asset]],Table228[[#All],[Bought number]]) -> 88 | M66: =SUMIF(Table228[[#All],[Asset]],Table228[[#This Row],[Asset]],Table228[[#All],[Sold Number]]) -> 88 | N66: =SUMIF(Table228[[#All],[Asset]],Table228[[#This Row],[Asset]],Table228[[#All],[Bought amount]]) -> 2640 | O66: =SUMIF(Table228[[#All],[Asset]],Table228[[#This Row],[Asset]],Table228[[#All],[Sold amount]]) -> 88 | P66: =Table228[[#This Row],[Total bought Amount]]/Table228[[#This Row],[Total bought Number]] -> 30 | Q66: =IFERROR(Table228[[#This Row],[Total Sold Amount]]/Table228[[#This Row],[Total Sold Number]],0) -> 1 | R66: =Table228[[#This Row],[Total bought Number]]-Table228[[#This Row],[Total Sold Number]] -> 0 | S66: =(Table228[[#This Row],[Ave exit price]]-Table228[[#This Row],[Ave Entry price]])*Table228[[#This Row],[Total Sold Number]] -> -2552 | T66: =(Table228[[#This Row],[Current Price]]-Table228[[#This Row],[Ave Entry price]])*Table228[[#This Row],[How many tokens now]] -> 0 | U66: =VLOOKUP(Table228[[#This Row],[Asset]],Table26[#All],10,FALSE) -> 2.84
A67: BAT APE | B67: 45352 | C67: Spot | D67: Wallet | E67: MagicEden Wallet | F67: 50 | G67: 5 | H67: =IF(G67>0,G67,0) -> 5 | I67: =IF(G67<0,ABS(G67),0) -> 0 | J67: =H67*F67 -> 250 | K67: =I67*F67 -> 0 | L67: =SUMIF(Table228[[#All],[Asset]],Table228[[#This Row],[Asset]],Table228[[#All],[Bought number]]) -> 5 | M67: =SUMIF(Table228[[#All],[Asset]],Table228[[#This Row],[Asset]],Table228[[#All],[Sold Number]]) -> 5 | N67: =SUMIF(Table228[[#All],[Asset]],Table228[[#This Row],[Asset]],Table228[[#All],[Bought amount]]) -> 250 | O67: =SUMIF(Table228[[#All],[Asset]],Table228[[#This Row],[Asset]],Table228[[#All],[Sold amount]]) -> 15 | P67: =Table228[[#This Row],[Total bought Amount]]/Table228[[#This Row],[Total bought Number]] -> 50 | Q67: =IFERROR(Table228[[#This Row],[Total Sold Amount]]/Table228[[#This Row],[Total Sold Number]],0) -> 3 | R67: =Table228[[#This Row],[Total bought Number]]-Table228[[#This Row],[Total Sold Number]] -> 0 | S67: =(Table228[[#This Row],[Ave exit price]]-Table228[[#This Row],[Ave Entry price]])*Table228[[#This Row],[Total Sold Number]] -> -235 | T67: =(Table228[[#This Row],[Current Price]]-Table228[[#This Row],[Ave Entry price]])*Table228[[#This Row],[How many tokens now]] -> 0 | U67: =VLOOKUP(Table228[[#This Row],[Asset]],Table26[#All],10,FALSE) -> 28.4
A68: Orcanaut | B68: 45352 | C68: Spot | D68: Wallet | E68: MagicEden Wallet | F68: 20 | G68: 1 | H68: =IF(G68>0,G68,0) -> 1 | I68: =IF(G68<0,ABS(G68),0) -> 0 | J68: =H68*F68 -> 20 | K68: =I68*F68 -> 0 | L68: =SUMIF(Table228[[#All],[Asset]],Table228[[#This Row],[Asset]],Table228[[#All],[Bought number]]) -> 1 | M68: =SUMIF(Table228[[#All],[Asset]],Table228[[#This Row],[Asset]],Table228[[#All],[Sold Number]]) -> 0 | N68: =SUMIF(Table228[[#All],[Asset]],Table228[[#This Row],[Asset]],Table228[[#All],[Bought amount]]) -> 20 | O68: =SUMIF(Table228[[#All],[Asset]],Table228[[#This Row],[Asset]],Table228[[#All],[Sold amount]]) -> 0 | P68: =Table228[[#This Row],[Total bought Amount]]/Table228[[#This Row],[Total bought Number]] -> 20 | Q68: =IFERROR(Table228[[#This Row],[Total Sold Amount]]/Table228[[#This Row],[Total Sold Number]],0) -> 0 | R68: =Table228[[#This Row],[Total bought Number]]-Table228[[#This Row],[Total Sold Number]] -> 1 | S68: =(Table228[[#This Row],[Ave exit price]]-Table228[[#This Row],[Ave Entry price]])*Table228[[#This Row],[Total Sold Number]] -> 0 | T68: =(Table228[[#This Row],[Current Price]]-Table228[[#This Row],[Ave Entry price]])*Table228[[#This Row],[How many tokens now]] -> 0 | U68: =VLOOKUP(Table228[[#This Row],[Asset]],Table26[#All],10,FALSE) -> 20
A69: BAT | B69: 45292 | C69: Spot | D69: Wallet | E69: Defi wallet | F69: 0.3 | G69: 11974.37 | H69: =IF(G69>0,G69,0) -> 11974.37 | I69: =IF(G69<0,ABS(G69),0) -> 0 | J69: =H69*F69 -> 3592.3109 | K69: =I69*F69 -> 0 | L69: =SUMIF(Table228[[#All],[Asset]],Table228[[#This Row],[Asset]],Table228[[#All],[Bought number]]) -> 12514.37 | M69: =SUMIF(Table228[[#All],[Asset]],Table228[[#This Row],[Asset]],Table228[[#All],[Sold Number]]) -> 12514.37 | N69: =SUMIF(Table228[[#All],[Asset]],Table228[[#This Row],[Asset]],Table228[[#All],[Bought amount]]) -> 3683.2523 | O69: =SUMIF(Table228[[#All],[Asset]],Table228[[#This Row],[Asset]],Table228[[#All],[Sold amount]]) -> 2365.2159 | P69: =Table228[[#This Row],[Total bought Amount]]/Table228[[#This Row],[Total bought Number]] -> 0.29432184 | Q69: =IFERROR(Table228[[#This Row],[Total Sold Amount]]/Table228[[#This Row],[Total Sold Number]],0) -> 0.189 | R69: =Table228[[#This Row],[Total bought Number]]-Table228[[#This Row],[Total Sold Number]] -> 0 | S69: =(Table228[[#This Row],[Ave exit price]]-Table228[[#This Row],[Ave Entry price]])*Table228[[#This Row],[Total Sold Number]] -> -1318.0364 | T69: =(Table228[[#This Row],[Current Price]]-Table228[[#This Row],[Ave Entry price]])*Table228[[#This Row],[How many tokens now]] -> 0 | U69: =VLOOKUP(Table228[[#This Row],[Asset]],Table26[#All],10,FALSE) -> 0.1925
A70: ZK | B70: 45474 | C70: Spot | D70: Wallet | E70: Defi wallet | F70: 0 | G70: 2975 | H70: =IF(G70>0,G70,0) -> 2975 | I70: =IF(G70<0,ABS(G70),0) -> 0 | J70: =H70*F70 -> 0 | K70: =I70*F70 -> 0 | L70: =SUMIF(Table228[[#All],[Asset]],Table228[[#This Row],[Asset]],Table228[[#All],[Bought number]]) -> 2975 | M70: =SUMIF(Table228[[#All],[Asset]],Table228[[#This Row],[Asset]],Table228[[#All],[Sold Number]]) -> 2975 | N70: =SUMIF(Table228[[#All],[Asset]],Table228[[#This Row],[Asset]],Table228[[#All],[Bought amount]]) -> 0 | O70: =SUMIF(Table228[[#All],[Asset]],Table228[[#This Row],[Asset]],Table228[[#All],[Sold amount]]) -> 404.6 | P70: =Table228[[#This Row],[Total bought Amount]]/Table228[[#This Row],[Total bought Number]] -> 0 | Q70: =IFERROR(Table228[[#This Row],[Total Sold Amount]]/Table228[[#This Row],[Total Sold Number]],0) -> 0.136 | R70: =Table228[[#This Row],[Total bought Number]]-Table228[[#This Row],[Total Sold Number]] -> 0 | S70: =(Table228[[#This Row],[Ave exit price]]-Table228[[#This Row],[Ave Entry price]])*Table228[[#This Row],[Total Sold Number]] -> 404.6 | T70: =(Table228[[#This Row],[Current Price]]-Table228[[#This Row],[Ave Entry price]])*Table228[[#This Row],[How many tokens now]] -> 0 | U70: =VLOOKUP(Table228[[#This Row],[Asset]],Table26[#All],10,FALSE) -> 0.17
A71: ETH | B71: 45292 | C71: Spot | D71: Wallet | E71: Defi wallet | F71: 2500 | G71: =0.05+0.0264+0.0164+0.0164+0.009+0.007+0.0056+0.0049+0.003+0.00299 -> 0.14169 | H71: =IF(G71>0,G71,0) -> 0.14169 | I71: =IF(G71<0,ABS(G71),0) -> 0 | J71: =H71*F71 -> 354.225 | K71: =I71*F71 -> 0 | L71: =SUMIF(Table228[[#All],[Asset]],Table228[[#This Row],[Asset]],Table228[[#All],[Bought number]]) -> 0.14169 | M71: =SUMIF(Table228[[#All],[Asset]],Table228[[#This Row],[Asset]],Table228[[#All],[Sold Number]]) -> 0 | N71: =SUMIF(Table228[[#All],[Asset]],Table228[[#This Row],[Asset]],Table228[[#All],[Bought amount]]) -> 354.225 | O71: =SUMIF(Table228[[#All],[Asset]],Table228[[#This Row],[Asset]],Table228[[#All],[Sold amount]]) -> 0 | P71: =Table228[[#This Row],[Total bought Amount]]/Table228[[#This Row],[Total bought Number]] -> 2500 | Q71: =IFERROR(Table228[[#This Row],[Total Sold Amount]]/Table228[[#This Row],[Total Sold Number]],0) -> 0 | R71: =Table228[[#This Row],[Total bought Number]]-Table228[[#This Row],[Total Sold Number]] -> 0.14169 | S71: =(Table228[[#This Row],[Ave exit price]]-Table228[[#This Row],[Ave Entry price]])*Table228[[#This Row],[Total Sold Number]] -> 0 | T71: =(Table228[[#This Row],[Current Price]]-Table228[[#This Row],[Ave Entry price]])*Table228[[#This Row],[How many tokens now]] -> 123.41199 | U71: =VLOOKUP(Table228[[#This Row],[Asset]],Table26[#All],10,FALSE) -> 3371
A72: Aero | B72: 45292 | C72: Staked | D72: Wallet | E72: Defi wallet | F72: 0.1 | G72: 1848.3562 | H72: =IF(G72>0,G72,0) -> 1848.3562 | I72: =IF(G72<0,ABS(G72),0) -> 0 | J72: =H72*F72 -> 184.83562 | K72: =I72*F72 -> 0 | L72: =SUMIF(Table228[[#All],[Asset]],Table228[[#This Row],[Asset]],Table228[[#All],[Bought number]]) -> 1848.3562 | M72: =SUMIF(Table228[[#All],[Asset]],Table228[[#This Row],[Asset]],Table228[[#All],[Sold Number]]) -> 0 | N72: =SUMIF(Table228[[#All],[Asset]],Table228[[#This Row],[Asset]],Table228[[#All],[Bought amount]]) -> 184.83562 | O72: =SUMIF(Table228[[#All],[Asset]],Table228[[#This Row],[Asset]],Table228[[#All],[Sold amount]]) -> 0 | P72: =Table228[[#This Row],[Total bought Amount]]/Table228[[#This Row],[Total bought Number]] -> 0.1 | Q72: =IFERROR(Table228[[#This Row],[Total Sold Amount]]/Table228[[#This Row],[Total Sold Number]],0) -> 0 | R72: =Table228[[#This Row],[Total bought Number]]-Table228[[#This Row],[Total Sold Number]] -> 1848.3562 | S72: =(Table228[[#This Row],[Ave exit price]]-Table228[[#This Row],[Ave Entry price]])*Table228[[#This Row],[Total Sold Number]] -> 0 | T72: =(Table228[[#This Row],[Current Price]]-Table228[[#This Row],[Ave Entry price]])*Table228[[#This Row],[How many tokens now]] -> 1324.1624 | U72: =VLOOKUP(Table228[[#This Row],[Asset]],Table26[#All],10,FALSE) -> 0.8164
A73: Aero/USDC | B73: 45292 | C73: LP | D73: Wallet | E73: Defi wallet | F73: 346.57 | G73: 1 | H73: =IF(G73>0,G73,0) -> 1 | I73: =IF(G73<0,ABS(G73),0) -> 0 | J73: =H73*F73 -> 346.57 | K73: =I73*F73 -> 0 | L73: =SUMIF(Table228[[#All],[Asset]],Table228[[#This Row],[Asset]],Table228[[#All],[Bought number]]) -> 1 | M73: =SUMIF(Table228[[#All],[Asset]],Table228[[#This Row],[Asset]],Table228[[#All],[Sold Number]]) -> 0 | N73: =SUMIF(Table228[[#All],[Asset]],Table228[[#This Row],[Asset]],Table228[[#All],[Bought amount]]) -> 346.57 | O73: =SUMIF(Table228[[#All],[Asset]],Table228[[#This Row],[Asset]],Table228[[#All],[Sold amount]]) -> 0 | P73: =Table228[[#This Row],[Total bought Amount]]/Table228[[#This Row],[Total bought Number]] -> 346.57 | Q73: =IFERROR(Table228[[#This Row],[Total Sold Amount]]/Table228[[#This Row],[Total Sold Number]],0) -> 0 | R73: =Table228[[#This Row],[Total bought Number]]-Table228[[#This Row],[Total Sold Number]] -> 1 | S73: =(Table228[[#This Row],[Ave exit price]]-Table228[[#This Row],[Ave Entry price]])*Table228[[#This Row],[Total Sold Number]] -> 0 | T73: =(Table228[[#This Row],[Current Price]]-Table228[[#This Row],[Ave Entry price]])*Table228[[#This Row],[How many tokens now]] -> 0.1 | U73: =VLOOKUP(Table228[[#This Row],[Asset]],Table26[#All],10,FALSE) -> 346.67
A74: SNX | B74: 45292 | C74: Spot | D74: Wallet | E74: Defi wallet | F74: 1.75 | G74: 1115.7603 | H74: =IF(G74>0,G74,0) -> 1115.7603 | I74: =IF(G74<0,ABS(G74),0) -> 0 | J74: =H74*F74 -> 1952.5805 | K74: =I74*F74 -> 0 | L74: =SUMIF(Table228[[#All],[Asset]],Table228[[#This Row],[Asset]],Table228[[#All],[Bought number]]) -> 1115.7603 | M74: =SUMIF(Table228[[#All],[Asset]],Table228[[#This Row],[Asset]],Table228[[#All],[Sold Number]]) -> 667 | N74: =SUMIF(Table228[[#All],[Asset]],Table228[[#This Row],[Asset]],Table228[[#All],[Bought amount]]) -> 1952.5805 | O74: =SUMIF(Table228[[#All],[Asset]],Table228[[#This Row],[Asset]],Table228[[#All],[Sold amount]]) -> 901.6506 | P74: =Table228[[#This Row],[Total bought Amount]]/Table228[[#This Row],[Total bought Number]] -> 1.75 | Q74: =IFERROR(Table228[[#This Row],[Total Sold Amount]]/Table228[[#This Row],[Total Sold Number]],0) -> 1.3518 | R74: =Table228[[#This Row],[Total bought Number]]-Table228[[#This Row],[Total Sold Number]] -> 448.7603 | S74: =(Table228[[#This Row],[Ave exit price]]-Table228[[#This Row],[Ave Entry price]])*Table228[[#This Row],[Total Sold Number]] -> -265.5994 | T74: =(Table228[[#This Row],[Current Price]]-Table228[[#This Row],[Ave Entry price]])*Table228[[#This Row],[How many tokens now]] -> 58.338839 | U74: =VLOOKUP(Table228[[#This Row],[Asset]],Table26[#All],10,FALSE) -> 1.88
A75: Equal | B75: 45292 | C75: Staked | D75: Wallet | E75: Defi wallet | F75: 3 | G75: 241 | H75: =IF(G75>0,G75,0) -> 241 | I75: =IF(G75<0,ABS(G75),0) -> 0 | J75: =H75*F75 -> 723 | K75: =I75*F75 -> 0 | L75: =SUMIF(Table228[[#All],[Asset]],Table228[[#This Row],[Asset]],Table228[[#All],[Bought number]]) -> 241 | M75: =SUMIF(Table228[[#All],[Asset]],Table228[[#This Row],[Asset]],Table228[[#All],[Sold Number]]) -> 241 | N75: =SUMIF(Table228[[#All],[Asset]],Table228[[#This Row],[Asset]],Table228[[#All],[Bought amount]]) -> 723 | O75: =SUMIF(Table228[[#All],[Asset]],Table228[[#This Row],[Asset]],Table228[[#All],[Sold amount]]) -> 2282.27 | P75: =Table228[[#This Row],[Total bought Amount]]/Table228[[#This Row],[Total bought Number]] -> 3 | Q75: =IFERROR(Table228[[#This Row],[Total Sold Amount]]/Table228[[#This Row],[Total Sold Number]],0) -> 9.47 | R75: =Table228[[#This Row],[Total bought Number]]-Table228[[#This Row],[Total Sold Number]] -> 0 | S75: =(Table228[[#This Row],[Ave exit price]]-Table228[[#This Row],[Ave Entry price]])*Table228[[#This Row],[Total Sold Number]] -> 1559.27 | T75: =(Table228[[#This Row],[Current Price]]-Table228[[#This Row],[Ave Entry price]])*Table228[[#This Row],[How many tokens now]] -> 0 | U75: =VLOOKUP(Table228[[#This Row],[Asset]],Table26[#All],10,FALSE) -> 9.61
A76: VRTX | B76: 45352 | C76: Staked | D76: Wallet | E76: Defi wallet | F76: 0.1411 | G76: 7509.6361 | H76: =IF(G76>0,G76,0) -> 7509.6361 | I76: =IF(G76<0,ABS(G76),0) -> 0 | J76: =H76*F76 -> 1059.6097 | K76: =I76*F76 -> 0 | L76: =SUMIF(Table228[[#All],[Asset]],Table228[[#This Row],[Asset]],Table228[[#All],[Bought number]]) -> 56191.636 | M76: =SUMIF(Table228[[#All],[Asset]],Table228[[#This Row],[Asset]],Table228[[#All],[Sold Number]]) -> 56191 | N76: =SUMIF(Table228[[#All],[Asset]],Table228[[#This Row],[Asset]],Table228[[#All],[Bought amount]]) -> 5356.8114 | O76: =SUMIF(Table228[[#All],[Asset]],Table228[[#This Row],[Asset]],Table228[[#All],[Sold amount]]) -> 1466.328 | P76: =Table228[[#This Row],[Total bought Amount]]/Table228[[#This Row],[Total bought Number]] -> 0.095331117 | Q76: =IFERROR(Table228[[#This Row],[Total Sold Amount]]/Table228[[#This Row],[Total Sold Number]],0) -> 0.026095425 | R76: =Table228[[#This Row],[Total bought Number]]-Table228[[#This Row],[Total Sold Number]] -> 0.6361 | S76: =(Table228[[#This Row],[Ave exit price]]-Table228[[#This Row],[Ave Entry price]])*Table228[[#This Row],[Total Sold Number]] -> -3890.4228 | T76: =(Table228[[#This Row],[Current Price]]-Table228[[#This Row],[Ave Entry price]])*Table228[[#This Row],[How many tokens now]] -> -0.044737623 | U76: =VLOOKUP(Table228[[#This Row],[Asset]],Table26[#All],10,FALSE) -> 0.025
A77: Frogana | B77: 45488 | C77: Spot | D77: Wallet | E77: MagicEden Wallet | F77: 216 | G77: -3 | H77: =IF(G77>0,G77,0) -> 0 | I77: =IF(G77<0,ABS(G77),0) -> 3 | J77: =H77*F77 -> 0 | K77: =I77*F77 -> 648 | L77: =SUMIF(Table228[[#All],[Asset]],Table228[[#This Row],[Asset]],Table228[[#All],[Bought number]]) -> 4 | M77: =SUMIF(Table228[[#All],[Asset]],Table228[[#This Row],[Asset]],Table228[[#All],[Sold Number]]) -> 4 | N77: =SUMIF(Table228[[#All],[Asset]],Table228[[#This Row],[Asset]],Table228[[#All],[Bought amount]]) -> 320 | O77: =SUMIF(Table228[[#All],[Asset]],Table228[[#This Row],[Asset]],Table228[[#All],[Sold amount]]) -> 788 | P77: =Table228[[#This Row],[Total bought Amount]]/Table228[[#This Row],[Total bought Number]] -> 80 | Q77: =IFERROR(Table228[[#This Row],[Total Sold Amount]]/Table228[[#This Row],[Total Sold Number]],0) -> 197 | R77: =Table228[[#This Row],[Total bought Number]]-Table228[[#This Row],[Total Sold Number]] -> 0 | S77: =(Table228[[#This Row],[Ave exit price]]-Table228[[#This Row],[Ave Entry price]])*Table228[[#This Row],[Total Sold Number]] -> 468 | T77: =(Table228[[#This Row],[Current Price]]-Table228[[#This Row],[Ave Entry price]])*Table228[[#This Row],[How many tokens now]] -> 0 | U77: =VLOOKUP(Table228[[#This Row],[Asset]],Table26[#All],10,FALSE) -> 287
A78: Flash Trade | B78: 45484 | C78: Staked | D78: Wallet | E78: Phantom 2 | F78: 650 | G78: 1 | H78: =IF(G78>0,G78,0) -> 1 | I78: =IF(G78<0,ABS(G78),0) -> 0 | J78: =H78*F78 -> 650 | K78: =I78*F78 -> 0 | L78: =SUMIF(Table228[[#All],[Asset]],Table228[[#This Row],[Asset]],Table228[[#All],[Bought number]]) -> 6 | M78: =SUMIF(Table228[[#All],[Asset]],Table228[[#This Row],[Asset]],Table228[[#All],[Sold Number]]) -> 6 | N78: =SUMIF(Table228[[#All],[Asset]],Table228[[#This Row],[Asset]],Table228[[#All],[Bought amount]]) -> 5550 | O78: =SUMIF(Table228[[#All],[Asset]],Table228[[#This Row],[Asset]],Table228[[#All],[Sold amount]]) -> 609 | P78: =Table228[[#This Row],[Total bought Amount]]/Table228[[#This Row],[Total bought Number]] -> 925 | Q78: =IFERROR(Table228[[#This Row],[Total Sold Amount]]/Table228[[#This Row],[Total Sold Number]],0) -> 101.5 | R78: =Table228[[#This Row],[Total bought Number]]-Table228[[#This Row],[Total Sold Number]] -> 0 | S78: =(Table228[[#This Row],[Ave exit price]]-Table228[[#This Row],[Ave Entry price]])*Table228[[#This Row],[Total Sold Number]] -> -4941 | T78: =(Table228[[#This Row],[Current Price]]-Table228[[#This Row],[Ave Entry price]])*Table228[[#This Row],[How many tokens now]] -> 0 | U78: =VLOOKUP(Table228[[#This Row],[Asset]],Table26[#All],10,FALSE) -> 710
A79: FLP | B79: 45489 | C79: Staked | D79: Wallet | E79: MagicEden Wallet | F79: 0.96 | G79: 232.46 | H79: =IF(G79>0,G79,0) -> 232.46 | I79: =IF(G79<0,ABS(G79),0) -> 0 | J79: =H79*F79 -> 223.1616 | K79: =I79*F79 -> 0 | L79: =SUMIF(Table228[[#All],[Asset]],Table228[[#This Row],[Asset]],Table228[[#All],[Bought number]]) -> 3846.05 | M79: =SUMIF(Table228[[#All],[Asset]],Table228[[#This Row],[Asset]],Table228[[#All],[Sold Number]]) -> 3726.05 | N79: =SUMIF(Table228[[#All],[Asset]],Table228[[#This Row],[Asset]],Table228[[#All],[Bought amount]]) -> 3550.4902 | O79: =SUMIF(Table228[[#All],[Asset]],Table228[[#This Row],[Asset]],Table228[[#All],[Sold amount]]) -> 3828.3504 | P79: =Table228[[#This Row],[Total bought Amount]]/Table228[[#This Row],[Total bought Number]] -> 0.92315237 | Q79: =IFERROR(Table228[[#This Row],[Total Sold Amount]]/Table228[[#This Row],[Total Sold Number]],0) -> 1.0274554 | R79: =Table228[[#This Row],[Total bought Number]]-Table228[[#This Row],[Total Sold Number]] -> 120 | S79: =(Table228[[#This Row],[Ave exit price]]-Table228[[#This Row],[Ave Entry price]])*Table228[[#This Row],[Total Sold Number]] -> 388.63849 | T79: =(Table228[[#This Row],[Current Price]]-Table228[[#This Row],[Ave Entry price]])*Table228[[#This Row],[How many tokens now]] -> -2.7782841 | U79: =VLOOKUP(Table228[[#This Row],[Asset]],Table26[#All],10,FALSE) -> 0.9
